Workbook

Sheet MENU

Sheet ORÇAMENTO
C2: CUSTO TOTAL | D2: PREÇO SUGERIDO | E2: PREÇO A TRABALHAR | F2: PORCENTAGEM
C3: =SUM(D7:D1014) -> 0 | D3: =SUM(E7:E1014) -> 0 | E3: =SUM(G7:G1014) -> 0 | F3: 1
C4: MARKUP MEDIO | D4: =IF(D3=0,"",SUM(F7:F1014)/COUNT(F7:F1014))
A6: MARCA | B6: PRODUTO | C6: QUANTIDADE | D6: CUSTO | E6: PREÇO SUGERIDO | F6: MARKUP | G6: PREÇO A TRABALHAR
D7: =IF($B7="","",SUM(VLOOKUP($B7,DADOS!$C$2:$I1014,4,0)*$C7)) | E7: =IF($B7="","",SUM(VLOOKUP($B7,DADOS!$C$2:$I1014,6,0)*$C7)) | F7: =IF($E7="","",(VLOOKUP($B7,DADOS!$C$2:$I1014,7,0))) | G7: =IF(D7="","",D7*$F$3+D7)
A8: =IF($B8="","",VLOOKUP($B8,DADOS!$C$2:$I1014,2,0)) | D8: =IF($B8="","",SUM(VLOOKUP($B8,DADOS!$C$2:$I1014,4,0)*$C8)) | E8: =IF($B8="","",SUM(VLOOKUP($B8,DADOS!$C$2:$I1014,6,0)*$C8)) | F8: =IF($E8="","",(VLOOKUP($B8,DADOS!$C$2:$I1014,7,0))) | G8: =IF(D8="","",D8*$F$3+D8)
A9: =IF($B9="","",VLOOKUP($B9,DADOS!$C$2:$I1014,2,0)) | D9: =IF($B9="","",SUM(VLOOKUP($B9,DADOS!$C$2:$I1014,4,0)*$C9)) | E9: =IF($B9="","",SUM(VLOOKUP($B9,DADOS!$C$2:$I1014,6,0)*$C9)) | F9: =IF($E9="","",(VLOOKUP($B9,DADOS!$C$2:$I1014,7,0))) | G9: =IF(D9="","",D9*$F$3+D9)
A10: =IF($B10="","",VLOOKUP($B10,DADOS!$C$2:$I1014,2,0)) | D10: =IF($B10="","",SUM(VLOOKUP($B10,DADOS!$C$2:$I1014,4,0)*$C10)) | E10: =IF($B10="","",SUM(VLOOKUP($B10,DADOS!$C$2:$I1014,6,0)*$C10)) | F10: =IF($E10="","",(VLOOKUP($B10,DADOS!$C$2:$I1014,7,0))) | G10: =IF(D10="","",D10*$F$3+D10)
A11: =IF($B11="","",VLOOKUP($B11,DADOS!$C$2:$I1014,2,0)) | D11: =IF($B11="","",SUM(VLOOKUP($B11,DADOS!$C$2:$I1014,4,0)*$C11)) | E11: =IF($B11="","",SUM(VLOOKUP($B11,DADOS!$C$2:$I1014,6,0)*$C11)) | F11: =IF($E11="","",(VLOOKUP($B11,DADOS!$C$2:$I1014,7,0))) | G11: =IF(D11="","",D11*$F$3+D11)
A12: =IF($B12="","",VLOOKUP($B12,DADOS!$C$2:$I1014,2,0)) | D12: =IF($B12="","",SUM(VLOOKUP($B12,DADOS!$C$2:$I1014,4,0)*$C12)) | E12: =IF($B12="","",SUM(VLOOKUP($B12,DADOS!$C$2:$I1014,6,0)*$C12)) | F12: =IF($E12="","",(VLOOKUP($B12,DADOS!$C$2:$I1014,7,0))) | G12: =IF(D12="","",D12*$F$3+D12)
A13: =IF($B13="","",VLOOKUP($B13,DADOS!$C$2:$I1014,2,0)) | D13: =IF($B13="","",SUM(VLOOKUP($B13,DADOS!$C$2:$I1014,4,0)*$C13)) | E13: =IF($B13="","",SUM(VLOOKUP($B13,DADOS!$C$2:$I1014,6,0)*$C13)) | F13: =IF($E13="","",(VLOOKUP($B13,DADOS!$C$2:$I1014,7,0))) | G13: =IF(D13="","",D13*$F$3+D13)
A14: =IF($B14="","",VLOOKUP($B14,DADOS!$C$2:$I1014,2,0)) | D14: =IF($B14="","",SUM(VLOOKUP($B14,DADOS!$C$2:$I1014,4,0)*$C14)) | E14: =IF($B14="","",SUM(VLOOKUP($B14,DADOS!$C$2:$I1014,6,0)*$C14)) | F14: =IF($E14="","",(VLOOKUP($B14,DADOS!$C$2:$I1014,7,0))) | G14: =IF(D14="","",D14*$F$3+D14)
A15: =IF($B15="","",VLOOKUP($B15,DADOS!$C$2:$I1014,2,0)) | D15: =IF($B15="","",SUM(VLOOKUP($B15,DADOS!$C$2:$I1014,4,0)*$C15)) | E15: =IF($B15="","",SUM(VLOOKUP($B15,DADOS!$C$2:$I1014,6,0)*$C15)) | F15: =IF($E15="","",(VLOOKUP($B15,DADOS!$C$2:$I1014,7,0))) | G15: =IF(D15="","",D15*$F$3+D15)
A16: =IF($B16="","",VLOOKUP($B16,DADOS!$C$2:$I1014,2,0)) | D16: =IF($B16="","",SUM(VLOOKUP($B16,DADOS!$C$2:$I1014,4,0)*$C16)) | E16: =IF($B16="","",SUM(VLOOKUP($B16,DADOS!$C$2:$I1014,6,0)*$C16)) | F16: =IF($E16="","",(VLOOKUP($B16,DADOS!$C$2:$I1014,7,0))) | G16: =IF(D16="","",D16*$F$3+D16)
A17: =IF($B17="","",VLOOKUP($B17,DADOS!$C$2:$I1014,2,0)) | D17: =IF($B17="","",SUM(VLOOKUP($B17,DADOS!$C$2:$I1014,4,0)*$C17)) | E17: =IF($B17="","",SUM(VLOOKUP($B17,DADOS!$C$2:$I1014,6,0)*$C17)) | F17: =IF($E17="","",(VLOOKUP($B17,DADOS!$C$2:$I1014,7,0))) | G17: =IF(D17="","",D17*$F$3+D17)
A18: =IF($B18="","",VLOOKUP($B18,DADOS!$C$2:$I1014,2,0)) | D18: =IF($B18="","",SUM(VLOOKUP($B18,DADOS!$C$2:$I1014,4,0)*$C18)) | E18: =IF($B18="","",SUM(VLOOKUP($B18,DADOS!$C$2:$I1014,6,0)*$C18)) | F18: =IF($E18="","",(VLOOKUP($B18,DADOS!$C$2:$I1014,7,0))) | G18: =IF(D18="","",D18*$F$3+D18)
A19: =IF($B19="","",VLOOKUP($B19,DADOS!$C$2:$I1014,2,0)) | D19: =IF($B19="","",SUM(VLOOKUP($B19,DADOS!$C$2:$I1014,4,0)*$C19)) | E19: =IF($B19="","",SUM(VLOOKUP($B19,DADOS!$C$2:$I1014,6,0)*$C19)) | F19: =IF($E19="","",(VLOOKUP($B19,DADOS!$C$2:$I1014,7,0))) | G19: =IF(D19="","",D19*$F$3+D19)
A20: =IF($B20="","",VLOOKUP($B20,DADOS!$C$2:$I1014,2,0)) | D20: =IF($B20="","",SUM(VLOOKUP($B20,DADOS!$C$2:$I1014,4,0)*$C20)) | E20: =IF($B20="","",SUM(VLOOKUP($B20,DADOS!$C$2:$I1014,6,0)*$C20)) | F20: =IF($E20="","",(VLOOKUP($B20,DADOS!$C$2:$I1014,7,0))) | G20: =IF(D20="","",D20*$F$3+D20)
A21: =IF($B21="","",VLOOKUP($B21,DADOS!$C$2:$I1014,2,0)) | D21: =IF($B21="","",SUM(VLOOKUP($B21,DADOS!$C$2:$I1014,4,0)*$C21)) | E21: =IF($B21="","",SUM(VLOOKUP($B21,DADOS!$C$2:$I1014,6,0)*$C21)) | F21: =IF($E21="","",(VLOOKUP($B21,DADOS!$C$2:$I1014,7,0))) | G21: =IF(D21="","",D21*$F$3+D21)
A22: =IF($B22="","",VLOOKUP($B22,DADOS!$C$2:$I1014,2,0)) | D22: =IF($B22="","",SUM(VLOOKUP($B22,DADOS!$C$2:$I1014,4,0)*$C22)) | E22: =IF($B22="","",SUM(VLOOKUP($B22,DADOS!$C$2:$I1014,6,0)*$C22)) | F22: =IF($E22="","",(VLOOKUP($B22,DADOS!$C$2:$I1014,7,0))) | G22: =IF(D22="","",D22*$F$3+D22)
A23: =IF($B23="","",VLOOKUP($B23,DADOS!$C$2:$I1014,2,0)) | D23: =IF($B23="","",SUM(VLOOKUP($B23,DADOS!$C$2:$I1014,4,0)*$C23)) | E23: =IF($B23="","",SUM(VLOOKUP($B23,DADOS!$C$2:$I1014,6,0)*$C23)) | F23: =IF($E23="","",(VLOOKUP($B23,DADOS!$C$2:$I1014,7,0))) | G23: =IF(D23="","",D23*$F$3+D23)
A24: =IF($B24="","",VLOOKUP($B24,DADOS!$C$2:$I1014,2,0)) | D24: =IF($B24="","",SUM(VLOOKUP($B24,DADOS!$C$2:$I1014,4,0)*$C24)) | E24: =IF($B24="","",SUM(VLOOKUP($B24,DADOS!$C$2:$I1014,6,0)*$C24)) | F24: =IF($E24="","",(VLOOKUP($B24,DADOS!$C$2:$I1014,7,0))) | G24: =IF(D24="","",D24*$F$3+D24)
A25: =IF($B25="","",VLOOKUP($B25,DADOS!$C$2:$I1014,2,0)) | D25: =IF($B25="","",SUM(VLOOKUP($B25,DADOS!$C$2:$I1014,4,0)*$C25)) | E25: =IF($B25="","",SUM(VLOOKUP($B25,DADOS!$C$2:$I1014,6,0)*$C25)) | F25: =IF($E25="","",(VLOOKUP($B25,DADOS!$C$2:$I1014,7,0))) | G25: =IF(D25="","",D25*$F$3+D25)
A26: =IF($B26="","",VLOOKUP($B26,DADOS!$C$2:$I1014,2,0)) | D26: =IF($B26="","",SUM(VLOOKUP($B26,DADOS!$C$2:$I1014,4,0)*$C26)) | E26: =IF($B26="","",SUM(VLOOKUP($B26,DADOS!$C$2:$I1014,6,0)*$C26)) | F26: =IF($E26="","",(VLOOKUP($B26,DADOS!$C$2:$I1014,7,0))) | G26: =IF(D26="","",D26*$F$3+D26)
A27: =IF($B27="","",VLOOKUP($B27,DADOS!$C$2:$I1014,2,0)) | D27: =IF($B27="","",SUM(VLOOKUP($B27,DADOS!$C$2:$I1014,4,0)*$C27)) | E27: =IF($B27="","",SUM(VLOOKUP($B27,DADOS!$C$2:$I1014,6,0)*$C27)) | F27: =IF($E27="","",(VLOOKUP($B27,DADOS!$C$2:$I1014,7,0))) | G27: =IF(D27="","",D27*$F$3+D27)
A28: =IF($B28="","",VLOOKUP($B28,DADOS!$C$2:$I1014,2,0)) | D28: =IF($B28="","",SUM(VLOOKUP($B28,DADOS!$C$2:$I1014,4,0)*$C28)) | E28: =IF($B28="","",SUM(VLOOKUP($B28,DADOS!$C$2:$I1014,6,0)*$C28)) | F28: =IF($E28="","",(VLOOKUP($B28,DADOS!$C$2:$I1014,7,0))) | G28: =IF(D28="","",D28*$F$3+D28)
A29: =IF($B29="","",VLOOKUP($B29,DADOS!$C$2:$I1014,2,0)) | D29: =IF($B29="","",SUM(VLOOKUP($B29,DADOS!$C$2:$I1014,4,0)*$C29)) | E29: =IF($B29="","",SUM(VLOOKUP($B29,DADOS!$C$2:$I1014,6,0)*$C29)) | F29: =IF($E29="","",(VLOOKUP($B29,DADOS!$C$2:$I1014,7,0))) | G29: =IF(D29="","",D29*$F$3+D29)
A30: =IF($B30="","",VLOOKUP($B30,DADOS!$C$2:$I1014,2,0)) | D30: =IF($B30="","",SUM(VLOOKUP($B30,DADOS!$C$2:$I1014,4,0)*$C30)) | E30: =IF($B30="","",SUM(VLOOKUP($B30,DADOS!$C$2:$I1014,6,0)*$C30)) | F30: =IF($E30="","",(VLOOKUP($B30,DADOS!$C$2:$I1014,7,0))) | G30: =IF(D30="","",D30*$F$3+D30)
A31: =IF($B31="","",VLOOKUP($B31,DADOS!$C$2:$I1014,2,0)) | D31: =IF($B31="","",SUM(VLOOKUP($B31,DADOS!$C$2:$I1014,4,0)*$C31)) | E31: =IF($B31="","",SUM(VLOOKUP($B31,DADOS!$C$2:$I1014,6,0)*$C31)) | F31: =IF($E31="","",(VLOOKUP($B31,DADOS!$C$2:$I1014,7,0))) | G31: =IF(D31="","",D31*$F$3+D31)
A32: =IF($B32="","",VLOOKUP($B32,DADOS!$C$2:$I1014,2,0)) | D32: =IF($B32="","",SUM(VLOOKUP($B32,DADOS!$C$2:$I1014,4,0)*$C32)) | E32: =IF($B32="","",SUM(VLOOKUP($B32,DADOS!$C$2:$I1014,6,0)*$C32)) | F32: =IF($E32="","",(VLOOKUP($B32,DADOS!$C$2:$I1014,7,0))) | G32: =IF(D32="","",D32*$F$3+D32)
A33: =IF($B33="","",VLOOKUP($B33,DADOS!$C$2:$I1014,2,0)) | D33: =IF($B33="","",SUM(VLOOKUP($B33,DADOS!$C$2:$I1014,4,0)*$C33)) | E33: =IF($B33="","",SUM(VLOOKUP($B33,DADOS!$C$2:$I1014,6,0)*$C33)) | F33: =IF($E33="","",(VLOOKUP($B33,DADOS!$C$2:$I1014,7,0))) | G33: =IF(D33="","",D33*$F$3+D33)
A34: =IF($B34="","",VLOOKUP($B34,DADOS!$C$2:$I1014,2,0)) | D34: =IF($B34="","",SUM(VLOOKUP($B34,DADOS!$C$2:$I1014,4,0)*$C34)) | E34: =IF($B34="","",SUM(VLOOKUP($B34,DADOS!$C$2:$I1014,6,0)*$C34)) | F34: =IF($E34="","",(VLOOKUP($B34,DADOS!$C$2:$I1014,7,0))) | G34: =IF(D34="","",D34*$F$3+D34)
A35: =IF($B35="","",VLOOKUP($B35,DADOS!$C$2:$I1014,2,0)) | D35: =IF($B35="","",SUM(VLOOKUP($B35,DADOS!$C$2:$I1014,4,0)*$C35)) | E35: =IF($B35="","",SUM(VLOOKUP($B35,DADOS!$C$2:$I1014,6,0)*$C35)) | F35: =IF($E35="","",(VLOOKUP($B35,DADOS!$C$2:$I1014,7,0))) | G35: =IF(D35="","",D35*$F$3+D35)
A36: =IF($B36="","",VLOOKUP($B36,DADOS!$C$2:$I1014,2,0)) | D36: =IF($B36="","",SUM(VLOOKUP($B36,DADOS!$C$2:$I1014,4,0)*$C36)) | E36: =IF($B36="","",SUM(VLOOKUP($B36,DADOS!$C$2:$I1014,6,0)*$C36)) | F36: =IF($E36="","",(VLOOKUP($B36,DADOS!$C$2:$I1014,7,0))) | G36: =IF(D36="","",D36*$F$3+D36)
A37: =IF($B37="","",VLOOKUP($B37,DADOS!$C$2:$I1014,2,0)) | D37: =IF($B37="","",SUM(VLOOKUP($B37,DADOS!$C$2:$I1014,4,0)*$C37)) | E37: =IF($B37="","",SUM(VLOOKUP($B37,DADOS!$C$2:$I1014,6,0)*$C37)) | F37: =IF($E37="","",(VLOOKUP($B37,DADOS!$C$2:$I1014,7,0))) | G37: =IF(D37="","",D37*$F$3+D37)
A38: =IF($B38="","",VLOOKUP($B38,DADOS!$C$2:$I1014,2,0)) | D38: =IF($B38="","",SUM(VLOOKUP($B38,DADOS!$C$2:$I1014,4,0)*$C38)) | E38: =IF($B38="","",SUM(VLOOKUP($B38,DADOS!$C$2:$I1014,6,0)*$C38)) | F38: =IF($E38="","",(VLOOKUP($B38,DADOS!$C$2:$I1014,7,0))) | G38: =IF(D38="","",D38*$F$3+D38)
A39: =IF($B39="","",VLOOKUP($B39,DADOS!$C$2:$I1014,2,0)) | D39: =IF($B39="","",SUM(VLOOKUP($B39,DADOS!$C$2:$I1014,4,0)*$C39)) | E39: =IF($B39="","",SUM(VLOOKUP($B39,DADOS!$C$2:$I1014,6,0)*$C39)) | F39: =IF($E39="","",(VLOOKUP($B39,DADOS!$C$2:$I1014,7,0))) | G39: =IF(D39="","",D39*$F$3+D39)
A40: =IF($B40="","",VLOOKUP($B40,DADOS!$C$2:$I1014,2,0)) | D40: =IF($B40="","",SUM(VLOOKUP($B40,DADOS!$C$2:$I1014,4,0)*$C40)) | E40: =IF($B40="","",SUM(VLOOKUP($B40,DADOS!$C$2:$I1014,6,0)*$C40)) | F40: =IF($E40="","",(VLOOKUP($B40,DADOS!$C$2:$I1014,7,0))) | G40: =IF(D40="","",D40*$F$3+D40)
A41: =IF($B41="","",VLOOKUP($B41,DADOS!$C$2:$I1014,2,0)) | D41: =IF($B41="","",SUM(VLOOKUP($B41,DADOS!$C$2:$I1014,4,0)*$C41)) | E41: =IF($B41="","",SUM(VLOOKUP($B41,DADOS!$C$2:$I1014,6,0)*$C41)) | F41: =IF($E41="","",(VLOOKUP($B41,DADOS!$C$2:$I1014,7,0))) | G41: =IF(D41="","",D41*$F$3+D41)
A42: =IF($B42="","",VLOOKUP($B42,DADOS!$C$2:$I1014,2,0)) | D42: =IF($B42="","",SUM(VLOOKUP($B42,DADOS!$C$2:$I1014,4,0)*$C42)) | E42: =IF($B42="","",SUM(VLOOKUP($B42,DADOS!$C$2:$I1014,6,0)*$C42)) | F42: =IF($E42="","",(VLOOKUP($B42,DADOS!$C$2:$I1014,7,0))) | G42: =IF(D42="","",D42*$F$3+D42)
A43: =IF($B43="","",VLOOKUP($B43,DADOS!$C$2:$I1014,2,0)) | D43: =IF($B43="","",SUM(VLOOKUP($B43,DADOS!$C$2:$I1014,4,0)*$C43)) | E43: =IF($B43="","",SUM(VLOOKUP($B43,DADOS!$C$2:$I1014,6,0)*$C43)) | F43: =IF($E43="","",(VLOOKUP($B43,DADOS!$C$2:$I1014,7,0))) | G43: =IF(D43="","",D43*$F$3+D43)
A44: =IF($B44="","",VLOOKUP($B44,DADOS!$C$2:$I1014,2,0)) | D44: =IF($B44="","",SUM(VLOOKUP($B44,DADOS!$C$2:$I1014,4,0)*$C44)) | E44: =IF($B44="","",SUM(VLOOKUP($B44,DADOS!$C$2:$I1014,6,0)*$C44)) | F44: =IF($E44="","",(VLOOKUP($B44,DADOS!$C$2:$I1014,7,0))) | G44: =IF(D44="","",D44*$F$3+D44)
A45: =IF($B45="","",VLOOKUP($B45,DADOS!$C$2:$I1014,2,0)) | D45: =IF($B45="","",SUM(VLOOKUP($B45,DADOS!$C$2:$I1014,4,0)*$C45)) | E45: =IF($B45="","",SUM(VLOOKUP($B45,DADOS!$C$2:$I1014,6,0)*$C45)) | F45: =IF($E45="","",(VLOOKUP($B45,DADOS!$C$2:$I1014,7,0))) | G45: =IF(D45="","",D45*$F$3+D45)
A46: =IF($B46="","",VLOOKUP($B46,DADOS!$C$2:$I1014,2,0)) | D46: =IF($B46="","",SUM(VLOOKUP($B46,DADOS!$C$2:$I1014,4,0)*$C46)) | E46: =IF($B46="","",SUM(VLOOKUP($B46,DADOS!$C$2:$I1014,6,0)*$C46)) | F46: =IF($E46="","",(VLOOKUP($B46,DADOS!$C$2:$I1014,7,0))) | G46: =IF(D46="","",D46*$F$3+D46)
A47: =IF($B47="","",VLOOKUP($B47,DADOS!$C$2:$I1014,2,0)) | D47: =IF($B47="","",SUM(VLOOKUP($B47,DADOS!$C$2:$I1014,4,0)*$C47)) | E47: =IF($B47="","",SUM(VLOOKUP($B47,DADOS!$C$2:$I1014,6,0)*$C47)) | F47: =IF($E47="","",(VLOOKUP($B47,DADOS!$C$2:$I1014,7,0))) | G47: =IF(D47="","",D47*$F$3+D47)
A48: =IF($B48="","",VLOOKUP($B48,DADOS!$C$2:$I1014,2,0)) | D48: =IF($B48="","",SUM(VLOOKUP($B48,DADOS!$C$2:$I1014,4,0)*$C48)) | E48: =IF($B48="","",SUM(VLOOKUP($B48,DADOS!$C$2:$I1014,6,0)*$C48)) | F48: =IF($E48="","",(VLOOKUP($B48,DADOS!$C$2:$I1014,7,0))) | G48: =IF(D48="","",D48*$F$3+D48)
A49: =IF($B49="","",VLOOKUP($B49,DADOS!$C$2:$I1014,2,0)) | D49: =IF($B49="","",SUM(VLOOKUP($B49,DADOS!$C$2:$I1014,4,0)*$C49)) | E49: =IF($B49="","",SUM(VLOOKUP($B49,DADOS!$C$2:$I1014,6,0)*$C49)) | F49: =IF($E49="","",(VLOOKUP($B49,DADOS!$C$2:$I1014,7,0))) | G49: =IF(D49="","",D49*$F$3+D49)
A50: =IF($B50="","",VLOOKUP($B50,DADOS!$C$2:$I1014,2,0)) | D50: =IF($B50="","",SUM(VLOOKUP($B50,DADOS!$C$2:$I1014,4,0)*$C50)) | E50: =IF($B50="","",SUM(VLOOKUP($B50,DADOS!$C$2:$I1014,6,0)*$C50)) | F50: =IF($E50="","",(VLOOKUP($B50,DADOS!$C$2:$I1014,7,0))) | G50: =IF(D50="","",D50*$F$3+D50)
A51: =IF($B51="","",VLOOKUP($B51,DADOS!$C$2:$I1014,2,0)) | D51: =IF($B51="","",SUM(VLOOKUP($B51,DADOS!$C$2:$I1014,4,0)*$C51)) | E51: =IF($B51="","",SUM(VLOOKUP($B51,DADOS!$C$2:$I1014,6,0)*$C51)) | F51: =IF($E51="","",(VLOOKUP($B51,DADOS!$C$2:$I1014,7,0))) | G51: =IF(D51="","",D51*$F$3+D51)
A52: =IF($B52="","",VLOOKUP($B52,DADOS!$C$2:$I1014,2,0)) | D52: =IF($B52="","",SUM(VLOOKUP($B52,DADOS!$C$2:$I1014,4,0)*$C52)) | E52: =IF($B52="","",SUM(VLOOKUP($B52,DADOS!$C$2:$I1014,6,0)*$C52)) | F52: =IF($E52="","",(VLOOKUP($B52,DADOS!$C$2:$I1014,7,0))) | G52: =IF(D52="","",D52*$F$3+D52)
A53: =IF($B53="","",VLOOKUP($B53,DADOS!$C$2:$I1014,2,0)) | D53: =IF($B53="","",SUM(VLOOKUP($B53,DADOS!$C$2:$I1014,4,0)*$C53)) | E53: =IF($B53="","",SUM(VLOOKUP($B53,DADOS!$C$2:$I1014,6,0)*$C53)) | F53: =IF($E53="","",(VLOOKUP($B53,DADOS!$C$2:$I1014,7,0))) | G53: =IF(D53="","",D53*$F$3+D53)
A54: =IF($B54="","",VLOOKUP($B54,DADOS!$C$2:$I1014,2,0)) | D54: =IF($B54="","",SUM(VLOOKUP($B54,DADOS!$C$2:$I1014,4,0)*$C54)) | E54: =IF($B54="","",SUM(VLOOKUP($B54,DADOS!$C$2:$I1014,6,0)*$C54)) | F54: =IF($E54="","",(VLOOKUP($B54,DADOS!$C$2:$I1014,7,0))) | G54: =IF(D54="","",D54*$F$3+D54)
A55: =IF($B55="","",VLOOKUP($B55,DADOS!$C$2:$I1014,2,0)) | D55: =IF($B55="","",SUM(VLOOKUP($B55,DADOS!$C$2:$I1014,4,0)*$C55)) | E55: =IF($B55="","",SUM(VLOOKUP($B55,DADOS!$C$2:$I1014,6,0)*$C55)) | F55: =IF($E55="","",(VLOOKUP($B55,DADOS!$C$2:$I1014,7,0))) | G55: =IF(D55="","",D55*$F$3+D55)
A56: =IF($B56="","",VLOOKUP($B56,DADOS!$C$2:$I1014,2,0)) | D56: =IF($B56="","",SUM(VLOOKUP($B56,DADOS!$C$2:$I1014,4,0)*$C56)) | E56: =IF($B56="","",SUM(VLOOKUP($B56,DADOS!$C$2:$I1014,6,0)*$C56)) | F56: =IF($E56="","",(VLOOKUP($B56,DADOS!$C$2:$I1014,7,0))) | G56: =IF(D56="","",D56*$F$3+D56)
A57: =IF($B57="","",VLOOKUP($B57,DADOS!$C$2:$I1014,2,0)) | D57: =IF($B57="","",SUM(VLOOKUP($B57,DADOS!$C$2:$I1014,4,0)*$C57)) | E57: =IF($B57="","",SUM(VLOOKUP($B57,DADOS!$C$2:$I1014,6,0)*$C57)) | F57: =IF($E57="","",(VLOOKUP($B57,DADOS!$C$2:$I1014,7,0))) | G57: =IF(D57="","",D57*$F$3+D57)
A58: =IF($B58="","",VLOOKUP($B58,DADOS!$C$2:$I1014,2,0)) | D58: =IF($B58="","",SUM(VLOOKUP($B58,DADOS!$C$2:$I1014,4,0)*$C58)) | E58: =IF($B58="","",SUM(VLOOKUP($B58,DADOS!$C$2:$I1014,6,0)*$C58)) | F58: =IF($E58="","",(VLOOKUP($B58,DADOS!$C$2:$I1014,7,0))) | G58: =IF(D58="","",D58*$F$3+D58)
A59: =IF($B59="","",VLOOKUP($B59,DADOS!$C$2:$I1014,2,0)) | D59: =IF($B59="","",SUM(VLOOKUP($B59,DADOS!$C$2:$I1014,4,0)*$C59)) | E59: =IF($B59="","",SUM(VLOOKUP($B59,DADOS!$C$2:$I1014,6,0)*$C59)) | F59: =IF($E59="","",(VLOOKUP($B59,DADOS!$C$2:$I1014,7,0))) | G59: =IF(D59="","",D59*$F$3+D59)
A60: =IF($B60="","",VLOOKUP($B60,DADOS!$C$2:$I1014,2,0)) | D60: =IF($B60="","",SUM(VLOOKUP($B60,DADOS!$C$2:$I1014,4,0)*$C60)) | E60: =IF($B60="","",SUM(VLOOKUP($B60,DADOS!$C$2:$I1014,6,0)*$C60)) | F60: =IF($E60="","",(VLOOKUP($B60,DADOS!$C$2:$I1014,7,0))) | G60: =IF(D60="","",D60*$F$3+D60)
A61: =IF($B61="","",VLOOKUP($B61,DADOS!$C$2:$I1014,2,0)) | D61: =IF($B61="","",SUM(VLOOKUP($B61,DADOS!$C$2:$I1014,4,0)*$C61)) | E61: =IF($B61="","",SUM(VLOOKUP($B61,DADOS!$C$2:$I1014,6,0)*$C61)) | F61: =IF($E61="","",(VLOOKUP($B61,DADOS!$C$2:$I1014,7,0))) | G61: =IF(D61="","",D61*$F$3+D61)
A62: =IF($B62="","",VLOOKUP($B62,DADOS!$C$2:$I1014,2,0)) | D62: =IF($B62="","",SUM(VLOOKUP($B62,DADOS!$C$2:$I1014,4,0)*$C62)) | E62: =IF($B62="","",SUM(VLOOKUP($B62,DADOS!$C$2:$I1014,6,0)*$C62)) | F62: =IF($E62="","",(VLOOKUP($B62,DADOS!$C$2:$I1014,7,0))) | G62: =IF(D62="","",D62*$F$3+D62)
A63: =IF($B63="","",VLOOKUP($B63,DADOS!$C$2:$I1014,2,0)) | D63: =IF($B63="","",SUM(VLOOKUP($B63,DADOS!$C$2:$I1014,4,0)*$C63)) | E63: =IF($B63="","",SUM(VLOOKUP($B63,DADOS!$C$2:$I1014,6,0)*$C63)) | F63: =IF($E63="","",(VLOOKUP($B63,DADOS!$C$2:$I1014,7,0))) | G63: =IF(D63="","",D63*$F$3+D63)
A64: =IF($B64="","",VLOOKUP($B64,DADOS!$C$2:$I1014,2,0)) | D64: =IF($B64="","",SUM(VLOOKUP($B64,DADOS!$C$2:$I1014,4,0)*$C64)) | E64: =IF($B64="","",SUM(VLOOKUP($B64,DADOS!$C$2:$I1014,6,0)*$C64)) | F64: =IF($E64="","",(VLOOKUP($B64,DADOS!$C$2:$I1014,7,0))) | G64: =IF(D64="","",D64*$F$3+D64)
A65: =IF($B65="","",VLOOKUP($B65,DADOS!$C$2:$I1014,2,0)) | D65: =IF($B65="","",SUM(VLOOKUP($B65,DADOS!$C$2:$I1014,4,0)*$C65)) | E65: =IF($B65="","",SUM(VLOOKUP($B65,DADOS!$C$2:$I1014,6,0)*$C65)) | F65: =IF($E65="","",(VLOOKUP($B65,DADOS!$C$2:$I1014,7,0))) | G65: =IF(D65="","",D65*$F$3+D65)
A66: =IF($B66="","",VLOOKUP($B66,DADOS!$C$2:$I1014,2,0)) | D66: =IF($B66="","",SUM(VLOOKUP($B66,DADOS!$C$2:$I1014,4,0)*$C66)) | E66: =IF($B66="","",SUM(VLOOKUP($B66,DADOS!$C$2:$I1014,6,0)*$C66)) | F66: =IF($E66="","",(VLOOKUP($B66,DADOS!$C$2:$I1014,7,0))) | G66: =IF(D66="","",D66*$F$3+D66)
A67: =IF($B67="","",VLOOKUP($B67,DADOS!$C$2:$I1014,2,0)) | D67: =IF($B67="","",SUM(VLOOKUP($B67,DADOS!$C$2:$I1014,4,0)*$C67)) | E67: =IF($B67="","",SUM(VLOOKUP($B67,DADOS!$C$2:$I1014,6,0)*$C67)) | F67: =IF($E67="","",(VLOOKUP($B67,DADOS!$C$2:$I1014,7,0))) | G67: =IF(D67="","",D67*$F$3+D67)
A68: =IF($B68="","",VLOOKUP($B68,DADOS!$C$2:$I1014,2,0)) | D68: =IF($B68="","",SUM(VLOOKUP($B68,DADOS!$C$2:$I1014,4,0)*$C68)) | E68: =IF($B68="","",SUM(VLOOKUP($B68,DADOS!$C$2:$I1014,6,0)*$C68)) | F68: =IF($E68="","",(VLOOKUP($B68,DADOS!$C$2:$I1014,7,0))) | G68: =IF(D68="","",D68*$F$3+D68)
A69: =IF($B69="","",VLOOKUP($B69,DADOS!$C$2:$I1014,2,0)) | D69: =IF($B69="","",SUM(VLOOKUP($B69,DADOS!$C$2:$I1014,4,0)*$C69)) | E69: =IF($B69="","",SUM(VLOOKUP($B69,DADOS!$C$2:$I1014,6,0)*$C69)) | F69: =IF($E69="","",(VLOOKUP($B69,DADOS!$C$2:$I1014,7,0))) | G69: =IF(D69="","",D69*$F$3+D69)
A70: =IF($B70="","",VLOOKUP($B70,DADOS!$C$2:$I1014,2,0)) | D70: =IF($B70="","",SUM(VLOOKUP($B70,DADOS!$C$2:$I1014,4,0)*$C70)) | E70: =IF($B70="","",SUM(VLOOKUP($B70,DADOS!$C$2:$I1014,6,0)*$C70)) | F70: =IF($E70="","",(VLOOKUP($B70,DADOS!$C$2:$I1014,7,0))) | G70: =IF(D70="","",D70*$F$3+D70)
A71: =IF($B71="","",VLOOKUP($B71,DADOS!$C$2:$I1014,2,0)) | D71: =IF($B71="","",SUM(VLOOKUP($B71,DADOS!$C$2:$I1014,4,0)*$C71)) | E71: =IF($B71="","",SUM(VLOOKUP($B71,DADOS!$C$2:$I1014,6,0)*$C71)) | F71: =IF($E71="","",(VLOOKUP($B71,DADOS!$C$2:$I1014,7,0))) | G71: =IF(D71="","",D71*$F$3+D71)
A72: =IF($B72="","",VLOOKUP($B72,DADOS!$C$2:$I1014,2,0)) | D72: =IF($B72="","",SUM(VLOOKUP($B72,DADOS!$C$2:$I1014,4,0)*$C72)) | E72: =IF($B72="","",SUM(VLOOKUP($B72,DADOS!$C$2:$I1014,6,0)*$C72)) | F72: =IF($E72="","",(VLOOKUP($B72,DADOS!$C$2:$I1014,7,0))) | G72: =IF(D72="","",D72*$F$3+D72)
A73: =IF($B73="","",VLOOKUP($B73,DADOS!$C$2:$I1014,2,0)) | D73: =IF($B73="","",SUM(VLOOKUP($B73,DADOS!$C$2:$I1014,4,0)*$C73)) | E73: =IF($B73="","",SUM(VLOOKUP($B73,DADOS!$C$2:$I1014,6,0)*$C73)) | F73: =IF($E73="","",(VLOOKUP($B73,DADOS!$C$2:$I1014,7,0))) | G73: =IF(D73="","",D73*$F$3+D73)
A74: =IF($B74="","",VLOOKUP($B74,DADOS!$C$2:$I1014,2,0)) | D74: =IF($B74="","",SUM(VLOOKUP($B74,DADOS!$C$2:$I1014,4,0)*$C74)) | E74: =IF($B74="","",SUM(VLOOKUP($B74,DADOS!$C$2:$I1014,6,0)*$C74)) | F74: =IF($E74="","",(VLOOKUP($B74,DADOS!$C$2:$I1014,7,0))) | G74: =IF(D74="","",D74*$F$3+D74)
A75: =IF($B75="","",VLOOKUP($B75,DADOS!$C$2:$I1014,2,0)) | D75: =IF($B75="","",SUM(VLOOKUP($B75,DADOS!$C$2:$I1014,4,0)*$C75)) | E75: =IF($B75="","",SUM(VLOOKUP($B75,DADOS!$C$2:$I1014,6,0)*$C75)) | F75: =IF($E75="","",(VLOOKUP($B75,DADOS!$C$2:$I1014,7,0))) | G75: =IF(D75="","",D75*$F$3+D75)
A76: =IF($B76="","",VLOOKUP($B76,DADOS!$C$2:$I1014,2,0)) | D76: =IF($B76="","",SUM(VLOOKUP($B76,DADOS!$C$2:$I1014,4,0)*$C76)) | E76: =IF($B76="","",SUM(VLOOKUP($B76,DADOS!$C$2:$I1014,6,0)*$C76)) | F76: =IF($E76="","",(VLOOKUP($B76,DADOS!$C$2:$I1014,7,0))) | G76: =IF(D76="","",D76*$F$3+D76)
A77: =IF($B77="","",VLOOKUP($B77,DADOS!$C$2:$I1014,2,0)) | D77: =IF($B77="","",SUM(VLOOKUP($B77,DADOS!$C$2:$I1014,4,0)*$C77)) | E77: =IF($B77="","",SUM(VLOOKUP($B77,DADOS!$C$2:$I1014,6,0)*$C77)) | F77: =IF($E77="","",(VLOOKUP($B77,DADOS!$C$2:$I1014,7,0))) | G77: =IF(D77="","",D77*$F$3+D77)
A78: =IF($B78="","",VLOOKUP($B78,DADOS!$C$2:$I1014,2,0)) | D78: =IF($B78="","",SUM(VLOOKUP($B78,DADOS!$C$2:$I1014,4,0)*$C78)) | E78: =IF($B78="","",SUM(VLOOKUP($B78,DADOS!$C$2:$I1014,6,0)*$C78)) | F78: =IF($E78="","",(VLOOKUP($B78,DADOS!$C$2:$I1014,7,0))) | G78: =IF(D78="","",D78*$F$3+D78)
A79: =IF($B79="","",VLOOKUP($B79,DADOS!$C$2:$I1014,2,0)) | D79: =IF($B79="","",SUM(VLOOKUP($B79,DADOS!$C$2:$I1014,4,0)*$C79)) | E79: =IF($B79="","",SUM(VLOOKUP($B79,DADOS!$C$2:$I1014,6,0)*$C79)) | F79: =IF($E79="","",(VLOOKUP($B79,DADOS!$C$2:$I1014,7,0))) | G79: =IF(D79="","",D79*$F$3+D79)
A80: =IF($B80="","",VLOOKUP($B80,DADOS!$C$2:$I1014,2,0)) | D80: =IF($B80="","",SUM(VLOOKUP($B80,DADOS!$C$2:$I1014,4,0)*$C80)) | E80: =IF($B80="","",SUM(VLOOKUP($B80,DADOS!$C$2:$I1014,6,0)*$C80)) | F80: =IF($E80="","",(VLOOKUP($B80,DADOS!$C$2:$I1014,7,0))) | G80: =IF(D80="","",D80*$F$3+D80)
A81: =IF($B81="","",VLOOKUP($B81,DADOS!$C$2:$I1014,2,0)) | D81: =IF($B81="","",SUM(VLOOKUP($B81,DADOS!$C$2:$I1014,4,0)*$C81)) | E81: =IF($B81="","",SUM(VLOOKUP($B81,DADOS!$C$2:$I1014,6,0)*$C81)) | F81: =IF($E81="","",(VLOOKUP($B81,DADOS!$C$2:$I1014,7,0))) | G81: =IF(D81="","",D81*$F$3+D81)
A82: =IF($B82="","",VLOOKUP($B82,DADOS!$C$2:$I1014,2,0)) | D82: =IF($B82="","",SUM(VLOOKUP($B82,DADOS!$C$2:$I1014,4,0)*$C82)) | E82: =IF($B82="","",SUM(VLOOKUP($B82,DADOS!$C$2:$I1014,6,0)*$C82)) | F82: =IF($E82="","",(VLOOKUP($B82,DADOS!$C$2:$I1014,7,0))) | G82: =IF(D82="","",D82*$F$3+D82)
A83: =IF($B83="","",VLOOKUP($B83,DADOS!$C$2:$I1014,2,0)) | D83: =IF($B83="","",SUM(VLOOKUP($B83,DADOS!$C$2:$I1014,4,0)*$C83)) | E83: =IF($B83="","",SUM(VLOOKUP($B83,DADOS!$C$2:$I1014,6,0)*$C83)) | F83: =IF($E83="","",(VLOOKUP($B83,DADOS!$C$2:$I1014,7,0))) | G83: =IF(D83="","",D83*$F$3+D83)
A84: =IF($B84="","",VLOOKUP($B84,DADOS!$C$2:$I1014,2,0)) | D84: =IF($B84="","",SUM(VLOOKUP($B84,DADOS!$C$2:$I1014,4,0)*$C84)) | E84: =IF($B84="","",SUM(VLOOKUP($B84,DADOS!$C$2:$I1014,6,0)*$C84)) | F84: =IF($E84="","",(VLOOKUP($B84,DADOS!$C$2:$I1014,7,0))) | G84: =IF(D84="","",D84*$F$3+D84)
A85: =IF($B85="","",VLOOKUP($B85,DADOS!$C$2:$I1014,2,0)) | D85: =IF($B85="","",SUM(VLOOKUP($B85,DADOS!$C$2:$I1014,4,0)*$C85)) | E85: =IF($B85="","",SUM(VLOOKUP($B85,DADOS!$C$2:$I1014,6,0)*$C85)) | F85: =IF($E85="","",(VLOOKUP($B85,DADOS!$C$2:$I1014,7,0))) | G85: =IF(D85="","",D85*$F$3+D85)
A86: =IF($B86="","",VLOOKUP($B86,DADOS!$C$2:$I1014,2,0)) | D86: =IF($B86="","",SUM(VLOOKUP($B86,DADOS!$C$2:$I1014,4,0)*$C86)) | E86: =IF($B86="","",SUM(VLOOKUP($B86,DADOS!$C$2:$I1014,6,0)*$C86)) | F86: =IF($E86="","",(VLOOKUP($B86,DADOS!$C$2:$I1014,7,0))) | G86: =IF(D86="","",D86*$F$3+D86)
A87: =IF($B87="","",VLOOKUP($B87,DADOS!$C$2:$I1014,2,0)) | D87: =IF($B87="","",SUM(VLOOKUP($B87,DADOS!$C$2:$I1014,4,0)*$C87)) | E87: =IF($B87="","",SUM(VLOOKUP($B87,DADOS!$C$2:$I1014,6,0)*$C87)) | F87: =IF($E87="","",(VLOOKUP($B87,DADOS!$C$2:$I1014,7,0))) | G87: =IF(D87="","",D87*$F$3+D87)
A88: =IF($B88="","",VLOOKUP($B88,DADOS!$C$2:$I1014,2,0)) | D88: =IF($B88="","",SUM(VLOOKUP($B88,DADOS!$C$2:$I1014,4,0)*$C88)) | E88: =IF($B88="","",SUM(VLOOKUP($B88,DADOS!$C$2:$I1014,6,0)*$C88)) | F88: =IF($E88="","",(VLOOKUP($B88,DADOS!$C$2:$I1014,7,0))) | G88: =IF(D88="","",D88*$F$3+D88)
A89: =IF($B89="","",VLOOKUP($B89,DADOS!$C$2:$I1014,2,0)) | D89: =IF($B89="","",SUM(VLOOKUP($B89,DADOS!$C$2:$I1014,4,0)*$C89)) | E89: =IF($B89="","",SUM(VLOOKUP($B89,DADOS!$C$2:$I1014,6,0)*$C89)) | F89: =IF($E89="","",(VLOOKUP($B89,DADOS!$C$2:$I1014,7,0))) | G89: =IF(D89="","",D89*$F$3+D89)
A90: =IF($B90="","",VLOOKUP($B90,DADOS!$C$2:$I1014,2,0)) | D90: =IF($B90="","",SUM(VLOOKUP($B90,DADOS!$C$2:$I1014,4,0)*$C90)) | E90: =IF($B90="","",SUM(VLOOKUP($B90,DADOS!$C$2:$I1014,6,0)*$C90)) | F90: =IF($E90="","",(VLOOKUP($B90,DADOS!$C$2:$I1014,7,0))) | G90: =IF(D90="","",D90*$F$3+D90)
A91: =IF($B91="","",VLOOKUP($B91,DADOS!$C$2:$I1014,2,0)) | D91: =IF($B91="","",SUM(VLOOKUP($B91,DADOS!$C$2:$I1014,4,0)*$C91)) | E91: =IF($B91="","",SUM(VLOOKUP($B91,DADOS!$C$2:$I1014,6,0)*$C91)) | F91: =IF($E91="","",(VLOOKUP($B91,DADOS!$C$2:$I1014,7,0))) | G91: =IF(D91="","",D91*$F$3+D91)
A92: =IF($B92="","",VLOOKUP($B92,DADOS!$C$2:$I1014,2,0)) | D92: =IF($B92="","",SUM(VLOOKUP($B92,DADOS!$C$2:$I1014,4,0)*$C92)) | E92: =IF($B92="","",SUM(VLOOKUP($B92,DADOS!$C$2:$I1014,6,0)*$C92)) | F92: =IF($E92="","",(VLOOKUP($B92,DADOS!$C$2:$I1014,7,0))) | G92: =IF(D92="","",D92*$F$3+D92)
A93: =IF($B93="","",VLOOKUP($B93,DADOS!$C$2:$I1014,2,0)) | D93: =IF($B93="","",SUM(VLOOKUP($B93,DADOS!$C$2:$I1014,4,0)*$C93)) | E93: =IF($B93="","",SUM(VLOOKUP($B93,DADOS!$C$2:$I1014,6,0)*$C93)) | F93: =IF($E93="","",(VLOOKUP($B93,DADOS!$C$2:$I1014,7,0))) | G93: =IF(D93="","",D93*$F$3+D93)
A94: =IF($B94="","",VLOOKUP($B94,DADOS!$C$2:$I1014,2,0)) | D94: =IF($B94="","",SUM(VLOOKUP($B94,DADOS!$C$2:$I1014,4,0)*$C94)) | E94: =IF($B94="","",SUM(VLOOKUP($B94,DADOS!$C$2:$I1014,6,0)*$C94)) | F94: =IF($E94="","",(VLOOKUP($B94,DADOS!$C$2:$I1014,7,0))) | G94: =IF(D94="","",D94*$F$3+D94)
A95: =IF($B95="","",VLOOKUP($B95,DADOS!$C$2:$I1014,2,0)) | D95: =IF($B95="","",SUM(VLOOKUP($B95,DADOS!$C$2:$I1014,4,0)*$C95)) | E95: =IF($B95="","",SUM(VLOOKUP($B95,DADOS!$C$2:$I1014,6,0)*$C95)) | F95: =IF($E95="","",(VLOOKUP($B95,DADOS!$C$2:$I1014,7,0))) | G95: =IF(D95="","",D95*$F$3+D95)
A96: =IF($B96="","",VLOOKUP($B96,DADOS!$C$2:$I1014,2,0)) | D96: =IF($B96="","",SUM(VLOOKUP($B96,DADOS!$C$2:$I1014,4,0)*$C96)) | E96: =IF($B96="","",SUM(VLOOKUP($B96,DADOS!$C$2:$I1014,6,0)*$C96)) | F96: =IF($E96="","",(VLOOKUP($B96,DADOS!$C$2:$I1014,7,0))) | G96: =IF(D96="","",D96*$F$3+D96)
A97: =IF($B97="","",VLOOKUP($B97,DADOS!$C$2:$I1014,2,0)) | D97: =IF($B97="","",SUM(VLOOKUP($B97,DADOS!$C$2:$I1014,4,0)*$C97)) | E97: =IF($B97="","",SUM(VLOOKUP($B97,DADOS!$C$2:$I1014,6,0)*$C97)) | F97: =IF($E97="","",(VLOOKUP($B97,DADOS!$C$2:$I1014,7,0))) | G97: =IF(D97="","",D97*$F$3+D97)
A98: =IF($B98="","",VLOOKUP($B98,DADOS!$C$2:$I1014,2,0)) | D98: =IF($B98="","",SUM(VLOOKUP($B98,DADOS!$C$2:$I1014,4,0)*$C98)) | E98: =IF($B98="","",SUM(VLOOKUP($B98,DADOS!$C$2:$I1014,6,0)*$C98)) | F98: =IF($E98="","",(VLOOKUP($B98,DADOS!$C$2:$I1014,7,0))) | G98: =IF(D98="","",D98*$F$3+D98)
A99: =IF($B99="","",VLOOKUP($B99,DADOS!$C$2:$I1014,2,0)) | D99: =IF($B99="","",SUM(VLOOKUP($B99,DADOS!$C$2:$I1014,4,0)*$C99)) | E99: =IF($B99="","",SUM(VLOOKUP($B99,DADOS!$C$2:$I1014,6,0)*$C99)) | F99: =IF($E99="","",(VLOOKUP($B99,DADOS!$C$2:$I1014,7,0))) | G99: =IF(D99="","",D99*$F$3+D99)
A100: =IF($B100="","",VLOOKUP($B100,DADOS!$C$2:$I1014,2,0)) | D100: =IF($B100="","",SUM(VLOOKUP($B100,DADOS!$C$2:$I1014,4,0)*$C100)) | E100: =IF($B100="","",SUM(VLOOKUP($B100,DADOS!$C$2:$I1014,6,0)*$C100)) | F100: =IF($E100="","",(VLOOKUP($B100,DADOS!$C$2:$I1014,7,0))) | G100: =IF(D100="","",D100*$F$3+D100)
A101: =IF($B101="","",VLOOKUP($B101,DADOS!$C$2:$I1014,2,0)) | D101: =IF($B101="","",SUM(VLOOKUP($B101,DADOS!$C$2:$I1014,4,0)*$C101)) | E101: =IF($B101="","",SUM(VLOOKUP($B101,DADOS!$C$2:$I1014,6,0)*$C101)) | F101: =IF($E101="","",(VLOOKUP($B101,DADOS!$C$2:$I1014,7,0))) | G101: =IF(D101="","",D101*$F$3+D101)
A102: =IF($B102="","",VLOOKUP($B102,DADOS!$C$2:$I1014,2,0)) | D102: =IF($B102="","",SUM(VLOOKUP($B102,DADOS!$C$2:$I1014,4,0)*$C102)) | E102: =IF($B102="","",SUM(VLOOKUP($B102,DADOS!$C$2:$I1014,6,0)*$C102)) | F102: =IF($E102="","",(VLOOKUP($B102,DADOS!$C$2:$I1014,7,0))) | G102: =IF(D102="","",D102*$F$3+D102)
...

Sheet DADOS
C1: PRODUTOS | D1: MARCA | E1: % | F1: CUSTO | G1: CUSTO TOTAL | H1: PREÇO SUGERIDO | I1: MARGEM
C2: =IFERROR(__xludf.DUMMYFUNCTION("IMPORTRANGE(""https://docs.google.com/spreadsheets/d/1DsdxsrBJOk75sDGmXMsLLa15LHA7JaMlvKBZACG-RHY/edit?gid=1280887965#gid=1280887965"",""TESTE!B2"")"),"AAT AC-1 G2") -> AAT AC-1 G2 | D2: =IFERROR(__xludf.DUMMYFUNCTION("IMPORTRANGE(""https://docs.google.com/spreadsheets/d/1DsdxsrBJOk75sDGmXMsLLa15LHA7JaMlvKBZACG-RHY/edit?gid=1280887965#gid=1280887965"",""TESTE!A2"")"),"AAT") -> AAT | E2: 0 | F2: 0 | G2: 0 | H2: =IFERROR(__xludf.DUMMYFUNCTION("IMPORTRANGE(""https://docs.google.com/spreadsheets/d/1DsdxsrBJOk75sDGmXMsLLa15LHA7JaMlvKBZACG-RHY/edit?gid=1280887965#gid=1280887965"",""TESTE!D2"")"),3640.0) -> 3640 | I2: =IF(G2>0,(H2-G2)/G2,IF(H2>0,0,0)) -> 0
C3: =IFERROR(__xludf.DUMMYFUNCTION("IMPORTRANGE(""https://docs.google.com/spreadsheets/d/1DsdxsrBJOk75sDGmXMsLLa15LHA7JaMlvKBZACG-RHY/edit?gid=1280887965#gid=1280887965"",""TESTE!B3"")"),"AAT AC-2 G2") -> AAT AC-2 G2 | D3: =IFERROR(__xludf.DUMMYFUNCTION("IMPORTRANGE(""https://docs.google.com/spreadsheets/d/1DsdxsrBJOk75sDGmXMsLLa15LHA7JaMlvKBZACG-RHY/edit?gid=1280887965#gid=1280887965"",""TESTE!A3"")"),"AAT") -> AAT | E3: 0 | F3: 0 | G3: 0 | H3: =IFERROR(__xludf.DUMMYFUNCTION("IMPORTRANGE(""https://docs.google.com/spreadsheets/d/1DsdxsrBJOk75sDGmXMsLLa15LHA7JaMlvKBZACG-RHY/edit?gid=1280887965#gid=1280887965"",""TESTE!D3"")"),2150.0) -> 2150 | I3: =IF(G3>0,(H3-G3)/G3,IF(H3>0,0,0)) -> 0
C4: =IFERROR(__xludf.DUMMYFUNCTION("IMPORTRANGE(""https://docs.google.com/spreadsheets/d/1DsdxsrBJOk75sDGmXMsLLa15LHA7JaMlvKBZACG-RHY/edit?gid=1280887965#gid=1280887965"",""TESTE!B4"")"),"AAT BTA-1 G2") -> AAT BTA-1 G2 | D4: =IFERROR(__xludf.DUMMYFUNCTION("IMPORTRANGE(""https://docs.google.com/spreadsheets/d/1DsdxsrBJOk75sDGmXMsLLa15LHA7JaMlvKBZACG-RHY/edit?gid=1280887965#gid=1280887965"",""TESTE!A4"")"),"AAT") -> AAT | E4: 0 | F4: 0 | G4: 0 | H4: =IFERROR(__xludf.DUMMYFUNCTION("IMPORTRANGE(""https://docs.google.com/spreadsheets/d/1DsdxsrBJOk75sDGmXMsLLa15LHA7JaMlvKBZACG-RHY/edit?gid=1280887965#gid=1280887965"",""TESTE!D4"")"),950.0) -> 950 | I4: =IF(G4>0,(H4-G4)/G4,IF(H4>0,0,0)) -> 0
C5: =IFERROR(__xludf.DUMMYFUNCTION("IMPORTRANGE(""https://docs.google.com/spreadsheets/d/1DsdxsrBJOk75sDGmXMsLLa15LHA7JaMlvKBZACG-RHY/edit?gid=1280887965#gid=1280887965"",""TESTE!B5"")"),"AAT BTA-2 G2") -> AAT BTA-2 G2 | D5: =IFERROR(__xludf.DUMMYFUNCTION("IMPORTRANGE(""https://docs.google.com/spreadsheets/d/1DsdxsrBJOk75sDGmXMsLLa15LHA7JaMlvKBZACG-RHY/edit?gid=1280887965#gid=1280887965"",""TESTE!A5"")"),"AAT") -> AAT | E5: 0 | F5: 0 | G5: 0 | H5: =IFERROR(__xludf.DUMMYFUNCTION("IMPORTRANGE(""https://docs.google.com/spreadsheets/d/1DsdxsrBJOk75sDGmXMsLLa15LHA7JaMlvKBZACG-RHY/edit?gid=1280887965#gid=1280887965"",""TESTE!D5"")"),1350.0) -> 1350 | I5: =IF(G5>0,(H5-G5)/G5,IF(H5>0,0,0)) -> 0
C6: =IFERROR(__xludf.DUMMYFUNCTION("IMPORTRANGE(""https://docs.google.com/spreadsheets/d/1DsdxsrBJOk75sDGmXMsLLa15LHA7JaMlvKBZACG-RHY/edit?gid=1280887965#gid=1280887965"",""TESTE!B6"")"),"AAT BTA-3") -> AAT BTA-3 | D6: =IFERROR(__xludf.DUMMYFUNCTION("IMPORTRANGE(""https://docs.google.com/spreadsheets/d/1DsdxsrBJOk75sDGmXMsLLa15LHA7JaMlvKBZACG-RHY/edit?gid=1280887965#gid=1280887965"",""TESTE!A5"")"),"AAT") -> AAT | E6: 0 | F6: 0 | G6: 0 | H6: =IFERROR(__xludf.DUMMYFUNCTION("IMPORTRANGE(""https://docs.google.com/spreadsheets/d/1DsdxsrBJOk75sDGmXMsLLa15LHA7JaMlvKBZACG-RHY/edit?gid=1280887965#gid=1280887965"",""TESTE!D6"")"),1890.0) -> 1890 | I6: =IF(G6>0,(H6-G6)/G6,IF(H6>0,0,0)) -> 0
C7: =IFERROR(__xludf.DUMMYFUNCTION("IMPORTRANGE(""https://docs.google.com/spreadsheets/d/1DsdxsrBJOk75sDGmXMsLLa15LHA7JaMlvKBZACG-RHY/edit?gid=1280887965#gid=1280887965"",""TESTE!B7"")"),"AAT BTA-3 + AAT SLIM 6”") -> AAT BTA-3 + AAT SLIM 6” | D7: =IFERROR(__xludf.DUMMYFUNCTION("IMPORTRANGE(""https://docs.google.com/spreadsheets/d/1DsdxsrBJOk75sDGmXMsLLa15LHA7JaMlvKBZACG-RHY/edit?gid=1280887965#gid=1280887965"",""TESTE!A5"")"),"AAT") -> AAT | E7: 0 | F7: 0 | G7: 0 | H7: =IFERROR(__xludf.DUMMYFUNCTION("IMPORTRANGE(""https://docs.google.com/spreadsheets/d/1DsdxsrBJOk75sDGmXMsLLa15LHA7JaMlvKBZACG-RHY/edit?gid=1280887965#gid=1280887965"",""TESTE!D7"")"),2589.9) -> 2589.9 | I7: =IF(G7>0,(H7-G7)/G7,IF(H7>0,0,0)) -> 0
C8: =IFERROR(__xludf.DUMMYFUNCTION("IMPORTRANGE(""https://docs.google.com/spreadsheets/d/1DsdxsrBJOk75sDGmXMsLLa15LHA7JaMlvKBZACG-RHY/edit?gid=1280887965#gid=1280887965"",""TESTE!B8:B59"") "),"AAT BTS-1 Q") -> AAT BTS-1 Q | D8: =IFERROR(__xludf.DUMMYFUNCTION("IMPORTRANGE(""https://docs.google.com/spreadsheets/d/1DsdxsrBJOk75sDGmXMsLLa15LHA7JaMlvKBZACG-RHY/edit?gid=1280887965#gid=1280887965"",""TESTE!A5"")"),"AAT") -> AAT | E8: 0 | F8: 0 | G8: 0 | H8: =IFERROR(__xludf.DUMMYFUNCTION("IMPORTRANGE(""https://docs.google.com/spreadsheets/d/1DsdxsrBJOk75sDGmXMsLLa15LHA7JaMlvKBZACG-RHY/edit?gid=1280887965#gid=1280887965"",""TESTE!D8:d59"")"),2990.0) -> 2990 | I8: =IF(G8>0,(H8-G8)/G8,IF(H8>0,0,0)) -> 0
C9: =IFERROR(__xludf.DUMMYFUNCTION("""COMPUTED_VALUE"""),"AAT BTS-1 Q BLACK") -> AAT BTS-1 Q BLACK | D9: =IFERROR(__xludf.DUMMYFUNCTION("IMPORTRANGE(""https://docs.google.com/spreadsheets/d/1DsdxsrBJOk75sDGmXMsLLa15LHA7JaMlvKBZACG-RHY/edit?gid=1280887965#gid=1280887965"",""TESTE!A5"")"),"AAT") -> AAT | E9: 0 | F9: 0 | G9: 0 | H9: =IFERROR(__xludf.DUMMYFUNCTION("""COMPUTED_VALUE"""),2990.0) -> 2990 | I9: =IF(G9>0,(H9-G9)/G9,IF(H9>0,0,0)) -> 0
C10: =IFERROR(__xludf.DUMMYFUNCTION("""COMPUTED_VALUE"""),"AAT BTS-1 R") -> AAT BTS-1 R | D10: =IFERROR(__xludf.DUMMYFUNCTION("IMPORTRANGE(""https://docs.google.com/spreadsheets/d/1DsdxsrBJOk75sDGmXMsLLa15LHA7JaMlvKBZACG-RHY/edit?gid=1280887965#gid=1280887965"",""TESTE!A5"")"),"AAT") -> AAT | E10: 0 | F10: 0 | G10: 0 | H10: =IFERROR(__xludf.DUMMYFUNCTION("""COMPUTED_VALUE"""),2990.0) -> 2990 | I10: =IF(G10>0,(H10-G10)/G10,IF(H10>0,0,0)) -> 0
C11: =IFERROR(__xludf.DUMMYFUNCTION("""COMPUTED_VALUE"""),"AAT BTS-1 R BLACK") -> AAT BTS-1 R BLACK | D11: =IFERROR(__xludf.DUMMYFUNCTION("IMPORTRANGE(""https://docs.google.com/spreadsheets/d/1DsdxsrBJOk75sDGmXMsLLa15LHA7JaMlvKBZACG-RHY/edit?gid=1280887965#gid=1280887965"",""TESTE!A5"")"),"AAT") -> AAT | E11: 0 | F11: 0 | G11: 0 | H11: =IFERROR(__xludf.DUMMYFUNCTION("""COMPUTED_VALUE"""),2990.0) -> 2990 | I11: =IF(G11>0,(H11-G11)/G11,IF(H11>0,0,0)) -> 0
C12: =IFERROR(__xludf.DUMMYFUNCTION("""COMPUTED_VALUE"""),"AAT CUBE HOUT 12’’ BETON") -> AAT CUBE HOUT 12’’ BETON | D12: =IFERROR(__xludf.DUMMYFUNCTION("IMPORTRANGE(""https://docs.google.com/spreadsheets/d/1DsdxsrBJOk75sDGmXMsLLa15LHA7JaMlvKBZACG-RHY/edit?gid=1280887965#gid=1280887965"",""TESTE!A5"")"),"AAT") -> AAT | E12: 0 | F12: 0 | G12: 0 | H12: =IFERROR(__xludf.DUMMYFUNCTION("""COMPUTED_VALUE"""),5900.0) -> 5900 | I12: =IF(G12>0,(H12-G12)/G12,IF(H12>0,0,0)) -> 0
C13: =IFERROR(__xludf.DUMMYFUNCTION("""COMPUTED_VALUE"""),"AAT MA-1 G2") -> AAT MA-1 G2 | D13: =IFERROR(__xludf.DUMMYFUNCTION("IMPORTRANGE(""https://docs.google.com/spreadsheets/d/1DsdxsrBJOk75sDGmXMsLLa15LHA7JaMlvKBZACG-RHY/edit?gid=1280887965#gid=1280887965"",""TESTE!A5"")"),"AAT") -> AAT | E13: 0 | F13: 0 | G13: 0 | H13: =IFERROR(__xludf.DUMMYFUNCTION("""COMPUTED_VALUE"""),3200.0) -> 3200 | I13: =IF(G13>0,(H13-G13)/G13,IF(H13>0,0,0)) -> 0
C14: =IFERROR(__xludf.DUMMYFUNCTION("""COMPUTED_VALUE"""),"AAT MA-2 G2") -> AAT MA-2 G2 | D14: =IFERROR(__xludf.DUMMYFUNCTION("IMPORTRANGE(""https://docs.google.com/spreadsheets/d/1DsdxsrBJOk75sDGmXMsLLa15LHA7JaMlvKBZACG-RHY/edit?gid=1280887965#gid=1280887965"",""TESTE!A5"")"),"AAT") -> AAT | E14: 0 | F14: 0 | G14: 0 | H14: =IFERROR(__xludf.DUMMYFUNCTION("""COMPUTED_VALUE"""),3600.0) -> 3600 | I14: =IF(G14>0,(H14-G14)/G14,IF(H14>0,0,0)) -> 0
C15: =IFERROR(__xludf.DUMMYFUNCTION("""COMPUTED_VALUE"""),"AAT MA-3 G2") -> AAT MA-3 G2 | D15: =IFERROR(__xludf.DUMMYFUNCTION("IMPORTRANGE(""https://docs.google.com/spreadsheets/d/1DsdxsrBJOk75sDGmXMsLLa15LHA7JaMlvKBZACG-RHY/edit?gid=1280887965#gid=1280887965"",""TESTE!A5"")"),"AAT") -> AAT | E15: 0 | F15: 0 | G15: 0 | H15: =IFERROR(__xludf.DUMMYFUNCTION("""COMPUTED_VALUE"""),3900.0) -> 3900 | I15: =IF(G15>0,(H15-G15)/G15,IF(H15>0,0,0)) -> 0
C16: =IFERROR(__xludf.DUMMYFUNCTION("""COMPUTED_VALUE"""),"AAT MA-4 G2") -> AAT MA-4 G2 | D16: =IFERROR(__xludf.DUMMYFUNCTION("IMPORTRANGE(""https://docs.google.com/spreadsheets/d/1DsdxsrBJOk75sDGmXMsLLa15LHA7JaMlvKBZACG-RHY/edit?gid=1280887965#gid=1280887965"",""TESTE!A5"")"),"AAT") -> AAT | E16: 0 | F16: 0 | G16: 0 | H16: =IFERROR(__xludf.DUMMYFUNCTION("""COMPUTED_VALUE"""),4550.0) -> 4550 | I16: =IF(G16>0,(H16-G16)/G16,IF(H16>0,0,0)) -> 0
C17: =IFERROR(__xludf.DUMMYFUNCTION("""COMPUTED_VALUE"""),"AAT MP-1") -> AAT MP-1 | D17: =IFERROR(__xludf.DUMMYFUNCTION("IMPORTRANGE(""https://docs.google.com/spreadsheets/d/1DsdxsrBJOk75sDGmXMsLLa15LHA7JaMlvKBZACG-RHY/edit?gid=1280887965#gid=1280887965"",""TESTE!A5"")"),"AAT") -> AAT | E17: 0 | F17: 0 | G17: 0 | H17: =IFERROR(__xludf.DUMMYFUNCTION("""COMPUTED_VALUE"""),1990.0) -> 1990 | I17: =IF(G17>0,(H17-G17)/G17,IF(H17>0,0,0)) -> 0
C18: =IFERROR(__xludf.DUMMYFUNCTION("""COMPUTED_VALUE"""),"AAT PA-200") -> AAT PA-200 | D18: =IFERROR(__xludf.DUMMYFUNCTION("IMPORTRANGE(""https://docs.google.com/spreadsheets/d/1DsdxsrBJOk75sDGmXMsLLa15LHA7JaMlvKBZACG-RHY/edit?gid=1280887965#gid=1280887965"",""TESTE!A5"")"),"AAT") -> AAT | E18: 0 | F18: 0 | G18: 0 | H18: =IFERROR(__xludf.DUMMYFUNCTION("""COMPUTED_VALUE"""),1750.0) -> 1750 | I18: =IF(G18>0,(H18-G18)/G18,IF(H18>0,0,0)) -> 0
C19: =IFERROR(__xludf.DUMMYFUNCTION("""COMPUTED_VALUE"""),"AAT PA-60") -> AAT PA-60 | D19: =IFERROR(__xludf.DUMMYFUNCTION("IMPORTRANGE(""https://docs.google.com/spreadsheets/d/1DsdxsrBJOk75sDGmXMsLLa15LHA7JaMlvKBZACG-RHY/edit?gid=1280887965#gid=1280887965"",""TESTE!A5"")"),"AAT") -> AAT | E19: 0 | F19: 0 | G19: 0 | H19: =IFERROR(__xludf.DUMMYFUNCTION("""COMPUTED_VALUE"""),850.0) -> 850 | I19: =IF(G19>0,(H19-G19)/G19,IF(H19>0,0,0)) -> 0
C20: =IFERROR(__xludf.DUMMYFUNCTION("""COMPUTED_VALUE"""),"AAT PM-1 G2") -> AAT PM-1 G2 | D20: =IFERROR(__xludf.DUMMYFUNCTION("IMPORTRANGE(""https://docs.google.com/spreadsheets/d/1DsdxsrBJOk75sDGmXMsLLa15LHA7JaMlvKBZACG-RHY/edit?gid=1280887965#gid=1280887965"",""TESTE!A5"")"),"AAT") -> AAT | E20: 0 | F20: 0 | G20: 0 | H20: =IFERROR(__xludf.DUMMYFUNCTION("""COMPUTED_VALUE"""),3550.0) -> 3550 | I20: =IF(G20>0,(H20-G20)/G20,IF(H20>0,0,0)) -> 0
C21: =IFERROR(__xludf.DUMMYFUNCTION("""COMPUTED_VALUE"""),"AAT PM-10 CI") -> AAT PM-10 CI | D21: =IFERROR(__xludf.DUMMYFUNCTION("IMPORTRANGE(""https://docs.google.com/spreadsheets/d/1DsdxsrBJOk75sDGmXMsLLa15LHA7JaMlvKBZACG-RHY/edit?gid=1280887965#gid=1280887965"",""TESTE!A5"")"),"AAT") -> AAT | E21: 0 | F21: 0 | G21: 0 | H21: =IFERROR(__xludf.DUMMYFUNCTION("""COMPUTED_VALUE"""),3250.0) -> 3250 | I21: =IF(G21>0,(H21-G21)/G21,IF(H21>0,0,0)) -> 0
C22: =IFERROR(__xludf.DUMMYFUNCTION("""COMPUTED_VALUE"""),"AAT PM-11 CI") -> AAT PM-11 CI | D22: =IFERROR(__xludf.DUMMYFUNCTION("IMPORTRANGE(""https://docs.google.com/spreadsheets/d/1DsdxsrBJOk75sDGmXMsLLa15LHA7JaMlvKBZACG-RHY/edit?gid=1280887965#gid=1280887965"",""TESTE!A5"")"),"AAT") -> AAT | E22: 0 | F22: 0 | G22: 0 | H22: =IFERROR(__xludf.DUMMYFUNCTION("""COMPUTED_VALUE"""),4050.0) -> 4050 | I22: =IF(G22>0,(H22-G22)/G22,IF(H22>0,0,0)) -> 0
C23: =IFERROR(__xludf.DUMMYFUNCTION("""COMPUTED_VALUE"""),"AAT PM-2") -> AAT PM-2 | D23: =IFERROR(__xludf.DUMMYFUNCTION("IMPORTRANGE(""https://docs.google.com/spreadsheets/d/1DsdxsrBJOk75sDGmXMsLLa15LHA7JaMlvKBZACG-RHY/edit?gid=1280887965#gid=1280887965"",""TESTE!A5"")"),"AAT") -> AAT | E23: 0 | F23: 0 | G23: 0 | H23: =IFERROR(__xludf.DUMMYFUNCTION("""COMPUTED_VALUE"""),9800.0) -> 9800 | I23: =IF(G23>0,(H23-G23)/G23,IF(H23>0,0,0)) -> 0
C24: =IFERROR(__xludf.DUMMYFUNCTION("""COMPUTED_VALUE"""),"AAT PM-4 G2") -> AAT PM-4 G2 | D24: =IFERROR(__xludf.DUMMYFUNCTION("IMPORTRANGE(""https://docs.google.com/spreadsheets/d/1DsdxsrBJOk75sDGmXMsLLa15LHA7JaMlvKBZACG-RHY/edit?gid=1280887965#gid=1280887965"",""TESTE!A5"")"),"AAT") -> AAT | E24: 0 | F24: 0 | G24: 0 | H24: =IFERROR(__xludf.DUMMYFUNCTION("""COMPUTED_VALUE"""),5700.0) -> 5700 | I24: =IF(G24>0,(H24-G24)/G24,IF(H24>0,0,0)) -> 0
C25: =IFERROR(__xludf.DUMMYFUNCTION("""COMPUTED_VALUE"""),"AAT PM-5") -> AAT PM-5 | D25: =IFERROR(__xludf.DUMMYFUNCTION("IMPORTRANGE(""https://docs.google.com/spreadsheets/d/1DsdxsrBJOk75sDGmXMsLLa15LHA7JaMlvKBZACG-RHY/edit?gid=1280887965#gid=1280887965"",""TESTE!A5"")"),"AAT") -> AAT | E25: 0 | F25: 0 | G25: 0 | H25: =IFERROR(__xludf.DUMMYFUNCTION("""COMPUTED_VALUE"""),8750.0) -> 8750 | I25: =IF(G25>0,(H25-G25)/G25,IF(H25>0,0,0)) -> 0
C26: =IFERROR(__xludf.DUMMYFUNCTION("""COMPUTED_VALUE"""),"AAT PM-6 CI") -> AAT PM-6 CI | D26: =IFERROR(__xludf.DUMMYFUNCTION("IMPORTRANGE(""https://docs.google.com/spreadsheets/d/1DsdxsrBJOk75sDGmXMsLLa15LHA7JaMlvKBZACG-RHY/edit?gid=1280887965#gid=1280887965"",""TESTE!A5"")"),"AAT") -> AAT | E26: 0 | F26: 0 | G26: 0 | H26: =IFERROR(__xludf.DUMMYFUNCTION("""COMPUTED_VALUE"""),4200.0) -> 4200 | I26: =IF(G26>0,(H26-G26)/G26,IF(H26>0,0,0)) -> 0
C27: =IFERROR(__xludf.DUMMYFUNCTION("""COMPUTED_VALUE"""),"AAT PM-7 CI") -> AAT PM-7 CI | D27: =IFERROR(__xludf.DUMMYFUNCTION("IMPORTRANGE(""https://docs.google.com/spreadsheets/d/1DsdxsrBJOk75sDGmXMsLLa15LHA7JaMlvKBZACG-RHY/edit?gid=1280887965#gid=1280887965"",""TESTE!A5"")"),"AAT") -> AAT | E27: 0 | F27: 0 | G27: 0 | H27: =IFERROR(__xludf.DUMMYFUNCTION("""COMPUTED_VALUE"""),4930.0) -> 4930 | I27: =IF(G27>0,(H27-G27)/G27,IF(H27>0,0,0)) -> 0
C28: =IFERROR(__xludf.DUMMYFUNCTION("""COMPUTED_VALUE"""),"AAT PM-8 CI") -> AAT PM-8 CI | D28: =IFERROR(__xludf.DUMMYFUNCTION("IMPORTRANGE(""https://docs.google.com/spreadsheets/d/1DsdxsrBJOk75sDGmXMsLLa15LHA7JaMlvKBZACG-RHY/edit?gid=1280887965#gid=1280887965"",""TESTE!A5"")"),"AAT") -> AAT | E28: 0 | F28: 0 | G28: 0 | H28: =IFERROR(__xludf.DUMMYFUNCTION("""COMPUTED_VALUE"""),4800.0) -> 4800 | I28: =IF(G28>0,(H28-G28)/G28,IF(H28>0,0,0)) -> 0
C29: =IFERROR(__xludf.DUMMYFUNCTION("""COMPUTED_VALUE"""),"AAT PM-9 CI") -> AAT PM-9 CI | D29: =IFERROR(__xludf.DUMMYFUNCTION("IMPORTRANGE(""https://docs.google.com/spreadsheets/d/1DsdxsrBJOk75sDGmXMsLLa15LHA7JaMlvKBZACG-RHY/edit?gid=1280887965#gid=1280887965"",""TESTE!A5"")"),"AAT") -> AAT | E29: 0 | F29: 0 | G29: 0 | H29: =IFERROR(__xludf.DUMMYFUNCTION("""COMPUTED_VALUE"""),6600.0) -> 6600 | I29: =IF(G29>0,(H29-G29)/G29,IF(H29>0,0,0)) -> 0
C30: =IFERROR(__xludf.DUMMYFUNCTION("""COMPUTED_VALUE"""),"AAT PMR-1") -> AAT PMR-1 | D30: =IFERROR(__xludf.DUMMYFUNCTION("IMPORTRANGE(""https://docs.google.com/spreadsheets/d/1DsdxsrBJOk75sDGmXMsLLa15LHA7JaMlvKBZACG-RHY/edit?gid=1280887965#gid=1280887965"",""TESTE!A5"")"),"AAT") -> AAT | E30: 0 | F30: 0 | G30: 0 | H30: =IFERROR(__xludf.DUMMYFUNCTION("""COMPUTED_VALUE"""),3880.0) -> 3880 | I30: =IF(G30>0,(H30-G30)/G30,IF(H30>0,0,0)) -> 0
C31: =IFERROR(__xludf.DUMMYFUNCTION("""COMPUTED_VALUE"""),"AAT PMR-10") -> AAT PMR-10 | D31: =IFERROR(__xludf.DUMMYFUNCTION("IMPORTRANGE(""https://docs.google.com/spreadsheets/d/1DsdxsrBJOk75sDGmXMsLLa15LHA7JaMlvKBZACG-RHY/edit?gid=1280887965#gid=1280887965"",""TESTE!A5"")"),"AAT") -> AAT | E31: 0 | F31: 0 | G31: 0 | H31: =IFERROR(__xludf.DUMMYFUNCTION("""COMPUTED_VALUE"""),15000.0) -> 15000 | I31: =IF(G31>0,(H31-G31)/G31,IF(H31>0,0,0)) -> 0
C32: =IFERROR(__xludf.DUMMYFUNCTION("""COMPUTED_VALUE"""),"AAT PMR-10 G2") -> AAT PMR-10 G2 | D32: =IFERROR(__xludf.DUMMYFUNCTION("IMPORTRANGE(""https://docs.google.com/spreadsheets/d/1DsdxsrBJOk75sDGmXMsLLa15LHA7JaMlvKBZACG-RHY/edit?gid=1280887965#gid=1280887965"",""TESTE!A5"")"),"AAT") -> AAT | E32: 0 | F32: 0 | G32: 0 | H32: =IFERROR(__xludf.DUMMYFUNCTION("""COMPUTED_VALUE"""),15000.0) -> 15000 | I32: =IF(G32>0,(H32-G32)/G32,IF(H32>0,0,0)) -> 0
C33: =IFERROR(__xludf.DUMMYFUNCTION("""COMPUTED_VALUE"""),"AAT PMR-11 G2") -> AAT PMR-11 G2 | D33: =IFERROR(__xludf.DUMMYFUNCTION("IMPORTRANGE(""https://docs.google.com/spreadsheets/d/1DsdxsrBJOk75sDGmXMsLLa15LHA7JaMlvKBZACG-RHY/edit?gid=1280887965#gid=1280887965"",""TESTE!A5"")"),"AAT") -> AAT | E33: 0 | F33: 0 | G33: 0 | H33: =IFERROR(__xludf.DUMMYFUNCTION("""COMPUTED_VALUE"""),13800.0) -> 13800 | I33: =IF(G33>0,(H33-G33)/G33,IF(H33>0,0,0)) -> 0
C34: =IFERROR(__xludf.DUMMYFUNCTION("""COMPUTED_VALUE"""),"AAT PMR-12") -> AAT PMR-12 | D34: =IFERROR(__xludf.DUMMYFUNCTION("IMPORTRANGE(""https://docs.google.com/spreadsheets/d/1DsdxsrBJOk75sDGmXMsLLa15LHA7JaMlvKBZACG-RHY/edit?gid=1280887965#gid=1280887965"",""TESTE!A5"")"),"AAT") -> AAT | E34: 0 | F34: 0 | G34: 0 | H34: =IFERROR(__xludf.DUMMYFUNCTION("""COMPUTED_VALUE"""),16000.0) -> 16000 | I34: =IF(G34>0,(H34-G34)/G34,IF(H34>0,0,0)) -> 0
C35: =IFERROR(__xludf.DUMMYFUNCTION("""COMPUTED_VALUE"""),"AAT PMR-12 G2") -> AAT PMR-12 G2 | D35: =IFERROR(__xludf.DUMMYFUNCTION("IMPORTRANGE(""https://docs.google.com/spreadsheets/d/1DsdxsrBJOk75sDGmXMsLLa15LHA7JaMlvKBZACG-RHY/edit?gid=1280887965#gid=1280887965"",""TESTE!A5"")"),"AAT") -> AAT | E35: 0 | F35: 0 | G35: 0 | H35: =IFERROR(__xludf.DUMMYFUNCTION("""COMPUTED_VALUE"""),16000.0) -> 16000 | I35: =IF(G35>0,(H35-G35)/G35,IF(H35>0,0,0)) -> 0
C36: =IFERROR(__xludf.DUMMYFUNCTION("""COMPUTED_VALUE"""),"AAT PMR-2") -> AAT PMR-2 | D36: =IFERROR(__xludf.DUMMYFUNCTION("IMPORTRANGE(""https://docs.google.com/spreadsheets/d/1DsdxsrBJOk75sDGmXMsLLa15LHA7JaMlvKBZACG-RHY/edit?gid=1280887965#gid=1280887965"",""TESTE!A5"")"),"AAT") -> AAT | E36: 0 | F36: 0 | G36: 0 | H36: =IFERROR(__xludf.DUMMYFUNCTION("""COMPUTED_VALUE"""),3050.0) -> 3050 | I36: =IF(G36>0,(H36-G36)/G36,IF(H36>0,0,0)) -> 0
C37: =IFERROR(__xludf.DUMMYFUNCTION("""COMPUTED_VALUE"""),"AAT PMR-3") -> AAT PMR-3 | D37: =IFERROR(__xludf.DUMMYFUNCTION("IMPORTRANGE(""https://docs.google.com/spreadsheets/d/1DsdxsrBJOk75sDGmXMsLLa15LHA7JaMlvKBZACG-RHY/edit?gid=1280887965#gid=1280887965"",""TESTE!A5"")"),"AAT") -> AAT | E37: 0 | F37: 0 | G37: 0 | H37: =IFERROR(__xludf.DUMMYFUNCTION("""COMPUTED_VALUE"""),2100.0) -> 2100 | I37: =IF(G37>0,(H37-G37)/G37,IF(H37>0,0,0)) -> 0
C38: =IFERROR(__xludf.DUMMYFUNCTION("""COMPUTED_VALUE"""),"AAT PMR-4 G2") -> AAT PMR-4 G2 | D38: =IFERROR(__xludf.DUMMYFUNCTION("IMPORTRANGE(""https://docs.google.com/spreadsheets/d/1DsdxsrBJOk75sDGmXMsLLa15LHA7JaMlvKBZACG-RHY/edit?gid=1280887965#gid=1280887965"",""TESTE!A5"")"),"AAT") -> AAT | E38: 0 | F38: 0 | G38: 0 | H38: =IFERROR(__xludf.DUMMYFUNCTION("""COMPUTED_VALUE"""),9500.0) -> 9500 | I38: =IF(G38>0,(H38-G38)/G38,IF(H38>0,0,0)) -> 0
C39: =IFERROR(__xludf.DUMMYFUNCTION("""COMPUTED_VALUE"""),"AAT PMR-5") -> AAT PMR-5 | D39: =IFERROR(__xludf.DUMMYFUNCTION("IMPORTRANGE(""https://docs.google.com/spreadsheets/d/1DsdxsrBJOk75sDGmXMsLLa15LHA7JaMlvKBZACG-RHY/edit?gid=1280887965#gid=1280887965"",""TESTE!A5"")"),"AAT") -> AAT | E39: 0 | F39: 0 | G39: 0 | H39: =IFERROR(__xludf.DUMMYFUNCTION("""COMPUTED_VALUE"""),12100.0) -> 12100 | I39: =IF(G39>0,(H39-G39)/G39,IF(H39>0,0,0)) -> 0
C40: =IFERROR(__xludf.DUMMYFUNCTION("""COMPUTED_VALUE"""),"AAT PMR-5 G2") -> AAT PMR-5 G2 | D40: =IFERROR(__xludf.DUMMYFUNCTION("IMPORTRANGE(""https://docs.google.com/spreadsheets/d/1DsdxsrBJOk75sDGmXMsLLa15LHA7JaMlvKBZACG-RHY/edit?gid=1280887965#gid=1280887965"",""TESTE!A5"")"),"AAT") -> AAT | E40: 0 | F40: 0 | G40: 0 | H40: =IFERROR(__xludf.DUMMYFUNCTION("""COMPUTED_VALUE"""),12100.0) -> 12100 | I40: =IF(G40>0,(H40-G40)/G40,IF(H40>0,0,0)) -> 0
C41: =IFERROR(__xludf.DUMMYFUNCTION("""COMPUTED_VALUE"""),"AAT PMR-6") -> AAT PMR-6 | D41: =IFERROR(__xludf.DUMMYFUNCTION("IMPORTRANGE(""https://docs.google.com/spreadsheets/d/1DsdxsrBJOk75sDGmXMsLLa15LHA7JaMlvKBZACG-RHY/edit?gid=1280887965#gid=1280887965"",""TESTE!A5"")"),"AAT") -> AAT | E41: 0 | F41: 0 | G41: 0 | H41: =IFERROR(__xludf.DUMMYFUNCTION("""COMPUTED_VALUE"""),10950.0) -> 10950 | I41: =IF(G41>0,(H41-G41)/G41,IF(H41>0,0,0)) -> 0
C42: =IFERROR(__xludf.DUMMYFUNCTION("""COMPUTED_VALUE"""),"AAT PMR-6 G2") -> AAT PMR-6 G2 | D42: =IFERROR(__xludf.DUMMYFUNCTION("IMPORTRANGE(""https://docs.google.com/spreadsheets/d/1DsdxsrBJOk75sDGmXMsLLa15LHA7JaMlvKBZACG-RHY/edit?gid=1280887965#gid=1280887965"",""TESTE!A5"")"),"AAT") -> AAT | E42: 0 | F42: 0 | G42: 0 | H42: =IFERROR(__xludf.DUMMYFUNCTION("""COMPUTED_VALUE"""),10950.0) -> 10950 | I42: =IF(G42>0,(H42-G42)/G42,IF(H42>0,0,0)) -> 0
C43: =IFERROR(__xludf.DUMMYFUNCTION("""COMPUTED_VALUE"""),"AAT PMR-7 G2") -> AAT PMR-7 G2 | D43: =IFERROR(__xludf.DUMMYFUNCTION("IMPORTRANGE(""https://docs.google.com/spreadsheets/d/1DsdxsrBJOk75sDGmXMsLLa15LHA7JaMlvKBZACG-RHY/edit?gid=1280887965#gid=1280887965"",""TESTE!A5"")"),"AAT") -> AAT | E43: 0 | F43: 0 | G43: 0 | H43: =IFERROR(__xludf.DUMMYFUNCTION("""COMPUTED_VALUE"""),12950.0) -> 12950 | I43: =IF(G43>0,(H43-G43)/G43,IF(H43>0,0,0)) -> 0
C44: =IFERROR(__xludf.DUMMYFUNCTION("""COMPUTED_VALUE"""),"AAT PMR-8 G2") -> AAT PMR-8 G2 | D44: =IFERROR(__xludf.DUMMYFUNCTION("IMPORTRANGE(""https://docs.google.com/spreadsheets/d/1DsdxsrBJOk75sDGmXMsLLa15LHA7JaMlvKBZACG-RHY/edit?gid=1280887965#gid=1280887965"",""TESTE!A5"")"),"AAT") -> AAT | E44: 0 | F44: 0 | G44: 0 | H44: =IFERROR(__xludf.DUMMYFUNCTION("""COMPUTED_VALUE"""),7500.0) -> 7500 | I44: =IF(G44>0,(H44-G44)/G44,IF(H44>0,0,0)) -> 0
C45: =IFERROR(__xludf.DUMMYFUNCTION("""COMPUTED_VALUE"""),"AAT PMR-9") -> AAT PMR-9 | D45: =IFERROR(__xludf.DUMMYFUNCTION("IMPORTRANGE(""https://docs.google.com/spreadsheets/d/1DsdxsrBJOk75sDGmXMsLLa15LHA7JaMlvKBZACG-RHY/edit?gid=1280887965#gid=1280887965"",""TESTE!A5"")"),"AAT") -> AAT | E45: 0 | F45: 0 | G45: 0 | H45: =IFERROR(__xludf.DUMMYFUNCTION("""COMPUTED_VALUE"""),12500.0) -> 12500 | I45: =IF(G45>0,(H45-G45)/G45,IF(H45>0,0,0)) -> 0
C46: =IFERROR(__xludf.DUMMYFUNCTION("""COMPUTED_VALUE"""),"AAT PMR-9 G2") -> AAT PMR-9 G2 | D46: =IFERROR(__xludf.DUMMYFUNCTION("IMPORTRANGE(""https://docs.google.com/spreadsheets/d/1DsdxsrBJOk75sDGmXMsLLa15LHA7JaMlvKBZACG-RHY/edit?gid=1280887965#gid=1280887965"",""TESTE!A5"")"),"AAT") -> AAT | E46: 0 | F46: 0 | G46: 0 | H46: =IFERROR(__xludf.DUMMYFUNCTION("""COMPUTED_VALUE"""),12500.0) -> 12500 | I46: =IF(G46>0,(H46-G46)/G46,IF(H46>0,0,0)) -> 0
C47: =IFERROR(__xludf.DUMMYFUNCTION("""COMPUTED_VALUE"""),"AAT PMS-100") -> AAT PMS-100 | D47: =IFERROR(__xludf.DUMMYFUNCTION("IMPORTRANGE(""https://docs.google.com/spreadsheets/d/1DsdxsrBJOk75sDGmXMsLLa15LHA7JaMlvKBZACG-RHY/edit?gid=1280887965#gid=1280887965"",""TESTE!A5"")"),"AAT") -> AAT | E47: 0 | F47: 0 | G47: 0 | H47: =IFERROR(__xludf.DUMMYFUNCTION("""COMPUTED_VALUE"""),2990.0) -> 2990 | I47: =IF(G47>0,(H47-G47)/G47,IF(H47>0,0,0)) -> 0
C48: =IFERROR(__xludf.DUMMYFUNCTION("""COMPUTED_VALUE"""),"AAT PMS-200") -> AAT PMS-200 | D48: =IFERROR(__xludf.DUMMYFUNCTION("IMPORTRANGE(""https://docs.google.com/spreadsheets/d/1DsdxsrBJOk75sDGmXMsLLa15LHA7JaMlvKBZACG-RHY/edit?gid=1280887965#gid=1280887965"",""TESTE!A5"")"),"AAT") -> AAT | E48: 0 | F48: 0 | G48: 0 | H48: =IFERROR(__xludf.DUMMYFUNCTION("""COMPUTED_VALUE"""),3450.0) -> 3450 | I48: =IF(G48>0,(H48-G48)/G48,IF(H48>0,0,0)) -> 0
C49: =IFERROR(__xludf.DUMMYFUNCTION("""COMPUTED_VALUE"""),"AAT PMS-300") -> AAT PMS-300 | D49: =IFERROR(__xludf.DUMMYFUNCTION("IMPORTRANGE(""https://docs.google.com/spreadsheets/d/1DsdxsrBJOk75sDGmXMsLLa15LHA7JaMlvKBZACG-RHY/edit?gid=1280887965#gid=1280887965"",""TESTE!A5"")"),"AAT") -> AAT | E49: 0 | F49: 0 | G49: 0 | H49: =IFERROR(__xludf.DUMMYFUNCTION("""COMPUTED_VALUE"""),4200.0) -> 4200 | I49: =IF(G49>0,(H49-G49)/G49,IF(H49>0,0,0)) -> 0
C50: =IFERROR(__xludf.DUMMYFUNCTION("""COMPUTED_VALUE"""),"AAT PWC-2 G2 120V") -> AAT PWC-2 G2 120V | D50: =IFERROR(__xludf.DUMMYFUNCTION("IMPORTRANGE(""https://docs.google.com/spreadsheets/d/1DsdxsrBJOk75sDGmXMsLLa15LHA7JaMlvKBZACG-RHY/edit?gid=1280887965#gid=1280887965"",""TESTE!A5"")"),"AAT") -> AAT | E50: 0 | F50: 0 | G50: 0 | H50: =IFERROR(__xludf.DUMMYFUNCTION("""COMPUTED_VALUE"""),1980.0) -> 1980 | I50: =IF(G50>0,(H50-G50)/G50,IF(H50>0,0,0)) -> 0
C51: =IFERROR(__xludf.DUMMYFUNCTION("""COMPUTED_VALUE"""),"AAT PWC-2 G2 220V") -> AAT PWC-2 G2 220V | D51: =IFERROR(__xludf.DUMMYFUNCTION("IMPORTRANGE(""https://docs.google.com/spreadsheets/d/1DsdxsrBJOk75sDGmXMsLLa15LHA7JaMlvKBZACG-RHY/edit?gid=1280887965#gid=1280887965"",""TESTE!A5"")"),"AAT") -> AAT | E51: 0 | F51: 0 | G51: 0 | H51: =IFERROR(__xludf.DUMMYFUNCTION("""COMPUTED_VALUE"""),1980.0) -> 1980 | I51: =IF(G51>0,(H51-G51)/G51,IF(H51>0,0,0)) -> 0
C52: =IFERROR(__xludf.DUMMYFUNCTION("""COMPUTED_VALUE"""),"AAT PWC-3 G2") -> AAT PWC-3 G2 | D52: =IFERROR(__xludf.DUMMYFUNCTION("IMPORTRANGE(""https://docs.google.com/spreadsheets/d/1DsdxsrBJOk75sDGmXMsLLa15LHA7JaMlvKBZACG-RHY/edit?gid=1280887965#gid=1280887965"",""TESTE!A5"")"),"AAT") -> AAT | E52: 0 | F52: 0 | G52: 0 | H52: =IFERROR(__xludf.DUMMYFUNCTION("""COMPUTED_VALUE"""),3100.0) -> 3100 | I52: =IF(G52>0,(H52-G52)/G52,IF(H52>0,0,0)) -> 0
C53: =IFERROR(__xludf.DUMMYFUNCTION("""COMPUTED_VALUE"""),"AAT PWC-4 G2") -> AAT PWC-4 G2 | D53: =IFERROR(__xludf.DUMMYFUNCTION("IMPORTRANGE(""https://docs.google.com/spreadsheets/d/1DsdxsrBJOk75sDGmXMsLLa15LHA7JaMlvKBZACG-RHY/edit?gid=1280887965#gid=1280887965"",""TESTE!A5"")"),"AAT") -> AAT | E53: 0 | F53: 0 | G53: 0 | H53: =IFERROR(__xludf.DUMMYFUNCTION("""COMPUTED_VALUE"""),3700.0) -> 3700 | I53: =IF(G53>0,(H53-G53)/G53,IF(H53>0,0,0)) -> 0
C54: =IFERROR(__xludf.DUMMYFUNCTION("""COMPUTED_VALUE"""),"AAT PWC-6") -> AAT PWC-6 | D54: =IFERROR(__xludf.DUMMYFUNCTION("IMPORTRANGE(""https://docs.google.com/spreadsheets/d/1DsdxsrBJOk75sDGmXMsLLa15LHA7JaMlvKBZACG-RHY/edit?gid=1280887965#gid=1280887965"",""TESTE!A5"")"),"AAT") -> AAT | E54: 0 | F54: 0 | G54: 0 | H54: =IFERROR(__xludf.DUMMYFUNCTION("""COMPUTED_VALUE"""),3480.0) -> 3480 | I54: =IF(G54>0,(H54-G54)/G54,IF(H54>0,0,0)) -> 0
C55: =IFERROR(__xludf.DUMMYFUNCTION("""COMPUTED_VALUE"""),"AAT PWC-7") -> AAT PWC-7 | D55: =IFERROR(__xludf.DUMMYFUNCTION("IMPORTRANGE(""https://docs.google.com/spreadsheets/d/1DsdxsrBJOk75sDGmXMsLLa15LHA7JaMlvKBZACG-RHY/edit?gid=1280887965#gid=1280887965"",""TESTE!A5"")"),"AAT") -> AAT | E55: 0 | F55: 0 | G55: 0 | H55: =IFERROR(__xludf.DUMMYFUNCTION("""COMPUTED_VALUE"""),4200.0) -> 4200 | I55: =IF(G55>0,(H55-G55)/G55,IF(H55>0,0,0)) -> 0
C56: =IFERROR(__xludf.DUMMYFUNCTION("""COMPUTED_VALUE"""),"AAT PWC-7 G2") -> AAT PWC-7 G2 | D56: =IFERROR(__xludf.DUMMYFUNCTION("IMPORTRANGE(""https://docs.google.com/spreadsheets/d/1DsdxsrBJOk75sDGmXMsLLa15LHA7JaMlvKBZACG-RHY/edit?gid=1280887965#gid=1280887965"",""TESTE!A5"")"),"AAT") -> AAT | E56: 0 | F56: 0 | G56: 0 | H56: =IFERROR(__xludf.DUMMYFUNCTION("""COMPUTED_VALUE"""),4200.0) -> 4200 | I56: =IF(G56>0,(H56-G56)/G56,IF(H56>0,0,0)) -> 0
C57: =IFERROR(__xludf.DUMMYFUNCTION("""COMPUTED_VALUE"""),"AAT PWC-8 220V") -> AAT PWC-8 220V | D57: =IFERROR(__xludf.DUMMYFUNCTION("IMPORTRANGE(""https://docs.google.com/spreadsheets/d/1DsdxsrBJOk75sDGmXMsLLa15LHA7JaMlvKBZACG-RHY/edit?gid=1280887965#gid=1280887965"",""TESTE!A5"")"),"AAT") -> AAT | E57: 0 | F57: 0 | G57: 0 | H57: =IFERROR(__xludf.DUMMYFUNCTION("""COMPUTED_VALUE"""),6600.0) -> 6600 | I57: =IF(G57>0,(H57-G57)/G57,IF(H57>0,0,0)) -> 0
C58: =IFERROR(__xludf.DUMMYFUNCTION("""COMPUTED_VALUE"""),"AAT SLIM 6") -> AAT SLIM 6 | D58: =IFERROR(__xludf.DUMMYFUNCTION("IMPORTRANGE(""https://docs.google.com/spreadsheets/d/1DsdxsrBJOk75sDGmXMsLLa15LHA7JaMlvKBZACG-RHY/edit?gid=1280887965#gid=1280887965"",""TESTE!A5"")"),"AAT") -> AAT | E58: 0 | F58: 0 | G58: 0 | H58: =IFERROR(__xludf.DUMMYFUNCTION("""COMPUTED_VALUE"""),780.0) -> 780 | I58: =IF(G58>0,(H58-G58)/G58,IF(H58>0,0,0)) -> 0
C59: =IFERROR(__xludf.DUMMYFUNCTION("""COMPUTED_VALUE"""),"AAT SLIM 6”") -> AAT SLIM 6” | D59: =IFERROR(__xludf.DUMMYFUNCTION("IMPORTRANGE(""https://docs.google.com/spreadsheets/d/1DsdxsrBJOk75sDGmXMsLLa15LHA7JaMlvKBZACG-RHY/edit?gid=1280887965#gid=1280887965"",""TESTE!A5"")"),"AAT") -> AAT | E59: 0 | F59: 0 | G59: 0 | H59: =IFERROR(__xludf.DUMMYFUNCTION("""COMPUTED_VALUE"""),780.0) -> 780 | I59: =IF(G59>0,(H59-G59)/G59,IF(H59>0,0,0)) -> 0
C60: =IFERROR(__xludf.DUMMYFUNCTION("IMPORTRANGE(""https://docs.google.com/spreadsheets/d/17pV1h3QXEhKsouzqT-wmZrwWCzREFYcQVORu3OKO97k/edit?gid=250502500#gid=250502500"",""PRODUTOS!C2:C101"")"),"Acoplador para respiro modelos TS") -> Acoplador para respiro modelos TS | D60: =IFERROR(__xludf.DUMMYFUNCTION("IMPORTRANGE(""https://docs.google.com/spreadsheets/d/17pV1h3QXEhKsouzqT-wmZrwWCzREFYcQVORu3OKO97k/edit?gid=250502500#gid=250502500"",""PRODUTOS!F2"")"),"AERTECNICA") -> AERTECNICA | E60: 0 | F60: 0 | G60: 0 | H60: =IFERROR(__xludf.DUMMYFUNCTION("IMPORTRANGE(""https://docs.google.com/spreadsheets/d/17pV1h3QXEhKsouzqT-wmZrwWCzREFYcQVORu3OKO97k/edit?gid=250502500#gid=250502500"",""PRODUTOS!E2:E101"")"),110.94) -> 110.94 | I60: =IF(G60>0,(H60-G60)/G60,IF(H60>0,0,0)) -> 0
C61: =IFERROR(__xludf.DUMMYFUNCTION("""COMPUTED_VALUE"""),"Base de Tomada Eclettis com conexão") -> Base de Tomada Eclettis com conexão | D61: =IFERROR(__xludf.DUMMYFUNCTION("IMPORTRANGE(""https://docs.google.com/spreadsheets/d/17pV1h3QXEhKsouzqT-wmZrwWCzREFYcQVORu3OKO97k/edit?gid=250502500#gid=250502500"",""PRODUTOS!F2"")"),"AERTECNICA") -> AERTECNICA | E61: 0 | F61: 0 | G61: 0 | H61: =IFERROR(__xludf.DUMMYFUNCTION("""COMPUTED_VALUE"""),480.06) -> 480.06 | I61: =IF(G61>0,(H61-G61)/G61,IF(H61>0,0,0)) -> 0
C62: =IFERROR(__xludf.DUMMYFUNCTION("""COMPUTED_VALUE"""),"Base de Tomada New Air com conexão Curva") -> Base de Tomada New Air com conexão Curva | D62: =IFERROR(__xludf.DUMMYFUNCTION("IMPORTRANGE(""https://docs.google.com/spreadsheets/d/17pV1h3QXEhKsouzqT-wmZrwWCzREFYcQVORu3OKO97k/edit?gid=250502500#gid=250502500"",""PRODUTOS!F2"")"),"AERTECNICA") -> AERTECNICA | E62: 0 | F62: 0 | G62: 0 | H62: =IFERROR(__xludf.DUMMYFUNCTION("""COMPUTED_VALUE"""),61.38) -> 61.38 | I62: =IF(G62>0,(H62-G62)/G62,IF(H62>0,0,0)) -> 0
C63: =IFERROR(__xludf.DUMMYFUNCTION("""COMPUTED_VALUE"""),"Base de tomada PRATICO com 2"" para parede de alvenaria") -> Base de tomada PRATICO com 2" para parede de alvenaria | D63: =IFERROR(__xludf.DUMMYFUNCTION("IMPORTRANGE(""https://docs.google.com/spreadsheets/d/17pV1h3QXEhKsouzqT-wmZrwWCzREFYcQVORu3OKO97k/edit?gid=250502500#gid=250502500"",""PRODUTOS!F2"")"),"AERTECNICA") -> AERTECNICA | E63: 0 | F63: 0 | G63: 0 | H63: =IFERROR(__xludf.DUMMYFUNCTION("""COMPUTED_VALUE"""),533.33) -> 533.33 | I63: =IF(G63>0,(H63-G63)/G63,IF(H63>0,0,0)) -> 0
C64: =IFERROR(__xludf.DUMMYFUNCTION("""COMPUTED_VALUE"""),"Caixa com Porta de Embutir") -> Caixa com Porta de Embutir | D64: =IFERROR(__xludf.DUMMYFUNCTION("IMPORTRANGE(""https://docs.google.com/spreadsheets/d/17pV1h3QXEhKsouzqT-wmZrwWCzREFYcQVORu3OKO97k/edit?gid=250502500#gid=250502500"",""PRODUTOS!F2"")"),"AERTECNICA") -> AERTECNICA | E64: 0 | F64: 0 | G64: 0 | H64: =IFERROR(__xludf.DUMMYFUNCTION("""COMPUTED_VALUE"""),785.73) -> 785.73 | I64: =IF(G64>0,(H64-G64)/G64,IF(H64>0,0,0)) -> 0
C65: =IFERROR(__xludf.DUMMYFUNCTION("""COMPUTED_VALUE"""),"CAPA DE FECHAMENTO EM PVC") -> CAPA DE FECHAMENTO EM PVC | D65: =IFERROR(__xludf.DUMMYFUNCTION("IMPORTRANGE(""https://docs.google.com/spreadsheets/d/17pV1h3QXEhKsouzqT-wmZrwWCzREFYcQVORu3OKO97k/edit?gid=250502500#gid=250502500"",""PRODUTOS!F2"")"),"AERTECNICA") -> AERTECNICA | E65: 0 | F65: 0 | G65: 0 | H65: =IFERROR(__xludf.DUMMYFUNCTION("""COMPUTED_VALUE"""),55.56) -> 55.56 | I65: =IF(G65>0,(H65-G65)/G65,IF(H65>0,0,0)) -> 0
C66: =IFERROR(__xludf.DUMMYFUNCTION("""COMPUTED_VALUE"""),"CENTRAL PERFETTO - CLASSIC") -> CENTRAL PERFETTO - CLASSIC | D66: =IFERROR(__xludf.DUMMYFUNCTION("IMPORTRANGE(""https://docs.google.com/spreadsheets/d/17pV1h3QXEhKsouzqT-wmZrwWCzREFYcQVORu3OKO97k/edit?gid=250502500#gid=250502500"",""PRODUTOS!F2"")"),"AERTECNICA") -> AERTECNICA | E66: 0 | F66: 0 | G66: 0 | H66: =IFERROR(__xludf.DUMMYFUNCTION("""COMPUTED_VALUE"""),6651.52) -> 6651.52 | I66: =IF(G66>0,(H66-G66)/G66,IF(H66>0,0,0)) -> 0
C67: =IFERROR(__xludf.DUMMYFUNCTION("""COMPUTED_VALUE"""),"Central de Aspiração de Embutir Q200 - 6 pontos (area recomendada de aproximadamente 300 m2) - distancia maxima 25 metros") -> Central de Aspiração de Embutir Q200 - 6 pontos (area recomendada de aproximadamente 300 m2) - distancia maxima 25 metros | D67: =IFERROR(__xludf.DUMMYFUNCTION("IMPORTRANGE(""https://docs.google.com/spreadsheets/d/17pV1h3QXEhKsouzqT-wmZrwWCzREFYcQVORu3OKO97k/edit?gid=250502500#gid=250502500"",""PRODUTOS!F2"")"),"AERTECNICA") -> AERTECNICA | E67: 0 | F67: 0 | G67: 0 | H67: =IFERROR(__xludf.DUMMYFUNCTION("""COMPUTED_VALUE"""),4530.3) -> 4530.3 | I67: =IF(G67>0,(H67-G67)/G67,IF(H67>0,0,0)) -> 0
C68: =IFERROR(__xludf.DUMMYFUNCTION("""COMPUTED_VALUE"""),"Central Perfetto Classic TC3 - 16 pontos (área recomendade de aproximadamente 800 m2) - distância máxima 45 metros") -> Central Perfetto Classic TC3 - 16 pontos (área recomendade de aproximadamente 800 m2) - distância máxima 45 metros | D68: =IFERROR(__xludf.DUMMYFUNCTION("IMPORTRANGE(""https://docs.google.com/spreadsheets/d/17pV1h3QXEhKsouzqT-wmZrwWCzREFYcQVORu3OKO97k/edit?gid=250502500#gid=250502500"",""PRODUTOS!F2"")"),"AERTECNICA") -> AERTECNICA | E68: 0 | F68: 0 | G68: 0 | H68: =IFERROR(__xludf.DUMMYFUNCTION("""COMPUTED_VALUE"""),15909.09) -> 15909.09 | I68: =IF(G68>0,(H68-G68)/G68,IF(H68>0,0,0)) -> 0
C69: =IFERROR(__xludf.DUMMYFUNCTION("""COMPUTED_VALUE"""),"Central Perfetto Classic TC4 - 25 pontos (área recomendada de aproximadamente 1250 m2) - distância máxima 55 metros") -> Central Perfetto Classic TC4 - 25 pontos (área recomendada de aproximadamente 1250 m2) - distância máxima 55 metros | D69: =IFERROR(__xludf.DUMMYFUNCTION("IMPORTRANGE(""https://docs.google.com/spreadsheets/d/17pV1h3QXEhKsouzqT-wmZrwWCzREFYcQVORu3OKO97k/edit?gid=250502500#gid=250502500"",""PRODUTOS!F2"")"),"AERTECNICA") -> AERTECNICA | E69: 0 | F69: 0 | G69: 0 | H69: =IFERROR(__xludf.DUMMYFUNCTION("""COMPUTED_VALUE"""),18939.39) -> 18939.39 | I69: =IF(G69>0,(H69-G69)/G69,IF(H69>0,0,0)) -> 0
C70: =IFERROR(__xludf.DUMMYFUNCTION("""COMPUTED_VALUE"""),"Central Perfetto Inox TX2 - 10 pontos (área recomendada de aproximadamente 500 m2) - distância máxima 35 metros SOB ENCOMENDA") -> Central Perfetto Inox TX2 - 10 pontos (área recomendada de aproximadamente 500 m2) - distância máxima 35 metros SOB ENCOMENDA | D70: =IFERROR(__xludf.DUMMYFUNCTION("IMPORTRANGE(""https://docs.google.com/spreadsheets/d/17pV1h3QXEhKsouzqT-wmZrwWCzREFYcQVORu3OKO97k/edit?gid=250502500#gid=250502500"",""PRODUTOS!F2"")"),"AERTECNICA") -> AERTECNICA | E70: 0 | F70: 0 | G70: 0 | H70: =IFERROR(__xludf.DUMMYFUNCTION("""COMPUTED_VALUE"""),10874.24) -> 10874.24 | I70: =IF(G70>0,(H70-G70)/G70,IF(H70>0,0,0)) -> 0
C71: =IFERROR(__xludf.DUMMYFUNCTION("""COMPUTED_VALUE"""),"Central Perfetto Inox TX3 - 16 pontos (área recomendada de aproximadamente 800 m2) - distância máxima 45 metros SOB ENCOMENDA") -> Central Perfetto Inox TX3 - 16 pontos (área recomendada de aproximadamente 800 m2) - distância máxima 45 metros SOB ENCOMENDA | D71: =IFERROR(__xludf.DUMMYFUNCTION("IMPORTRANGE(""https://docs.google.com/spreadsheets/d/17pV1h3QXEhKsouzqT-wmZrwWCzREFYcQVORu3OKO97k/edit?gid=250502500#gid=250502500"",""PRODUTOS!F2"")"),"AERTECNICA") -> AERTECNICA | E71: 0 | F71: 0 | G71: 0 | H71: =IFERROR(__xludf.DUMMYFUNCTION("""COMPUTED_VALUE"""),11496.97) -> 11496.97 | I71: =IF(G71>0,(H71-G71)/G71,IF(H71>0,0,0)) -> 0
C72: =IFERROR(__xludf.DUMMYFUNCTION("""COMPUTED_VALUE"""),"Central Perfetto Inox TX4 - 25 pontos (área recomendada de aproximadamente 1250 m2) - distância máxima 55 metros") -> Central Perfetto Inox TX4 - 25 pontos (área recomendada de aproximadamente 1250 m2) - distância máxima 55 metros | D72: =IFERROR(__xludf.DUMMYFUNCTION("IMPORTRANGE(""https://docs.google.com/spreadsheets/d/17pV1h3QXEhKsouzqT-wmZrwWCzREFYcQVORu3OKO97k/edit?gid=250502500#gid=250502500"",""PRODUTOS!F2"")"),"AERTECNICA") -> AERTECNICA | E72: 0 | F72: 0 | G72: 0 | H72: =IFERROR(__xludf.DUMMYFUNCTION("""COMPUTED_VALUE"""),15819.7) -> 15819.7 | I72: =IF(G72>0,(H72-G72)/G72,IF(H72>0,0,0)) -> 0
C73: =IFERROR(__xludf.DUMMYFUNCTION("""COMPUTED_VALUE"""),"CENTRAL STUDIO - QB") -> CENTRAL STUDIO - QB | D73: =IFERROR(__xludf.DUMMYFUNCTION("IMPORTRANGE(""https://docs.google.com/spreadsheets/d/17pV1h3QXEhKsouzqT-wmZrwWCzREFYcQVORu3OKO97k/edit?gid=250502500#gid=250502500"",""PRODUTOS!F2"")"),"AERTECNICA") -> AERTECNICA | E73: 0 | F73: 0 | G73: 0 | H73: =IFERROR(__xludf.DUMMYFUNCTION("""COMPUTED_VALUE"""),2060.61) -> 2060.61 | I73: =IF(G73>0,(H73-G73)/G73,IF(H73>0,0,0)) -> 0
C74: =IFERROR(__xludf.DUMMYFUNCTION("""COMPUTED_VALUE"""),"Central Studio TC2 - 10 pontos (área recomendada de aproximadamente 500 m2) - distÂncia máxima 35 metros SEM ESTOQUE") -> Central Studio TC2 - 10 pontos (área recomendada de aproximadamente 500 m2) - distÂncia máxima 35 metros SEM ESTOQUE | D74: =IFERROR(__xludf.DUMMYFUNCTION("IMPORTRANGE(""https://docs.google.com/spreadsheets/d/17pV1h3QXEhKsouzqT-wmZrwWCzREFYcQVORu3OKO97k/edit?gid=250502500#gid=250502500"",""PRODUTOS!F2"")"),"AERTECNICA") -> AERTECNICA | E74: 0 | F74: 0 | G74: 0 | H74: =IFERROR(__xludf.DUMMYFUNCTION("""COMPUTED_VALUE"""),5861.27) -> 5861.27 | I74: =IF(G74>0,(H74-G74)/G74,IF(H74>0,0,0)) -> 0
C75: =IFERROR(__xludf.DUMMYFUNCTION("""COMPUTED_VALUE"""),"Central Studio TS1 - 6 pontos (área recomendada de aproximadamente 300 m2) - distância máxima 25 metros") -> Central Studio TS1 - 6 pontos (área recomendada de aproximadamente 300 m2) - distância máxima 25 metros | D75: =IFERROR(__xludf.DUMMYFUNCTION("IMPORTRANGE(""https://docs.google.com/spreadsheets/d/17pV1h3QXEhKsouzqT-wmZrwWCzREFYcQVORu3OKO97k/edit?gid=250502500#gid=250502500"",""PRODUTOS!F2"")"),"AERTECNICA") -> AERTECNICA | E75: 0 | F75: 0 | G75: 0 | H75: =IFERROR(__xludf.DUMMYFUNCTION("""COMPUTED_VALUE"""),5227.27) -> 5227.27 | I75: =IF(G75>0,(H75-G75)/G75,IF(H75>0,0,0)) -> 0
C76: =IFERROR(__xludf.DUMMYFUNCTION("""COMPUTED_VALUE"""),"Central Studio TS2 - 10 pontos (área recomendada de aproximadamente 500 m2) - distância máxima 35 metros") -> Central Studio TS2 - 10 pontos (área recomendada de aproximadamente 500 m2) - distância máxima 35 metros | D76: =IFERROR(__xludf.DUMMYFUNCTION("IMPORTRANGE(""https://docs.google.com/spreadsheets/d/17pV1h3QXEhKsouzqT-wmZrwWCzREFYcQVORu3OKO97k/edit?gid=250502500#gid=250502500"",""PRODUTOS!F2"")"),"AERTECNICA") -> AERTECNICA | E76: 0 | F76: 0 | G76: 0 | H76: =IFERROR(__xludf.DUMMYFUNCTION("""COMPUTED_VALUE"""),6857.58) -> 6857.58 | I76: =IF(G76>0,(H76-G76)/G76,IF(H76>0,0,0)) -> 0
C77: =IFERROR(__xludf.DUMMYFUNCTION("""COMPUTED_VALUE"""),"Central Studio TS4 - 25 pontos (área recomendada de aproximadamente 1250 m2) - distância máxima 45 metros") -> Central Studio TS4 - 25 pontos (área recomendada de aproximadamente 1250 m2) - distância máxima 45 metros | D77: =IFERROR(__xludf.DUMMYFUNCTION("IMPORTRANGE(""https://docs.google.com/spreadsheets/d/17pV1h3QXEhKsouzqT-wmZrwWCzREFYcQVORu3OKO97k/edit?gid=250502500#gid=250502500"",""PRODUTOS!F2"")"),"AERTECNICA") -> AERTECNICA | E77: 0 | F77: 0 | G77: 0 | H77: =IFERROR(__xludf.DUMMYFUNCTION("""COMPUTED_VALUE"""),7454.55) -> 7454.55 | I77: =IF(G77>0,(H77-G77)/G77,IF(H77>0,0,0)) -> 0
C78: =IFERROR(__xludf.DUMMYFUNCTION("""COMPUTED_VALUE"""),"Conexão activador giratório mangueira-tomada Ø 32") -> Conexão activador giratório mangueira-tomada Ø 32 | D78: =IFERROR(__xludf.DUMMYFUNCTION("IMPORTRANGE(""https://docs.google.com/spreadsheets/d/17pV1h3QXEhKsouzqT-wmZrwWCzREFYcQVORu3OKO97k/edit?gid=250502500#gid=250502500"",""PRODUTOS!F2"")"),"AERTECNICA") -> AERTECNICA | E78: 0 | F78: 0 | G78: 0 | H78: =IFERROR(__xludf.DUMMYFUNCTION("""COMPUTED_VALUE"""),148.33) -> 148.33 | I78: =IF(G78>0,(H78-G78)/G78,IF(H78>0,0,0)) -> 0
C79: =IFERROR(__xludf.DUMMYFUNCTION("""COMPUTED_VALUE"""),"Conexão curva de plástico com regulador de pressão, Ø 32") -> Conexão curva de plástico com regulador de pressão, Ø 32 | D79: =IFERROR(__xludf.DUMMYFUNCTION("IMPORTRANGE(""https://docs.google.com/spreadsheets/d/17pV1h3QXEhKsouzqT-wmZrwWCzREFYcQVORu3OKO97k/edit?gid=250502500#gid=250502500"",""PRODUTOS!F2"")"),"AERTECNICA") -> AERTECNICA | E79: 0 | F79: 0 | G79: 0 | H79: =IFERROR(__xludf.DUMMYFUNCTION("""COMPUTED_VALUE"""),175.0) -> 175 | I79: =IF(G79>0,(H79-G79)/G79,IF(H79>0,0,0)) -> 0
C80: =IFERROR(__xludf.DUMMYFUNCTION("""COMPUTED_VALUE"""),"Conexão para aplicar as escovas para animais directamente na mangueira Ø 32") -> Conexão para aplicar as escovas para animais directamente na mangueira Ø 32 | D80: =IFERROR(__xludf.DUMMYFUNCTION("IMPORTRANGE(""https://docs.google.com/spreadsheets/d/17pV1h3QXEhKsouzqT-wmZrwWCzREFYcQVORu3OKO97k/edit?gid=250502500#gid=250502500"",""PRODUTOS!F2"")"),"AERTECNICA") -> AERTECNICA | E80: 0 | F80: 0 | G80: 0 | H80: =IFERROR(__xludf.DUMMYFUNCTION("""COMPUTED_VALUE"""),314.33) -> 314.33 | I80: =IF(G80>0,(H80-G80)/G80,IF(H80>0,0,0)) -> 0
C81: =IFERROR(__xludf.DUMMYFUNCTION("""COMPUTED_VALUE"""),"CONEXÃO PARA EXAUTÃO DO AR EM PVC") -> CONEXÃO PARA EXAUTÃO DO AR EM PVC | D81: =IFERROR(__xludf.DUMMYFUNCTION("IMPORTRANGE(""https://docs.google.com/spreadsheets/d/17pV1h3QXEhKsouzqT-wmZrwWCzREFYcQVORu3OKO97k/edit?gid=250502500#gid=250502500"",""PRODUTOS!F2"")"),"AERTECNICA") -> AERTECNICA | E81: 0 | F81: 0 | G81: 0 | H81: =IFERROR(__xludf.DUMMYFUNCTION("""COMPUTED_VALUE"""),13.36) -> 13.36 | I81: =IF(G81>0,(H81-G81)/G81,IF(H81>0,0,0)) -> 0
C82: =IFERROR(__xludf.DUMMYFUNCTION("""COMPUTED_VALUE"""),"Conjunto de pré-instalação 1 Ponto de tomada PRATICO com 2"" para gesso cartonado") -> Conjunto de pré-instalação 1 Ponto de tomada PRATICO com 2" para gesso cartonado | D82: =IFERROR(__xludf.DUMMYFUNCTION("IMPORTRANGE(""https://docs.google.com/spreadsheets/d/17pV1h3QXEhKsouzqT-wmZrwWCzREFYcQVORu3OKO97k/edit?gid=250502500#gid=250502500"",""PRODUTOS!F2"")"),"AERTECNICA") -> AERTECNICA | E82: 0 | F82: 0 | G82: 0 | H82: =IFERROR(__xludf.DUMMYFUNCTION("""COMPUTED_VALUE"""),1933.33) -> 1933.33 | I82: =IF(G82>0,(H82-G82)/G82,IF(H82>0,0,0)) -> 0
C83: =IFERROR(__xludf.DUMMYFUNCTION("""COMPUTED_VALUE"""),"Conjunto de pré-instalação 1 Ponto de tomada PRATICO com 2"" para parede de alvenaria") -> Conjunto de pré-instalação 1 Ponto de tomada PRATICO com 2" para parede de alvenaria | D83: =IFERROR(__xludf.DUMMYFUNCTION("IMPORTRANGE(""https://docs.google.com/spreadsheets/d/17pV1h3QXEhKsouzqT-wmZrwWCzREFYcQVORu3OKO97k/edit?gid=250502500#gid=250502500"",""PRODUTOS!F2"")"),"AERTECNICA") -> AERTECNICA | E83: 0 | F83: 0 | G83: 0 | H83: =IFERROR(__xludf.DUMMYFUNCTION("""COMPUTED_VALUE"""),3081.82) -> 3081.82 | I83: =IF(G83>0,(H83-G83)/G83,IF(H83>0,0,0)) -> 0
C84: =IFERROR(__xludf.DUMMYFUNCTION("""COMPUTED_VALUE"""),"Curva tomada Vac Pan") -> Curva tomada Vac Pan | D84: =IFERROR(__xludf.DUMMYFUNCTION("IMPORTRANGE(""https://docs.google.com/spreadsheets/d/17pV1h3QXEhKsouzqT-wmZrwWCzREFYcQVORu3OKO97k/edit?gid=250502500#gid=250502500"",""PRODUTOS!F2"")"),"AERTECNICA") -> AERTECNICA | E84: 0 | F84: 0 | G84: 0 | H84: =IFERROR(__xludf.DUMMYFUNCTION("""COMPUTED_VALUE"""),34.61) -> 34.61 | I84: =IF(G84>0,(H84-G84)/G84,IF(H84>0,0,0)) -> 0
C85: =IFERROR(__xludf.DUMMYFUNCTION("""COMPUTED_VALUE"""),"Curva Longa PVC 90o FF - 50 mm") -> Curva Longa PVC 90o FF - 50 mm | D85: =IFERROR(__xludf.DUMMYFUNCTION("IMPORTRANGE(""https://docs.google.com/spreadsheets/d/17pV1h3QXEhKsouzqT-wmZrwWCzREFYcQVORu3OKO97k/edit?gid=250502500#gid=250502500"",""PRODUTOS!F2"")"),"AERTECNICA") -> AERTECNICA | E85: 0 | F85: 0 | G85: 0 | H85: =IFERROR(__xludf.DUMMYFUNCTION("""COMPUTED_VALUE"""),8.45) -> 8.45 | I85: =IF(G85>0,(H85-G85)/G85,IF(H85>0,0,0)) -> 0
C86: =IFERROR(__xludf.DUMMYFUNCTION("""COMPUTED_VALUE"""),"Curva Longa PVC 90o FF - 50 mm - Caixa com 80 peças") -> Curva Longa PVC 90o FF - 50 mm - Caixa com 80 peças | D86: =IFERROR(__xludf.DUMMYFUNCTION("IMPORTRANGE(""https://docs.google.com/spreadsheets/d/17pV1h3QXEhKsouzqT-wmZrwWCzREFYcQVORu3OKO97k/edit?gid=250502500#gid=250502500"",""PRODUTOS!F2"")"),"AERTECNICA") -> AERTECNICA | E86: 0 | F86: 0 | G86: 0 | H86: =IFERROR(__xludf.DUMMYFUNCTION("""COMPUTED_VALUE"""),579.26) -> 579.26 | I86: =IF(G86>0,(H86-G86)/G86,IF(H86>0,0,0)) -> 0
C87: =IFERROR(__xludf.DUMMYFUNCTION("""COMPUTED_VALUE"""),"Curva PVC Ø 50 a 45° FF") -> Curva PVC Ø 50 a 45° FF | D87: =IFERROR(__xludf.DUMMYFUNCTION("IMPORTRANGE(""https://docs.google.com/spreadsheets/d/17pV1h3QXEhKsouzqT-wmZrwWCzREFYcQVORu3OKO97k/edit?gid=250502500#gid=250502500"",""PRODUTOS!F2"")"),"AERTECNICA") -> AERTECNICA | E87: 0 | F87: 0 | G87: 0 | H87: =IFERROR(__xludf.DUMMYFUNCTION("""COMPUTED_VALUE"""),6.88) -> 6.88 | I87: =IF(G87>0,(H87-G87)/G87,IF(H87>0,0,0)) -> 0
C88: =IFERROR(__xludf.DUMMYFUNCTION("""COMPUTED_VALUE"""),"Curva PVC Ø 50 a 45° FF - Caixa com 92 peças") -> Curva PVC Ø 50 a 45° FF - Caixa com 92 peças | D88: =IFERROR(__xludf.DUMMYFUNCTION("IMPORTRANGE(""https://docs.google.com/spreadsheets/d/17pV1h3QXEhKsouzqT-wmZrwWCzREFYcQVORu3OKO97k/edit?gid=250502500#gid=250502500"",""PRODUTOS!F2"")"),"AERTECNICA") -> AERTECNICA | E88: 0 | F88: 0 | G88: 0 | H88: =IFERROR(__xludf.DUMMYFUNCTION("""COMPUTED_VALUE"""),537.5) -> 537.5 | I88: =IF(G88>0,(H88-G88)/G88,IF(H88>0,0,0)) -> 0
C89: =IFERROR(__xludf.DUMMYFUNCTION("""COMPUTED_VALUE"""),"Derivação PVC 45o FF - 50 mm") -> Derivação PVC 45o FF - 50 mm | D89: =IFERROR(__xludf.DUMMYFUNCTION("IMPORTRANGE(""https://docs.google.com/spreadsheets/d/17pV1h3QXEhKsouzqT-wmZrwWCzREFYcQVORu3OKO97k/edit?gid=250502500#gid=250502500"",""PRODUTOS!F2"")"),"AERTECNICA") -> AERTECNICA | E89: 0 | F89: 0 | G89: 0 | H89: =IFERROR(__xludf.DUMMYFUNCTION("""COMPUTED_VALUE"""),11.77) -> 11.77 | I89: =IF(G89>0,(H89-G89)/G89,IF(H89>0,0,0)) -> 0
C90: =IFERROR(__xludf.DUMMYFUNCTION("""COMPUTED_VALUE"""),"Derivação PVC 45o FF - 50 mm - Caixa com 74 peças") -> Derivação PVC 45o FF - 50 mm - Caixa com 74 peças | D90: =IFERROR(__xludf.DUMMYFUNCTION("IMPORTRANGE(""https://docs.google.com/spreadsheets/d/17pV1h3QXEhKsouzqT-wmZrwWCzREFYcQVORu3OKO97k/edit?gid=250502500#gid=250502500"",""PRODUTOS!F2"")"),"AERTECNICA") -> AERTECNICA | E90: 0 | F90: 0 | G90: 0 | H90: =IFERROR(__xludf.DUMMYFUNCTION("""COMPUTED_VALUE"""),781.35) -> 781.35 | I90: =IF(G90>0,(H90-G90)/G90,IF(H90>0,0,0)) -> 0
C91: =IFERROR(__xludf.DUMMYFUNCTION("""COMPUTED_VALUE"""),"Derivação PVC 90o FF - 50 mm") -> Derivação PVC 90o FF - 50 mm | D91: =IFERROR(__xludf.DUMMYFUNCTION("IMPORTRANGE(""https://docs.google.com/spreadsheets/d/17pV1h3QXEhKsouzqT-wmZrwWCzREFYcQVORu3OKO97k/edit?gid=250502500#gid=250502500"",""PRODUTOS!F2"")"),"AERTECNICA") -> AERTECNICA | E91: 0 | F91: 0 | G91: 0 | H91: =IFERROR(__xludf.DUMMYFUNCTION("""COMPUTED_VALUE"""),11.11) -> 11.11 | I91: =IF(G91>0,(H91-G91)/G91,IF(H91>0,0,0)) -> 0
C92: =IFERROR(__xludf.DUMMYFUNCTION("""COMPUTED_VALUE"""),"Derivação PVC 90o FF - 50 mm - Caixa com 60 peças") -> Derivação PVC 90o FF - 50 mm - Caixa com 60 peças | D92: =IFERROR(__xludf.DUMMYFUNCTION("IMPORTRANGE(""https://docs.google.com/spreadsheets/d/17pV1h3QXEhKsouzqT-wmZrwWCzREFYcQVORu3OKO97k/edit?gid=250502500#gid=250502500"",""PRODUTOS!F2"")"),"AERTECNICA") -> AERTECNICA | E92: 0 | F92: 0 | G92: 0 | H92: =IFERROR(__xludf.DUMMYFUNCTION("""COMPUTED_VALUE"""),566.7) -> 566.7 | I92: =IF(G92>0,(H92-G92)/G92,IF(H92>0,0,0)) -> 0
C93: =IFERROR(__xludf.DUMMYFUNCTION("""COMPUTED_VALUE"""),"Escova articulada d.32 “flexible curves” 30 cm, de uso duplo aspira e dá lustro") -> Escova articulada d.32 “flexible curves” 30 cm, de uso duplo aspira e dá lustro | D93: =IFERROR(__xludf.DUMMYFUNCTION("IMPORTRANGE(""https://docs.google.com/spreadsheets/d/17pV1h3QXEhKsouzqT-wmZrwWCzREFYcQVORu3OKO97k/edit?gid=250502500#gid=250502500"",""PRODUTOS!F2"")"),"AERTECNICA") -> AERTECNICA | E93: 0 | F93: 0 | G93: 0 | H93: =IFERROR(__xludf.DUMMYFUNCTION("""COMPUTED_VALUE"""),295.41) -> 295.41 | I93: =IF(G93>0,(H93-G93)/G93,IF(H93>0,0,0)) -> 0
C94: =IFERROR(__xludf.DUMMYFUNCTION("""COMPUTED_VALUE"""),"Escova com cerdas para animais, Ø32, KA") -> Escova com cerdas para animais, Ø32, KA | D94: =IFERROR(__xludf.DUMMYFUNCTION("IMPORTRANGE(""https://docs.google.com/spreadsheets/d/17pV1h3QXEhKsouzqT-wmZrwWCzREFYcQVORu3OKO97k/edit?gid=250502500#gid=250502500"",""PRODUTOS!F2"")"),"AERTECNICA") -> AERTECNICA | E94: 0 | F94: 0 | G94: 0 | H94: =IFERROR(__xludf.DUMMYFUNCTION("""COMPUTED_VALUE"""),411.36) -> 411.36 | I94: =IF(G94>0,(H94-G94)/G94,IF(H94>0,0,0)) -> 0
C95: =IFERROR(__xludf.DUMMYFUNCTION("""COMPUTED_VALUE"""),"Escova Ø 32 para pavimento de madeira 30 cm, com cerdas em crina natural e rodas de feltro") -> Escova Ø 32 para pavimento de madeira 30 cm, com cerdas em crina natural e rodas de feltro | D95: =IFERROR(__xludf.DUMMYFUNCTION("IMPORTRANGE(""https://docs.google.com/spreadsheets/d/17pV1h3QXEhKsouzqT-wmZrwWCzREFYcQVORu3OKO97k/edit?gid=250502500#gid=250502500"",""PRODUTOS!F2"")"),"AERTECNICA") -> AERTECNICA | E95: 0 | F95: 0 | G95: 0 | H95: =IFERROR(__xludf.DUMMYFUNCTION("""COMPUTED_VALUE"""),258.67) -> 258.67 | I95: =IF(G95>0,(H95-G95)/G95,IF(H95>0,0,0)) -> 0
C96: =IFERROR(__xludf.DUMMYFUNCTION("""COMPUTED_VALUE"""),"Escova para pavimento-tapete com rodas, Ø32") -> Escova para pavimento-tapete com rodas, Ø32 | D96: =IFERROR(__xludf.DUMMYFUNCTION("IMPORTRANGE(""https://docs.google.com/spreadsheets/d/17pV1h3QXEhKsouzqT-wmZrwWCzREFYcQVORu3OKO97k/edit?gid=250502500#gid=250502500"",""PRODUTOS!F2"")"),"AERTECNICA") -> AERTECNICA | E96: 0 | F96: 0 | G96: 0 | H96: =IFERROR(__xludf.DUMMYFUNCTION("""COMPUTED_VALUE"""),266.67) -> 266.67 | I96: =IF(G96>0,(H96-G96)/G96,IF(H96>0,0,0)) -> 0
C97: =IFERROR(__xludf.DUMMYFUNCTION("""COMPUTED_VALUE"""),"Escova turbo bate tapeçaria, Ø32") -> Escova turbo bate tapeçaria, Ø32 | D97: =IFERROR(__xludf.DUMMYFUNCTION("IMPORTRANGE(""https://docs.google.com/spreadsheets/d/17pV1h3QXEhKsouzqT-wmZrwWCzREFYcQVORu3OKO97k/edit?gid=250502500#gid=250502500"",""PRODUTOS!F2"")"),"AERTECNICA") -> AERTECNICA | E97: 0 | F97: 0 | G97: 0 | H97: =IFERROR(__xludf.DUMMYFUNCTION("""COMPUTED_VALUE"""),411.36) -> 411.36 | I97: =IF(G97>0,(H97-G97)/G97,IF(H97>0,0,0)) -> 0
C98: =IFERROR(__xludf.DUMMYFUNCTION("""COMPUTED_VALUE"""),"Escova turbo bate tapete-alcatifa com rodas, Ø32") -> Escova turbo bate tapete-alcatifa com rodas, Ø32 | D98: =IFERROR(__xludf.DUMMYFUNCTION("IMPORTRANGE(""https://docs.google.com/spreadsheets/d/17pV1h3QXEhKsouzqT-wmZrwWCzREFYcQVORu3OKO97k/edit?gid=250502500#gid=250502500"",""PRODUTOS!F2"")"),"AERTECNICA") -> AERTECNICA | E98: 0 | F98: 0 | G98: 0 | H98: =IFERROR(__xludf.DUMMYFUNCTION("""COMPUTED_VALUE"""),641.82) -> 641.82 | I98: =IF(G98>0,(H98-G98)/G98,IF(H98>0,0,0)) -> 0
C99: =IFERROR(__xludf.DUMMYFUNCTION("""COMPUTED_VALUE"""),"ESPAÇADOR TURBINA") -> ESPAÇADOR TURBINA | D99: =IFERROR(__xludf.DUMMYFUNCTION("IMPORTRANGE(""https://docs.google.com/spreadsheets/d/17pV1h3QXEhKsouzqT-wmZrwWCzREFYcQVORu3OKO97k/edit?gid=250502500#gid=250502500"",""PRODUTOS!F2"")"),"AERTECNICA") -> AERTECNICA | E99: 0 | F99: 0 | G99: 0 | H99: =IFERROR(__xludf.DUMMYFUNCTION("""COMPUTED_VALUE"""),13.3) -> 13.3 | I99: =IF(G99>0,(H99-G99)/G99,IF(H99>0,0,0)) -> 0
C100: =IFERROR(__xludf.DUMMYFUNCTION("""COMPUTED_VALUE"""),"Extensão Modular para tomadas New Air - Unidade") -> Extensão Modular para tomadas New Air - Unidade | D100: =IFERROR(__xludf.DUMMYFUNCTION("IMPORTRANGE(""https://docs.google.com/spreadsheets/d/17pV1h3QXEhKsouzqT-wmZrwWCzREFYcQVORu3OKO97k/edit?gid=250502500#gid=250502500"",""PRODUTOS!F2"")"),"AERTECNICA") -> AERTECNICA | E100: 0 | F100: 0 | G100: 0 | H100: =IFERROR(__xludf.DUMMYFUNCTION("""COMPUTED_VALUE"""),77.83) -> 77.83 | I100: =IF(G100>0,(H100-G100)/G100,IF(H100>0,0,0)) -> 0
...

Sheet ESTOQUE
D1: CATEGORIA | E1: PRODUTO | F1: SALDO | G1: ENTRADA | H1: SAIDA | I1: CUSTO | J1: CUSTO TOTAL
D2: ACESSÓRIO | E2: ANTENNA PROTECT | F2: =G2-H2 -> 1 | G2: =SUMIFS('LANÇAMENTOS'!$H:$H,'LANÇAMENTOS'!$E:$E,"ENTRADA",'LANÇAMENTOS'!$G:$G,$E2) -> 1 | H2: =SUMIFS('LANÇAMENTOS'!$H:$H,'LANÇAMENTOS'!$E:$E,"SAIDA",'LANÇAMENTOS'!$G:$G,$E2) -> 0 | J2: =I2*F2 -> 0
A3: ATUALIZADO EM 10/04/2025 | D3: ACESSÓRIO | E3: CABLE PROTECT | F3: =G3-H3 -> 1 | G3: =SUMIFS('LANÇAMENTOS'!$H:$H,'LANÇAMENTOS'!$E:$E,"ENTRADA",'LANÇAMENTOS'!$G:$G,$E3) -> 1 | H3: =SUMIFS('LANÇAMENTOS'!$H:$H,'LANÇAMENTOS'!$E:$E,"SAIDA",'LANÇAMENTOS'!$G:$G,$E3) -> 0 | J3: =I3*F3 -> 0
D4: ACESSÓRIO | E4: KIT PASSADOR DE FIO EXPANSÍVEL | F4: =G4-H4 -> 7 | G4: =SUMIFS('LANÇAMENTOS'!$H:$H,'LANÇAMENTOS'!$E:$E,"ENTRADA",'LANÇAMENTOS'!$G:$G,$E4) -> 7 | H4: =SUMIFS('LANÇAMENTOS'!$H:$H,'LANÇAMENTOS'!$E:$E,"SAIDA",'LANÇAMENTOS'!$G:$G,$E4) -> 0 | J4: =I4*F4 -> 0
D5: ACESSÓRIO | E5: MICROFONE PARA CALIBRAÇÃO | F5: =G5-H5 -> 5 | G5: =SUMIFS('LANÇAMENTOS'!$H:$H,'LANÇAMENTOS'!$E:$E,"ENTRADA",'LANÇAMENTOS'!$G:$G,$E5) -> 6 | H5: =SUMIFS('LANÇAMENTOS'!$H:$H,'LANÇAMENTOS'!$E:$E,"SAIDA",'LANÇAMENTOS'!$G:$G,$E5) -> 1 | J5: =I5*F5 -> 0
D6: ACESSÓRIO | E6: ABRAÇADEIRAS | F6: =G6-H6 -> 11 | G6: =SUMIFS('LANÇAMENTOS'!$H:$H,'LANÇAMENTOS'!$E:$E,"ENTRADA",'LANÇAMENTOS'!$G:$G,$E6) -> 11 | H6: =SUMIFS('LANÇAMENTOS'!$H:$H,'LANÇAMENTOS'!$E:$E,"SAIDA",'LANÇAMENTOS'!$G:$G,$E6) -> 0 | J6: =I6*F6 -> 0
D7: ACESSÓRIO | E7: EMENDA HDMI RETO | F7: =G7-H7 -> 11 | G7: =SUMIFS('LANÇAMENTOS'!$H:$H,'LANÇAMENTOS'!$E:$E,"ENTRADA",'LANÇAMENTOS'!$G:$G,$E7) -> 11 | H7: =SUMIFS('LANÇAMENTOS'!$H:$H,'LANÇAMENTOS'!$E:$E,"SAIDA",'LANÇAMENTOS'!$G:$G,$E7) -> 0 | J7: =I7*F7 -> 0
D8: ACESSÓRIO | E8: EMENDA HDMI EM L | F8: =G8-H8 -> 4 | G8: =SUMIFS('LANÇAMENTOS'!$H:$H,'LANÇAMENTOS'!$E:$E,"ENTRADA",'LANÇAMENTOS'!$G:$G,$E8) -> 4 | H8: =SUMIFS('LANÇAMENTOS'!$H:$H,'LANÇAMENTOS'!$E:$E,"SAIDA",'LANÇAMENTOS'!$G:$G,$E8) -> 0 | J8: =I8*F8 -> 0
D9: ACESSÓRIO | E9: RÉGUA 5 TOMADAS COM LIGA | F9: =G9-H9 -> 1 | G9: =SUMIFS('LANÇAMENTOS'!$H:$H,'LANÇAMENTOS'!$E:$E,"ENTRADA",'LANÇAMENTOS'!$G:$G,$E9) -> 3 | H9: =SUMIFS('LANÇAMENTOS'!$H:$H,'LANÇAMENTOS'!$E:$E,"SAIDA",'LANÇAMENTOS'!$G:$G,$E9) -> 2 | J9: =I9*F9 -> 0
D10: AMPLIFICADOR | E10: HAYONIK APLIFICADOR 450 | F10: =G10-H10 -> 3 | G10: =SUMIFS('LANÇAMENTOS'!$H:$H,'LANÇAMENTOS'!$E:$E,"ENTRADA",'LANÇAMENTOS'!$G:$G,$E10) -> 3 | H10: =SUMIFS('LANÇAMENTOS'!$H:$H,'LANÇAMENTOS'!$E:$E,"SAIDA",'LANÇAMENTOS'!$G:$G,$E10) -> 0 | J10: =I10*F10 -> 0
D11: APARELHO | E11: HDMI ARC | F11: =G11-H11 -> 8 | G11: =SUMIFS('LANÇAMENTOS'!$H:$H,'LANÇAMENTOS'!$E:$E,"ENTRADA",'LANÇAMENTOS'!$G:$G,$E11) -> 8 | H11: =SUMIFS('LANÇAMENTOS'!$H:$H,'LANÇAMENTOS'!$E:$E,"SAIDA",'LANÇAMENTOS'!$G:$G,$E11) -> 0 | J11: =I11*F11 -> 0
D12: APARELHO | E12: SWITCH HIKVISION 8P 1GB | F12: =G12-H12 -> 3 | G12: =SUMIFS('LANÇAMENTOS'!$H:$H,'LANÇAMENTOS'!$E:$E,"ENTRADA",'LANÇAMENTOS'!$G:$G,$E12) -> 3 | H12: =SUMIFS('LANÇAMENTOS'!$H:$H,'LANÇAMENTOS'!$E:$E,"SAIDA",'LANÇAMENTOS'!$G:$G,$E12) -> 0 | J12: =I12*F12 -> 0
D13: APARELHO | E13: SWITCH HIKVISION 5P 1GB | F13: =G13-H13 -> 2 | G13: =SUMIFS('LANÇAMENTOS'!$H:$H,'LANÇAMENTOS'!$E:$E,"ENTRADA",'LANÇAMENTOS'!$G:$G,$E13) -> 2 | H13: =SUMIFS('LANÇAMENTOS'!$H:$H,'LANÇAMENTOS'!$E:$E,"SAIDA",'LANÇAMENTOS'!$G:$G,$E13) -> 0 | J13: =I13*F13 -> 0
D14: APARELHO | E14: SWITCH MERCURYS 8P FAST | F14: =G14-H14 -> 2 | G14: =SUMIFS('LANÇAMENTOS'!$H:$H,'LANÇAMENTOS'!$E:$E,"ENTRADA",'LANÇAMENTOS'!$G:$G,$E14) -> 2 | H14: =SUMIFS('LANÇAMENTOS'!$H:$H,'LANÇAMENTOS'!$E:$E,"SAIDA",'LANÇAMENTOS'!$G:$G,$E14) -> 0 | J14: =I14*F14 -> 0
D15: APARELHO | E15: SWITCH MERCURYS 5P FAST | F15: =G15-H15 -> 1 | G15: =SUMIFS('LANÇAMENTOS'!$H:$H,'LANÇAMENTOS'!$E:$E,"ENTRADA",'LANÇAMENTOS'!$G:$G,$E15) -> 1 | H15: =SUMIFS('LANÇAMENTOS'!$H:$H,'LANÇAMENTOS'!$E:$E,"SAIDA",'LANÇAMENTOS'!$G:$G,$E15) -> 0 | J15: =I15*F15 -> 0
... D28: CABO | E28: HDMI STORM 0,5m | F28: =G28-H28 -> 0 | G28: =SUMIFS('LANÇAMENTOS'!$H:$H,'LANÇAMENTOS'!$E:$E,"ENTRADA",'LANÇAMENTOS'!$G:$G,$E28) -> 0 | H28: =SUMIFS('LANÇAMENTOS'!$H:$H,'LANÇAMENTOS'!$E:$E,"SAIDA",'LANÇAMENTOS'!$G:$G,$E28) -> 0 | J28: =I28*F28 -> 0
D29: CABO | E29: HDMI STORM 1,5m | F29: =G29-H29 -> 20 | G29: =SUMIFS('LANÇAMENTOS'!$H:$H,'LANÇAMENTOS'!$E:$E,"ENTRADA",'LANÇAMENTOS'!$G:$G,$E29) -> 23 | H29: =SUMIFS('LANÇAMENTOS'!$H:$H,'LANÇAMENTOS'!$E:$E,"SAIDA",'LANÇAMENTOS'!$G:$G,$E29) -> 3 | I29: 27.61 | J29: =I29*F29 -> 552.2
D30: CABO | E30: HDMI STORM 1m | F30: =G30-H30 -> 13 | G30: =SUMIFS('LANÇAMENTOS'!$H:$H,'LANÇAMENTOS'!$E:$E,"ENTRADA",'LANÇAMENTOS'!$G:$G,$E30) -> 13 | H30: =SUMIFS('LANÇAMENTOS'!$H:$H,'LANÇAMENTOS'!$E:$E,"SAIDA",'LANÇAMENTOS'!$G:$G,$E30) -> 0 | I30: 14.63 | J30: =I30*F30 -> 190.19
D31: CABO | E31: HDMI STORM 2m | F31: =G31-H31 -> 17 | G31: =SUMIFS('LANÇAMENTOS'!$H:$H,'LANÇAMENTOS'!$E:$E,"ENTRADA",'LANÇAMENTOS'!$G:$G,$E31) -> 20 | H31: =SUMIFS('LANÇAMENTOS'!$H:$H,'LANÇAMENTOS'!$E:$E,"SAIDA",'LANÇAMENTOS'!$G:$G,$E31) -> 3 | I31: 30.83 | J31: =I31*F31 -> 524.11
D32: CABO | E32: HDMI STORM 3m | F32: =G32-H32 -> 12 | G32: =SUMIFS('LANÇAMENTOS'!$H:$H,'LANÇAMENTOS'!$E:$E,"ENTRADA",'LANÇAMENTOS'!$G:$G,$E32) -> 15 | H32: =SUMIFS('LANÇAMENTOS'!$H:$H,'LANÇAMENTOS'!$E:$E,"SAIDA",'LANÇAMENTOS'!$G:$G,$E32) -> 3 | I32: 25.03 | J32: =I32*F32 -> 300.36
D33: CABO | E33: HDMI STORM 5m | F33: =G33-H33 -> 0 | G33: =SUMIFS('LANÇAMENTOS'!$H:$H,'LANÇAMENTOS'!$E:$E,"ENTRADA",'LANÇAMENTOS'!$G:$G,$E33) -> 0 | H33: =SUMIFS('LANÇAMENTOS'!$H:$H,'LANÇAMENTOS'!$E:$E,"SAIDA",'LANÇAMENTOS'!$G:$G,$E33) -> 0 | I33: 49.61 | J33: =I33*F33 -> 0
D34: CABO | E34: RCA Y 1 MACHO + 2 FÊMES 90 GRAUS | F34: =G34-H34 -> 13 | G34: =SUMIFS('LANÇAMENTOS'!$H:$H,'LANÇAMENTOS'!$E:$E,"ENTRADA",'LANÇAMENTOS'!$G:$G,$E34) -> 13 | H34: =SUMIFS('LANÇAMENTOS'!$H:$H,'LANÇAMENTOS'!$E:$E,"SAIDA",'LANÇAMENTOS'!$G:$G,$E34) -> 0 | J34: =I34*F34 -> 0
D35: CABO | E35: TOSLINK PIX 10m | F35: =G35-H35 -> 6 | G35: =SUMIFS('LANÇAMENTOS'!$H:$H,'LANÇAMENTOS'!$E:$E,"ENTRADA",'LANÇAMENTOS'!$G:$G,$E35) -> 6 | H35: =SUMIFS('LANÇAMENTOS'!$H:$H,'LANÇAMENTOS'!$E:$E,"SAIDA",'LANÇAMENTOS'!$G:$G,$E35) -> 0 | J35: =I35*F35 -> 0
D36: CABO | E36: TOSLINK PIX 1m | F36: =G36-H36 -> 4 | G36: =SUMIFS('LANÇAMENTOS'!$H:$H,'LANÇAMENTOS'!$E:$E,"ENTRADA",'LANÇAMENTOS'!$G:$G,$E36) -> 7 | H36: =SUMIFS('LANÇAMENTOS'!$H:$H,'LANÇAMENTOS'!$E:$E,"SAIDA",'LANÇAMENTOS'!$G:$G,$E36) -> 3 | J36: =I36*F36 -> 0
D37: CABO | E37: TOSLINK PIX 2m | F37: =G37-H37 -> 20 | G37: =SUMIFS('LANÇAMENTOS'!$H:$H,'LANÇAMENTOS'!$E:$E,"ENTRADA",'LANÇAMENTOS'!$G:$G,$E37) -> 21 | H37: =SUMIFS('LANÇAMENTOS'!$H:$H,'LANÇAMENTOS'!$E:$E,"SAIDA",'LANÇAMENTOS'!$G:$G,$E37) -> 1 | J37: =I37*F37 -> 0
D38: CABO | E38: TOSLINK PIX 3m | F38: =G38-H38 -> 5 | G38: =SUMIFS('LANÇAMENTOS'!$H:$H,'LANÇAMENTOS'!$E:$E,"ENTRADA",'LANÇAMENTOS'!$G:$G,$E38) -> 6 | H38: =SUMIFS('LANÇAMENTOS'!$H:$H,'LANÇAMENTOS'!$E:$E,"SAIDA",'LANÇAMENTOS'!$G:$G,$E38) -> 1 | J38: =I38*F38 -> 0
D39: CABO | E39: TOSLINK PIX 5m | F39: =G39-H39 -> 6 | G39: =SUMIFS('LANÇAMENTOS'!$H:$H,'LANÇAMENTOS'!$E:$E,"ENTRADA",'LANÇAMENTOS'!$G:$G,$E39) -> 8 | H39: =SUMIFS('LANÇAMENTOS'!$H:$H,'LANÇAMENTOS'!$E:$E,"SAIDA",'LANÇAMENTOS'!$G:$G,$E39) -> 2 | J39: =I39*F39 -> 0
D40: CABO | E40: CABO 4P X 24 300M | F40: =G40-H40 -> 0.25 | G40: =SUMIFS('LANÇAMENTOS'!$H:$H,'LANÇAMENTOS'!$E:$E,"ENTRADA",'LANÇAMENTOS'!$G:$G,$E40) -> 0.25 | H40: =SUMIFS('LANÇAMENTOS'!$H:$H,'LANÇAMENTOS'!$E:$E,"SAIDA",'LANÇAMENTOS'!$G:$G,$E40) -> 0 | J40: =I40*F40 -> 0
D41: CABO | E41: RCA STORM 5M | F41: =G41-H41 -> 6 | G41: =SUMIFS('LANÇAMENTOS'!$H:$H,'LANÇAMENTOS'!$E:$E,"ENTRADA",'LANÇAMENTOS'!$G:$G,$E41) -> 6 | H41: =SUMIFS('LANÇAMENTOS'!$H:$H,'LANÇAMENTOS'!$E:$E,"SAIDA",'LANÇAMENTOS'!$G:$G,$E41) -> 0 | J41: =I41*F41 -> 0
D42: CABO | E42: RCA STORM 3M | F42: =G42-H42 -> 6 | G42: =SUMIFS('LANÇAMENTOS'!$H:$H,'LANÇAMENTOS'!$E:$E,"ENTRADA",'LANÇAMENTOS'!$G:$G,$E42) -> 6 | H42: =SUMIFS('LANÇAMENTOS'!$H:$H,'LANÇAMENTOS'!$E:$E,"SAIDA",'LANÇAMENTOS'!$G:$G,$E42) -> 0 | J42: =I42*F42 -> 0
D43: CABO | E43: RCA STORM 1M | F43: =G43-H43 -> 16 | G43: =SUMIFS('LANÇAMENTOS'!$H:$H,'LANÇAMENTOS'!$E:$E,"ENTRADA",'LANÇAMENTOS'!$G:$G,$E43) -> 16 | H43: =SUMIFS('LANÇAMENTOS'!$H:$H,'LANÇAMENTOS'!$E:$E,"SAIDA",'LANÇAMENTOS'!$G:$G,$E43) -> 0 | J43: =I43*F43 -> 0
D44: CABO | E44: TOSLINK DMD 1,5M | F44: =G44-H44 -> 4 | G44: =SUMIFS('LANÇAMENTOS'!$H:$H,'LANÇAMENTOS'!$E:$E,"ENTRADA",'LANÇAMENTOS'!$G:$G,$E44) -> 4 | H44: =SUMIFS('LANÇAMENTOS'!$H:$H,'LANÇAMENTOS'!$E:$E,"SAIDA",'LANÇAMENTOS'!$G:$G,$E44) -> 0 | J44: =I44*F44 -> 0
D45: CABO | E45: TOSLINK DMD 3M | F45: =G45-H45 -> 3 | G45: =SUMIFS('LANÇAMENTOS'!$H:$H,'LANÇAMENTOS'!$E:$E,"ENTRADA",'LANÇAMENTOS'!$G:$G,$E45) -> 3 | H45: =SUMIFS('LANÇAMENTOS'!$H:$H,'LANÇAMENTOS'!$E:$E,"SAIDA",'LANÇAMENTOS'!$G:$G,$E45) -> 0 | J45: =I45*F45 -> 0
... D50: CABO | E50: RCA SUMAY 1,2M | F50: =G50-H50 -> 1 | G50: =SUMIFS('LANÇAMENTOS'!$H:$H,'LANÇAMENTOS'!$E:$E,"ENTRADA",'LANÇAMENTOS'!$G:$G,$E50) -> 4 | H50: =SUMIFS('LANÇAMENTOS'!$H:$H,'LANÇAMENTOS'!$E:$E,"SAIDA",'LANÇAMENTOS'!$G:$G,$E50) -> 3 | J50: =I50*F50 -> 0
D51: CAIXA DE SOM | E51: JBL CI6S PLUS | F51: =G51-H51 -> 0 | G51: =SUMIFS('LANÇAMENTOS'!$H:$H,'LANÇAMENTOS'!$E:$E,"ENTRADA",'LANÇAMENTOS'!$G:$G,$E51) -> 29 | H51: =SUMIFS('LANÇAMENTOS'!$H:$H,'LANÇAMENTOS'!$E:$E,"SAIDA",'LANÇAMENTOS'!$G:$G,$E51) -> 29 | I51: 228.74 | J51: =I51*F51 -> 0
D52: CAIXA DE SOM | E52: JBL CI6SA | F52: =G52-H52 -> 0 | G52: =SUMIFS('LANÇAMENTOS'!$H:$H,'LANÇAMENTOS'!$E:$E,"ENTRADA",'LANÇAMENTOS'!$G:$G,$E52) -> 1 | H52: =SUMIFS('LANÇAMENTOS'!$H:$H,'LANÇAMENTOS'!$E:$E,"SAIDA",'LANÇAMENTOS'!$G:$G,$E52) -> 1 | J52: =I52*F52 -> 0
D53: CAIXA DE SOM | E53: JBL CI6SA PLUS | F53: =G53-H53 -> 6 | G53: =SUMIFS('LANÇAMENTOS'!$H:$H,'LANÇAMENTOS'!$E:$E,"ENTRADA",'LANÇAMENTOS'!$G:$G,$E53) -> 27 | H53: =SUMIFS('LANÇAMENTOS'!$H:$H,'LANÇAMENTOS'!$E:$E,"SAIDA",'LANÇAMENTOS'!$G:$G,$E53) -> 21 | J53: =I53*F53 -> 0
D54: CAIXA DE SOM | E54: JBL CI8P | F54: =G54-H54 -> 8 | G54: =SUMIFS('LANÇAMENTOS'!$H:$H,'LANÇAMENTOS'!$E:$E,"ENTRADA",'LANÇAMENTOS'!$G:$G,$E54) -> 12 | H54: =SUMIFS('LANÇAMENTOS'!$H:$H,'LANÇAMENTOS'!$E:$E,"SAIDA",'LANÇAMENTOS'!$G:$G,$E54) -> 4 | I54: 664.73 | J54: =I54*F54 -> 5317.84
D55: CAIXA DE SOM | E55: JBL CI8S | F55: =G55-H55 -> 0 | G55: =SUMIFS('LANÇAMENTOS'!$H:$H,'LANÇAMENTOS'!$E:$E,"ENTRADA",'LANÇAMENTOS'!$G:$G,$E55) -> 4 | H55: =SUMIFS('LANÇAMENTOS'!$H:$H,'LANÇAMENTOS'!$E:$E,"SAIDA",'LANÇAMENTOS'!$G:$G,$E55) -> 4 | J55: =I55*F55 -> 0
D56: CAIXA DE SOM | E56: JBL CI8SA | F56: =G56-H56 -> 0 | G56: =SUMIFS('LANÇAMENTOS'!$H:$H,'LANÇAMENTOS'!$E:$E,"ENTRADA",'LANÇAMENTOS'!$G:$G,$E56) -> 3 | H56: =SUMIFS('LANÇAMENTOS'!$H:$H,'LANÇAMENTOS'!$E:$E,"SAIDA",'LANÇAMENTOS'!$G:$G,$E56) -> 3 | J56: =I56*F56 -> 0
D57: CAIXA DE SOM | E57: JBL STAGE 260C | F57: =G57-H57 -> 7 | G57: =SUMIFS('LANÇAMENTOS'!$H:$H,'LANÇAMENTOS'!$E:$E,"ENTRADA",'LANÇAMENTOS'!$G:$G,$E57) -> 28 | H57: =SUMIFS('LANÇAMENTOS'!$H:$H,'LANÇAMENTOS'!$E:$E,"SAIDA",'LANÇAMENTOS'!$G:$G,$E57) -> 21 | J57: =I57*F57 -> 0
D58: CAIXA DE SOM | E58: JBL STAGE 260CSA | F58: =G58-H58 -> 12 | G58: =SUMIFS('LANÇAMENTOS'!$H:$H,'LANÇAMENTOS'!$E:$E,"ENTRADA",'LANÇAMENTOS'!$G:$G,$E58) -> 18 | H58: =SUMIFS('LANÇAMENTOS'!$H:$H,'LANÇAMENTOS'!$E:$E,"SAIDA",'LANÇAMENTOS'!$G:$G,$E58) -> 6 | J58: =I58*F58 -> 0
D59: CAIXA DE SOM | E59: JBL STAGE XD-6 | F59: =G59-H59 -> 3 | G59: =SUMIFS('LANÇAMENTOS'!$H:$H,'LANÇAMENTOS'!$E:$E,"ENTRADA",'LANÇAMENTOS'!$G:$G,$E59) -> 6 | H59: =SUMIFS('LANÇAMENTOS'!$H:$H,'LANÇAMENTOS'!$E:$E,"SAIDA",'LANÇAMENTOS'!$G:$G,$E59) -> 3 | J59: =I59*F59 -> 0
D60: CAIXA DE SOM | E60: JBL SUBWOOFER 200P | F60: =G60-H60 -> 5 | G60: =SUMIFS('LANÇAMENTOS'!$H:$H,'LANÇAMENTOS'!$E:$E,"ENTRADA",'LANÇAMENTOS'!$G:$G,$E60) -> 5 | H60: =SUMIFS('LANÇAMENTOS'!$H:$H,'LANÇAMENTOS'!$E:$E,"SAIDA",'LANÇAMENTOS'!$G:$G,$E60) -> 0 | J60: =I60*F60 -> 0
D61: CAIXA DE SOM | E61: JBL SUBWOOFER A100P | F61: =G61-H61 -> 1 | G61: =SUMIFS('LANÇAMENTOS'!$H:$H,'LANÇAMENTOS'!$E:$E,"ENTRADA",'LANÇAMENTOS'!$G:$G,$E61) -> 5 | H61: =SUMIFS('LANÇAMENTOS'!$H:$H,'LANÇAMENTOS'!$E:$E,"SAIDA",'LANÇAMENTOS'!$G:$G,$E61) -> 4 | J61: =I61*F61 -> 0
D62: CAIXA DE SOM | E62: SUMAY 100W | F62: =G62-H62 -> 6 | G62: =SUMIFS('LANÇAMENTOS'!$H:$H,'LANÇAMENTOS'!$E:$E,"ENTRADA",'LANÇAMENTOS'!$G:$G,$E62) -> 6 | H62: =SUMIFS('LANÇAMENTOS'!$H:$H,'LANÇAMENTOS'!$E:$E,"SAIDA",'LANÇAMENTOS'!$G:$G,$E62) -> 0 | J62: =I62*F62 -> 0
D63: CAIXA DE SOM | E63: SUMAY 80W | F63: =G63-H63 -> 4 | G63: =SUMIFS('LANÇAMENTOS'!$H:$H,'LANÇAMENTOS'!$E:$E,"ENTRADA",'LANÇAMENTOS'!$G:$G,$E63) -> 4 | H63: =SUMIFS('LANÇAMENTOS'!$H:$H,'LANÇAMENTOS'!$E:$E,"SAIDA",'LANÇAMENTOS'!$G:$G,$E63) -> 0 | J63: =I63*F63 -> 0
D64: CAIXA DE SOM | E64: HAYONIK CS 630 PLUS BRANCA | F64: =G64-H64 -> 32 | G64: =SUMIFS('LANÇAMENTOS'!$H:$H,'LANÇAMENTOS'!$E:$E,"ENTRADA",'LANÇAMENTOS'!$G:$G,$E64) -> 32 | H64: =SUMIFS('LANÇAMENTOS'!$H:$H,'LANÇAMENTOS'!$E:$E,"SAIDA",'LANÇAMENTOS'!$G:$G,$E64) -> 0 | J64: =I64*F64 -> 0
D65: CAIXA DE SOM | E65: HAYONIK CS 630 PLUS PRETA | F65: =G65-H65 -> 0 | G65: =SUMIFS('LANÇAMENTOS'!$H:$H,'LANÇAMENTOS'!$E:$E,"ENTRADA",'LANÇAMENTOS'!$G:$G,$E65) -> 0 | H65: =SUMIFS('LANÇAMENTOS'!$H:$H,'LANÇAMENTOS'!$E:$E,"SAIDA",'LANÇAMENTOS'!$G:$G,$E65) -> 0 | J65: =I65*F65 -> 0
D66: CONDICIONADOR DE ENERGIA | E66: FullProtect FPT1000 | F66: =G66-H66 -> 9 | G66: =SUMIFS('LANÇAMENTOS'!$H:$H,'LANÇAMENTOS'!$E:$E,"ENTRADA",'LANÇAMENTOS'!$G:$G,$E66) -> 17 | H66: =SUMIFS('LANÇAMENTOS'!$H:$H,'LANÇAMENTOS'!$E:$E,"SAIDA",'LANÇAMENTOS'!$G:$G,$E66) -> 8 | J66: =I66*F66 -> 0
... D69: CONECTOR | E69: CONECTOR RJ45 | F69: =G69-H69 -> 0 | G69: =SUMIFS('LANÇAMENTOS'!$H:$H,'LANÇAMENTOS'!$E:$E,"ENTRADA",'LANÇAMENTOS'!$G:$G,$E69) -> 1 | H69: =SUMIFS('LANÇAMENTOS'!$H:$H,'LANÇAMENTOS'!$E:$E,"SAIDA",'LANÇAMENTOS'!$G:$G,$E69) -> 1 | J69: =I69*F69 -> 0
D70: RECEIVER | E70: JBLMA510BLKBR | F70: =G70-H70 -> 2 | G70: =SUMIFS('LANÇAMENTOS'!$H:$H,'LANÇAMENTOS'!$E:$E,"ENTRADA",'LANÇAMENTOS'!$G:$G,$E70) -> 4 | H70: =SUMIFS('LANÇAMENTOS'!$H:$H,'LANÇAMENTOS'!$E:$E,"SAIDA",'LANÇAMENTOS'!$G:$G,$E70) -> 2 | I70: 3142.36 | J70: =I70*F70 -> 6284.72
D71: RECEIVER | E71: JBLMA7100HP | F71: =G71-H71 -> 1 | G71: =SUMIFS('LANÇAMENTOS'!$H:$H,'LANÇAMENTOS'!$E:$E,"ENTRADA",'LANÇAMENTOS'!$G:$G,$E71) -> 1 | H71: =SUMIFS('LANÇAMENTOS'!$H:$H,'LANÇAMENTOS'!$E:$E,"SAIDA",'LANÇAMENTOS'!$G:$G,$E71) -> 0 | J71: =I71*F71 -> 0
D72: RECEIVER | E72: DENON S760H | F72: =G72-H72 -> 1 | G72: =SUMIFS('LANÇAMENTOS'!$H:$H,'LANÇAMENTOS'!$E:$E,"ENTRADA",'LANÇAMENTOS'!$G:$G,$E72) -> 1 | H72: =SUMIFS('LANÇAMENTOS'!$H:$H,'LANÇAMENTOS'!$E:$E,"SAIDA",'LANÇAMENTOS'!$G:$G,$E72) -> 0 | J72: =I72*F72 -> 0
D73: SUPORTE | E73: SUPORTE TV 32" - 86" | F73: =G73-H73 -> 16 | G73: =SUMIFS('LANÇAMENTOS'!$H:$H,'LANÇAMENTOS'!$E:$E,"ENTRADA",'LANÇAMENTOS'!$G:$G,$E73) -> 16 | H73: =SUMIFS('LANÇAMENTOS'!$H:$H,'LANÇAMENTOS'!$E:$E,"SAIDA",'LANÇAMENTOS'!$G:$G,$E73) -> 0 | J73: 0
D74: SUPORTE | E74: SUPORTE TV 37" - 70" | F74: =G74-H74 -> 0 | G74: =SUMIFS('LANÇAMENTOS'!$H:$H,'LANÇAMENTOS'!$E:$E,"ENTRADA",'LANÇAMENTOS'!$G:$G,$E74) -> 2 | H74: =SUMIFS('LANÇAMENTOS'!$H:$H,'LANÇAMENTOS'!$E:$E,"SAIDA",'LANÇAMENTOS'!$G:$G,$E74) -> 2 | J74: =I74*F74 -> 0
D75: SUPORTE | E75: SUPORTE TV PINO 14" A 84" | F75: =G75-H75 -> 2 | G75: =SUMIFS('LANÇAMENTOS'!$H:$H,'LANÇAMENTOS'!$E:$E,"ENTRADA",'LANÇAMENTOS'!$G:$G,$E75) -> 6 | H75: =SUMIFS('LANÇAMENTOS'!$H:$H,'LANÇAMENTOS'!$E:$E,"SAIDA",'LANÇAMENTOS'!$G:$G,$E75) -> 4 | J75: =I75*F75 -> 0
F76: =G76-H76 -> 0 | G76: =SUMIFS('LANÇAMENTOS'!$H:$H,'LANÇAMENTOS'!$E:$E,"ENTRADA",'LANÇAMENTOS'!$G:$G,$E76) -> 0 | H76: =SUMIFS('LANÇAMENTOS'!$H:$H,'LANÇAMENTOS'!$E:$E,"SAIDA",'LANÇAMENTOS'!$G:$G,$E76) -> 0 | J76: =I76*F76 -> 0
F77: =G77-H77 -> 0 | G77: =SUMIFS('LANÇAMENTOS'!$H:$H,'LANÇAMENTOS'!$E:$E,"ENTRADA",'LANÇAMENTOS'!$G:$G,$E77) -> 0 | H77: =SUMIFS('LANÇAMENTOS'!$H:$H,'LANÇAMENTOS'!$E:$E,"SAIDA",'LANÇAMENTOS'!$G:$G,$E77) -> 0 | J77: =I77*F77 -> 0
F78: =G78-H78 -> 0 | G78: =SUMIFS('LANÇAMENTOS'!$H:$H,'LANÇAMENTOS'!$E:$E,"ENTRADA",'LANÇAMENTOS'!$G:$G,$E78) -> 0 | H78: =SUMIFS('LANÇAMENTOS'!$H:$H,'LANÇAMENTOS'!$E:$E,"SAIDA",'LANÇAMENTOS'!$G:$G,$E78) -> 0 | J78: =I78*F78 -> 0
F79: =G79-H79 -> 0 | G79: =SUMIFS('LANÇAMENTOS'!$H:$H,'LANÇAMENTOS'!$E:$E,"ENTRADA",'LANÇAMENTOS'!$G:$G,$E79) -> 0 | H79: =SUMIFS('LANÇAMENTOS'!$H:$H,'LANÇAMENTOS'!$E:$E,"SAIDA",'LANÇAMENTOS'!$G:$G,$E79) -> 0 | J79: =I79*F79 -> 0
F80: =G80-H80 -> 0 | G80: =SUMIFS('LANÇAMENTOS'!$H:$H,'LANÇAMENTOS'!$E:$E,"ENTRADA",'LANÇAMENTOS'!$G:$G,$E80) -> 0 | H80: =SUMIFS('LANÇAMENTOS'!$H:$H,'LANÇAMENTOS'!$E:$E,"SAIDA",'LANÇAMENTOS'!$G:$G,$E80) -> 0 | J80: =I80*F80 -> 0

Sheet LANÇAMENTOS
D1: DATA | E1: SITUAÇÃO | F1: TIPO | G1: PRODUTO | H1: QUANTIDADE
D6: DATA | E6: SITUAÇÃO | F6: TIPO | G6: PRODUTO | H6: QUANTIDADE
D8: 45763 | E8: SAIDA | F8: CLIENTE LOJA | G8: JBL CI6SA PLUS | H8: 4
D9: 45757 | E9: ENTRADA | F9: ACERTO ESTOQUE | G9: HDMI ARC | H9: 8
D10: 45757 | E10: ENTRADA | F10: ACERTO ESTOQUE | G10: SWITCH MERCURYS 5P FAST | H10: 1
D11: 45757 | E11: ENTRADA | F11: ACERTO ESTOQUE | G11: SWITCH MERCURYS 8P FAST | H11: 2
D12: 45757 | E12: ENTRADA | F12: ACERTO ESTOQUE | G12: SWITCH HIKVISION 5P 1GB | H12: 2
D13: 45757 | E13: ENTRADA | F13: ACERTO ESTOQUE | G13: SWITCH HIKVISION 8P 1GB | H13: 3
D14: 45757 | E14: SAIDA | F14: ACERTO ESTOQUE | G14: JBLMA510BLKBR | H14: 1
D15: 45757 | E15: SAIDA | F15: ACERTO ESTOQUE | G15: JBL CI6SA PLUS | H15: 3
D16: 45757 | E16: SAIDA | F16: ACERTO ESTOQUE | G16: JBL CI6S PLUS | H16: 2
D17: 45757 | E17: SAIDA | F17: ACERTO ESTOQUE | G17: RCA SUMAY 1,2M | H17: 3
D18: 45757 | E18: SAIDA | F18: ACERTO ESTOQUE | G18: FONTE 12V 3A | H18: 2
D19: 45757 | E19: ENTRADA | F19: ACERTO ESTOQUE | G19: RCA STORM 1M | H19: 10
... D168: 45521 | E168: ENTRADA | F168: ACERTO ESTOQUE | G168: TERMOSTATO | H168: 7

Sheet PEDIDO
B3: NOME COMPLETO:
B4: ENDEREÇO:
B5: TELEFONE:
B6: EMAIL:
E11: PEDIDO
B15: PRODUTOS | E15: QUANTIDADE | F15: PREÇO UNITÁRIO | H15: TOTAL
B16: Par de Caixa Som Ambiente JBL C321B 30W Branca | E16: 8 | F16: =626.1*2 -> 1252.2 | H16: =F16*E16 -> 10017.6
B17: Caixa Acústica Hayonik HSP-450IB Indoor Branca | E17: 16 | F17: =157.4*2 -> 314.8 | H17: =F17*E17 -> 5036.8
B60: INVESTIMENTO TOTAL | F60: =SUM(H15:H60) -> 15054.4
G67: Dados Bancarios
G69: PIX CNPJ: 13.744.082/0001-20
G70: AJUSTE FINO AUTOMAÇÃO RESIDENCIAL
A75: Rua Joinville, 36 | Vila Nova | Blumenau/SC
A76: (47) 3042 - 3781 | (47) 99139 - 6883
A77: www.ajustefinoht.com.br

Sheet PROD. SITE
A1: nome | B1: estoque-quantidade | C1: estoque-gerenciado | D1: estoque-situacao-em-estoque | E1: estoque-situacao-sem-estoque | F1: ativo | G1: usado | H1: id | I1: tipo | J1: sku-pai | K1: sku | L1: destaque | M1: ncm | N1: gtin | O1: mpn | P1: seo-tag-title | Q1: seo-tag-description | R1: descricao-completa | S1: url-video-youtube | T1: preco-sob-consulta | U1: preco-custo | V1: preco-cheio | W1: preco-promocional | X1: marca | Y1: peso-em-kg | Z1: altura-em-cm | AA1: largura-em-cm | AB1: comprimento-em-cm | AC1: categoria-nome-nivel-1 | AD1: categoria-nome-nivel-2 | AE1: categoria-nome-nivel-3 | AF1: categoria-nome-nivel-4 | AG1: categoria-nome-nivel-5 | AH1: imagem-1 | AI1: imagem-2 | AJ1: imagem-3 | AK1: imagem-4 | AL1: imagem-5 | AM1: grade-genero | AN1: grade-produto-com-uma-cor | AO1: grade-produto-com-duas-cores | AP1: grade-tamanho-de-anelalianca | AQ1: grade-tamanho-de-calca | AR1: grade-tamanho-de-camisacamiseta | AS1: grade-tamanho-de-capacete | AT1: grade-tamanho-de-tenis | AU1: grade-voltagem | AV1: grade-tamanho-juvenil-infantil | AW1: grade-formato-telacaixa-de-som | AX1: grade-formato-telacor | AY1: grade-tamanho-cabos | AZ1: grade-tamanho-de-projeto | BA1: grade-tamanho-mangueira
A2: Kit De Conector Banana Nakamichi 4 Unid | B2: 28 | C2: S | D2: imediata | E2: indisponivel | F2: S | G2: N | H2: 72473218 | I2: sem-variacao | K2: 2F7JN3U5D | L2: S | R2: <p><span style="font-size:16px;"><span style="font-family:trebuchet ms,helvetica,sans-serif;"><strong><span style="color: rgb(102, 102, 102);">DESCRIÇÃO:</span></strong><br style="box-sizing: border-box; color: rgb(102, 102, 102); font-family: &quot;Proxima Nova&quot;, -apple-system, &quot;Helvetica Neue&quot;, Helvetica, Roboto, Arial, sans-serif; font-size: 20px;" /> <span style="color: rgb(102, 102, 102);">Os conectores Nakamichi são fabricados com materiais de excelente qualidade, esse tipo de conector "BANANA" é muito utilizado na confecção de cabos de alta performance para sonorização de home theater e outros.</span><br style="box-sizing: border-box; color: rgb(102, 102, 102); font-family: &quot;Proxima Nova&quot;, -apple-system, &quot;Helvetica Neue&quot;, Helvetica, Roboto, Arial, sans-serif; font-size: 20px;" /> <br style="box-sizing: border-box; color: rgb(102, 102, 102); font-family: &quot;Proxima Nova&quot;, -apple-system, &quot;Helvetica Neue&quot;, Helvetica, Roboto, Arial, sans-serif; font-size: 20px;" /> <strong><span style="color: rgb(102, 102, 102);">ESPECIFICAÇÃO:</span></strong><br style="box-sizing: border-box; color: rgb(102, 102, 102); font-family: &quot;Proxima Nova&quot;, -apple-system, &quot;Helvetica Neue&quot;, Helvetica, Roboto, Arial, sans-serif; font-size: 20px;" /> <span style="color: rgb(102, 102, 102);">- Alta qualidade 100% novo!</span><br style="box-sizing: border-box; color: rgb(102, 102, 102); font-family: &quot;Proxima Nova&quot;, -apple-system, &quot;Helvetica Neue&quot;, Helvetica, Roboto, Arial, sans-serif; font-size: 20px;" /> <span style="color: rgb(102, 102, 102);">- Chapeamento de ouro 24k para transferência de sinal máximo e durabilidade.</span><br style="box-sizing: border-box; color: rgb(102, 102, 102); font-family: &quot;Proxima Nova&quot;, -apple-system, &quot;Helvetica Neue&quot;, Helvetica, Roboto, Arial, sans-serif; font-size: 20px;" /> <span style="color: rgb(102, 102, 102);">- Acomoda o cabo com tamanho do fio até 4mm. Aceita 8awg ao fio do orador 20awg.</span><br style="box-sizing: border-box; color: rgb(102, 102, 102); font-family: &quot;Proxima Nova&quot;, -apple-system, &quot;Helvetica Neue&quot;, Helvetica, Roboto, Arial, sans-serif; font-size: 20px;" /> <span style="color: rgb(102, 102, 102);">- Parafusos dobro de travamento.</span><br style="box-sizing: border-box; color: rgb(102, 102, 102); font-family: &quot;Proxima Nova&quot;, -apple-system, &quot;Helvetica Neue&quot;, Helvetica, Roboto, Arial, sans-serif; font-size: 20px;" /> <span style="color: rgb(102, 102, 102);">- Kit com 04 unidades sendo 02 vermelhas e 02 pretas.</span></span></span></p> | T2: N | V2: 43.9 | X2: Nakamichi | Y2: 0.4 | Z2: 20 | AA2: 20 | AB2: 10 | AH2: https://cdn.awsli.com.br/948/948321/produto/72473218/83d46b23c8.jpg | AI2: https://cdn.awsli.com.br/948/948321/produto/72473218/2cedede271.jpg
A3: CABO DE ÁUDIO ÓPTICO TOSLINK PIX 2m | B3: 21 | C3: S | D3: imediata | E3: indisponivel | F3: S | G3: N | H3: 59336047 | I3: sem-variacao | K3: TOSLINK2M | L3: N | R3: <p><span style="font-size:16px;"><span style="font-family:verdana,geneva,sans-serif;">Você merece o melhor som digital e sem nenhum tipo de interferências ou distorção!</span></span></p> <p><span style="font-size:16px;"><span style="font-family:verdana,geneva,sans-serif;">Aproveite o máximo de fidelidade e desempenho sonoro dos seus equipamentos com o Cabo Ótico Digital da CHIP SCE. Com ele você poderá ter uma transmissão livre de interferências e qualidade incomparável de áudio.</span></span></p> <p><span style="font-size:16px;"><span style="font-family:verdana,geneva,sans-serif;">Indicado para equipamentos que utilizam conexão óptica como: Blu-ray, TV's, receptores de TV Digital, vídeo games, receivers, DVD, home theaters e demais equipamentos que se adéquam à este sistema.</span></span></p> <p><span style="font-size:16px;"><strong><span style="font-family:verdana,geneva,sans-serif;">Especificações Técnicas:</span></strong></span></p> <p><span style="font-size:16px;"><span style="font-family:verdana,geneva,sans-serif;">Tamanho: 02 metros</span></span></p> <p><span style="font-size:16px;"><span style="font-family:verdana,geneva,sans-serif;">Conectores: Toslink - Gold</span></span></p> <p><span style="font-size:16px;"><span style="font-family:verdana,geneva,sans-serif;">Cabo: Fibra Ótica</span></span></p> <p><span style="font-size:16px;"><span style="font-family:verdana,geneva,sans-serif;">Aplicações: Blu-Ray, Receptores de Imagens digitais, Vídeo Games, Receivers, DVD, TVs e Home Theater.</span></span></p> <p><span style="font-size:16px;"><span style="font-family:verdana,geneva,sans-serif;"><strong>Conteúdo da embalagem:</strong><br /> 01 - Cabo Ótico de 2 metros</span></span></p> | T3: N | V3: 19.99 | X3: PIX | Y3: 0.8 | Z3: 12 | AA3: 12 | AB3: 12 | AH3: https://cdn.awsli.com.br/948/948321/produto/59336047/82a8782820.jpg | AI3: https://cdn.awsli.com.br/948/948321/produto/59336047/61c4b17699.jpg
A4: CAIXA DE SOM JBL CI6SA PLUS DE EMBUTIR ANGULADA - 160W RMS | B4: 16 | C4: S | D4: imediata | E4: indisponivel | F4: S | G4: N | H4: 263282847 | I4: sem-variacao | K4: 22BNRZMT7-W5SBT1VFO | L4: N | R4: <p style="margin: 0px 0px 10px; padding: 0px; color: rgb(102, 102, 102); font-family: Roboto, sans-serif; font-size: 12px; font-style: normal; font-variant-ligatures: normal; font-variant-caps: normal; font-weight: 400; letter-spacing: normal; orphans: 2; text-align: start; text-indent: 0px; text-transform: none; widows: 2; word-spacing: 0px; -webkit-text-stroke-width: 0px; white-space: normal; text-decoration-thickness: initial; text-decoration-style: initial; text-decoration-color: initial; background-color: rgb(255, 255, 255);"><span style="font-size:16px;margin:0px;padding:0px;"><span style="margin: 0px; padding: 0px;"><span style="margin: 0px; padding: 0px; font-family: verdana, geneva, sans-serif;"><span style="margin: 0px; padding: 0px;">Descrição do Produto:</span></span></span><br style="margin: 0px; padding: 0px;" /> <br style="margin: 0px; padding: 0px;" /> <span style="-webkit-text-stroke-width: 0px; background-color: rgb(255, 255, 255); color: rgb(102, 102, 102); font-family: Roboto, sans-serif; font-style: normal; font-variant-caps: normal; font-variant-ligatures: normal; font-weight: 400; letter-spacing: normal; margin: 0px 0px 10px; orphans: 2; text-align: start; text-decoration-color: initial; text-decoration-style: initial; text-decoration-thickness: initial; text-indent: 0px; text-transform: none; white-space: normal; widows: 2; word-spacing: 0px;">Caixa de som de embutir quadrada e angulada com alto-falante de Kevlar de 6.5 polegadas e tweeter com domo de seda de 20mm. Possui impedância de 8 ohms, e suporta potência máxima de 160 Watts RMS. Sua resposta de frequência é de 53Hz a 20kHz e possui sensibilidade de 90dB. Essa nova geração vem equipada com tela magnética para facilitar a instalação, além de incorporar um novo crossover para melhorar a performance de áudio e um ímã maior para otimizar o trabalho do alto-falante. O peso unitário da unidade é de 1,8kg.</span><button aria-controls="radix-:r5:" aria-expanded="true" class="sc-75806410-0 fPPRHK" data-radix-collection-item="" data-state="open" id="radix-:r4:" style="margin: 0px; padding: 0px; font-size: 16px; vertical-align: middle; line-height: 20px; appearance: button; cursor: pointer; font-weight: 400; font-family: Poppins, sans-serif !important; border: none; list-style: none; box-sizing: border-box; width: 1408.8px; background: transparent; display: flex; -webkit-box-pack: justify; justify-content: space-between; -webkit-box-align: center; align-items: center; orphans: 2; widows: 2; -webkit-text-stroke-width: 0px; white-space: normal; text-decoration-thickness: initial; text-decoration-style: initial; text-decoration-color: initial;" type="button"></button></span></p> <p style="margin: 0px 0px 10px; padding: 0px; color: rgb(102, 102, 102); font-family: Roboto, sans-serif; font-size: 12px; font-style: normal; font-variant-ligatures: normal; font-variant-caps: normal; font-weight: 400; letter-spacing: normal; orphans: 2; text-align: start; text-indent: 0px; text-transform: none; widows: 2; word-spacing: 0px; -webkit-text-stroke-width: 0px; white-space: normal; text-decoration-thickness: initial; text-decoration-style: initial; text-decoration-color: initial; background-color: rgb(255, 255, 255);"><span style="margin: 0px; padding: 0px; font-size: 16px;"><span style="margin: 0px; padding: 0px; border: none; list-style: none; box-sizing: border-box; line-height: 1.125rem; font-weight: 700; font-family: Poppins, sans-serif !important;">Informações Técnicas:<br style="margin: 0px; padding: 0px;" /> <br style="margin: 0px; padding: 0px;" /> Características:</span></span></p> <p style="margin: 0px 0px 10px; padding: 0px; color: rgb(102, 102, 102); font-family: Roboto, sans-serif; font-size: 12px; font-style: normal; font-variant-ligatures: normal; font-variant-caps: normal; font-weight: 400; letter-spacing: normal; orphans: 2; text-align: start; text-indent: 0px; text-transform: none; widows: 2; word-spacing: 0px; -webkit-text-stroke-width: 0px; white-space: normal; background-color: rgb(255, 255, 255); text-decoration-thickness: initial; text-decoration-style: initial; text-decoration-color: initial;"><br style="margin: 0px; padding: 0px; border: none; list-style: none; box-sizing: border-box; font-size: 16px; font-family: Poppins, sans-serif !important;" /> <span style="margin: 0px; padding: 0px; color: rgb(102, 102, 102); font-family: Roboto, sans-serif; font-size: 16px; background-color: rgb(255, 255, 255);">- Marca: JBL<br style="margin: 0px; padding: 0px; border: none; list-style: none; box-sizing: border-box; font-size: 16px; font-family: Poppins, sans-serif !important;" /> - Modelo: CI6SA PLUS<br style="margin: 0px; padding: 0px; border: none; list-style: none; box-sizing: border-box; font-size: 16px; font-family: Poppins, sans-serif !important;" /> <br style="margin: 0px; padding: 0px; border: none; list-style: none; box-sizing: border-box; font-size: 16px; font-family: Poppins, sans-serif !important;" /> <strong style="margin: 0px; padding: 0px; font-weight: 700; border: none; list-style: none; box-sizing: border-box; font-size: 0.875rem; line-height: 1.125rem; font-family: Poppins, sans-serif !important;">Especificações Técnicas:</strong><br style="margin: 0px; padding: 0px; border: none; list-style: none; box-sizing: border-box; font-size: 16px; font-family: Poppins, sans-serif !important;" /> <br style="margin: 0px; padding: 0px; border: none; list-style: none; box-sizing: border-box; font-size: 16px; font-family: Poppins, sans-serif !important;" /> - Tipo de caixa: Embutir no Gesso<br style="margin: 0px; padding: 0px; border: none; list-style: none; box-sizing: border-box; font-size: 16px; font-family: Poppins, sans-serif !important;" /> - Formato: Quadrado<br style="margin: 0px; padding: 0px; border: none; list-style: none; box-sizing: border-box; font-size: 16px; font-family: Poppins, sans-serif !important;" /> - Sensibilidade: 90dB (@1W/m)<br style="margin: 0px; padding: 0px; border: none; list-style: none; box-sizing: border-box; font-size: 16px; font-family: Poppins, sans-serif !important;" /> - Woofer: Um woofer de 6"<br style="margin: 0px; padding: 0px; border: none; list-style: none; box-sizing: border-box; font-size: 16px; font-family: Poppins, sans-serif !important;" /> - Potência: 160</span><span style="margin: 0px; padding: 0px; color: rgb(102, 102, 102); font-family: Roboto, sans-serif; font-size: 16px; background-color: rgb(255, 255, 255);">W RMS<br style="margin: 0px; padding: 0px; border: none; list-style: none; box-sizing: border-box; font-size: 16px; font-family: Poppins, sans-serif !important;" /> - Impedância: 8 Ohms<br style="margin: 0px; padding: 0px; border: none; list-style: none; box-sizing: border-box; font-size: 16px; font-family: Poppins, sans-serif !important;" /> - Resposta de Frequência: 53Hz - 20KHz<br style="margin: 0px; padding: 0px; border: none; list-style: none; box-sizing: border-box; font-size: 16px; font-family: Poppins, sans-serif !important;" /> - Altura (cm): 23<br style="margin: 0px; padding: 0px; border: none; list-style: none; box-sizing: border-box; font-size: 16px; font-family: Poppins, sans-serif !important;" /> - Espessura (cm): 12<br style="margin: 0px; padding: 0px; border: none; list-style: none; box-sizing: border-box; font-size: 16px; font-family: Poppins, sans-serif !important;" /> - Largura (cm): 23<br style="margin: 0px; padding: 0px; border: none; list-style: none; box-sizing: border-box; font-size: 16px; font-family: Poppins, sans-serif !important;" /> - Peso (kg): 1.80<br style="margin: 0px; padding: 0px; border: none; list-style: none; box-sizing: border-box; font-size: 16px; font-family: Poppins, sans-serif !important;" /> <br style="margin: 0px; padding: 0px; border: none; list-style: none; box-sizing: border-box; font-size: 16px; font-family: Poppins, sans-serif !important;" /> <strong style="margin: 0px; padding: 0px; font-weight: 700; border: none; list-style: none; box-sizing: border-box; font-size: 0.875rem; line-height: 1.125rem; font-family: Poppins, sans-serif !important;">Conteúdo da Embalagem:</strong><br style="margin: 0px; padding: 0px; border: none; list-style: none; box-sizing: border-box; font-size: 16px; font-family: Poppins, sans-serif !important;" /> <br style="margin: 0px; padding: 0px; border: none; list-style: none; box-sizing: border-box; font-size: 16px; font-family: Poppins, sans-serif !important;" /> - Caixa de Embutir Quadrada CI6SA PLUS JBL 160W RMS<br style="margin: 0px; padding: 0px; border: none; list-style: none; box-sizing: border-box; font-size: 16px; font-family: Poppins, sans-serif !important;" /> - Manual de Instalação<br style="margin: 0px; padding: 0px; border: none; list-style: none; box-sizing: border-box; font-size: 16px; font-family: Poppins, sans-serif !important;" /> - Folheto de Segurança</span></p> <p style="margin: 0px; padding: 0px; color: rgb(102, 102, 102); font-style: normal; font-variant-ligatures: normal; font-variant-caps: normal; font-weight: 400; letter-spacing: normal; orphans: 2; text-align: start; text-indent: 0px; text-transform: none; widows: 2; word-spacing: 0px; -webkit-text-stroke-width: 0px; white-space: normal; background-color: rgb(255, 255, 255); text-decoration-thickness: initial; text-decoration-style: initial; text-decoration-color: initial; border: none; list-style: none; box-sizing: border-box; font-size: 0.875rem; line-height: 1.125rem; font-family: Poppins, sans-serif !important;"> </p> <p style="margin: 0px; padding: 0px; color: rgb(102, 102, 102); font-style: normal; font-variant-ligatures: normal; font-variant-caps: normal; font-weight: 400; letter-spacing: normal; orphans: 2; text-align: start; text-indent: 0px; text-transform: none; widows: 2; word-spacing: 0px; -webkit-text-stroke-width: 0px; white-space: normal; background-color: rgb(255, 255, 255); text-decoration-thickness: initial; text-decoration-style: initial; text-decoration-color: initial; border: none; list-style: none; box-sizing: border-box; font-size: 0.875rem; line-height: 1.125rem; font-family: Poppins, sans-serif !important;"><span style="margin: 0px; padding: 0px; font-size: 16px;"><strong style="margin: 0px; padding: 0px; font-weight: 700; border: none; list-style: none; box-sizing: border-box; font-size: 0.875rem; line-height: 1.125rem; font-family: Poppins, sans-serif !important;">Garantia do Fornecedor</strong></span></p> <p style="margin: 0px; padding: 0px; color: rgb(102, 102, 102); font-style: normal; font-variant-ligatures: normal; font-variant-caps: normal; font-weight: 400; letter-spacing: normal; orphans: 2; text-align: start; text-indent: 0px; text-transform: none; widows: 2; word-spacing: 0px; -webkit-text-stroke-width: 0px; white-space: normal; background-color: rgb(255, 255, 255); text-decoration-thickness: initial; text-decoration-style: initial; text-decoration-color: initial; border: none; list-style: none; box-sizing: border-box; font-size: 0.875rem; line-height: 1.125rem; font-family: Poppins, sans-serif !important;"><span style="margin: 0px; padding: 0px; font-size: 16px;">12 meses</span></p> <p style="margin: 0px; padding: 0px; color: rgb(102, 102, 102); font-style: normal; font-variant-ligatures: normal; font-variant-caps: normal; font-weight: 400; letter-spacing: normal; orphans: 2; text-align: start; text-indent: 0px; text-transform: none; widows: 2; word-spacing: 0px; -webkit-text-stroke-width: 0px; white-space: normal; background-color: rgb(255, 255, 255); text-decoration-thickness: initial; text-decoration-style: initial; text-decoration-color: initial; border: none; list-style: none; box-sizing: border-box; font-size: 0.875rem; line-height: 1.125rem; font-family: Poppins, sans-serif !important;"> </p> <p style="margin: 0px; padding: 0px; color: rgb(102, 102, 102); font-style: normal; font-variant-ligatures: normal; font-variant-caps: normal; font-weight: 400; letter-spacing: normal; orphans: 2; text-align: start; text-indent: 0px; text-transform: none; widows: 2; word-spacing: 0px; -webkit-text-stroke-width: 0px; white-space: normal; background-color: rgb(255, 255, 255); text-decoration-thickness: initial; text-decoration-style: initial; text-decoration-color: initial; border: none; list-style: none; box-sizing: border-box; font-size: 0.875rem; line-height: 1.125rem; font-family: Poppins, sans-serif !important;"><span style="margin: 0px; padding: 0px; font-size: 16px;"><strong style="margin: 0px; padding: 0px; font-weight: 700; border: none; list-style: none; box-sizing: border-box; font-size: 0.875rem; line-height: 1.125rem; font-family: Poppins, sans-serif !important;">Fabricante</strong></span></p> <p style="margin: 0px; padding: 0px; color: rgb(102, 102, 102); font-style: normal; font-variant-ligatures: normal; font-variant-caps: normal; font-weight: 400; letter-spacing: normal; orphans: 2; text-align: start; text-indent: 0px; text-transform: none; widows: 2; word-spacing: 0px; -webkit-text-stroke-width: 0px; white-space: normal; background-color: rgb(255, 255, 255); text-decoration-thickness: initial; text-decoration-style: initial; text-decoration-color: initial; border: none; list-style: none; box-sizing: border-box; font-size: 0.875rem; line-height: 1.125rem; font-family: Poppins, sans-serif !important;"><span style="margin: 0px; padding: 0px; font-size: 16px;">JBL</span></p> <p style="margin: 0px; padding: 0px; color: rgb(102, 102, 102); font-style: normal; font-variant-ligatures: normal; font-variant-caps: normal; font-weight: 400; letter-spacing: normal; orphans: 2; text-align: start; text-indent: 0px; text-transform: none; widows: 2; word-spacing: 0px; -webkit-text-stroke-width: 0px; white-space: normal; background-color: rgb(255, 255, 255); text-decoration-thickness: initial; text-decoration-style: initial; text-decoration-color: initial; border: none; list-style: none; box-sizing: border-box; font-size: 0.875rem; line-height: 1.125rem; font-family: Poppins, sans-serif !important;"> </p> <p style="margin: 0px; padding: 0px; color: rgb(102, 102, 102); font-style: normal; font-variant-ligatures: normal; font-variant-caps: normal; font-weight: 400; letter-spacing: normal; orphans: 2; text-align: start; text-indent: 0px; text-transform: none; widows: 2; word-spacing: 0px; -webkit-text-stroke-width: 0px; white-space: normal; background-color: rgb(255, 255, 255); text-decoration-thickness: initial; text-decoration-style: initial; text-decoration-color: initial; border: none; list-style: none; box-sizing: border-box; font-size: 0.875rem; line-height: 1.125rem; font-family: Poppins, sans-serif !important;"><span style="margin: 0px; padding: 0px; font-size: 16px;"><strong style="margin: 0px; padding: 0px; font-weight: 700; border: none; list-style: none; box-sizing: border-box; font-size: 0.875rem; line-height: 1.125rem; font-family: Poppins, sans-serif !important;">Modelo</strong></span></p> <p style="margin: 0px; padding: 0px; color: rgb(102, 102, 102); font-style: normal; font-variant-ligatures: normal; font-variant-caps: normal; font-weight: 400; letter-spacing: normal; orphans: 2; text-align: start; text-indent: 0px; text-transform: none; widows: 2; word-spacing: 0px; -webkit-text-stroke-width: 0px; white-space: normal; background-color: rgb(255, 255, 255); text-decoration-thickness: initial; text-decoration-style: initial; text-decoration-color: initial; border: none; list-style: none; box-sizing: border-box; font-size: 0.875rem; line-height: 1.125rem; font-family: Poppins, sans-serif !important;"><span style="margin: 0px; padding: 0px; font-size: 16px;">Caixa de Som de Embutir JBL CI6SA PLUS Quadrada 160W Rms</span></p> | T4: N | V4: 389.9 | X4: JBL | Y4: 2 | Z4: 28 | AA4: 28 | AB4: 18 | AH4: https://cdn.awsli.com.br/948/948321/produto/263282847/1-9a4khbfhsx.PNG | AI4: https://cdn.awsli.com.br/948/948321/produto/263282847/3-x8xnjaymeh.PNG | AJ4: https://cdn.awsli.com.br/948/948321/produto/263282847/2-nibs0s5h9r.PNG
A5: Cabo Rca Automotivo Y 1 Macho + 2 Fêmeas 90 Graus 25cm | B5: 14 | C5: S | D5: imediata | E5: indisponivel | F5: S | G5: N | H5: 72457584 | I5: sem-variacao | K5: XPT8SP5DC | L5: N | R5: <p><span style="font-size:16px;"><span style="font-family:trebuchet ms,helvetica,sans-serif;"><span style="color: rgb(102, 102, 102);">Utilizado nas ligações de equipamentos auxiliar de Áudio.</span><br style="box-sizing: border-box; color: rgb(102, 102, 102); font-family: &quot;Proxima Nova&quot;, -apple-system, &quot;Helvetica Neue&quot;, Helvetica, Roboto, Arial, sans-serif; font-size: 20px;" /> <span style="color: rgb(102, 102, 102);">Específico para som automotivo, simplesmente plugue em cada extremidade.</span><br style="box-sizing: border-box; color: rgb(102, 102, 102); font-family: &quot;Proxima Nova&quot;, -apple-system, &quot;Helvetica Neue&quot;, Helvetica, Roboto, Arial, sans-serif; font-size: 20px;" /> <br style="box-sizing: border-box; color: rgb(102, 102, 102); font-family: &quot;Proxima Nova&quot;, -apple-system, &quot;Helvetica Neue&quot;, Helvetica, Roboto, Arial, sans-serif; font-size: 20px;" /> <span style="color: rgb(102, 102, 102);">INFORMAÇÕES ADICIONAIS</span><br style="box-sizing: border-box; color: rgb(102, 102, 102); font-family: &quot;Proxima Nova&quot;, -apple-system, &quot;Helvetica Neue&quot;, Helvetica, Roboto, Arial, sans-serif; font-size: 20px;" /> <span style="color: rgb(102, 102, 102);">Conexão: 1 RCA Macho + 2 RCA Fêmeas 90º Graus.</span><br style="box-sizing: border-box; color: rgb(102, 102, 102); font-family: &quot;Proxima Nova&quot;, -apple-system, &quot;Helvetica Neue&quot;, Helvetica, Roboto, Arial, sans-serif; font-size: 20px;" /> <span style="color: rgb(102, 102, 102);">Cabo: 4mm.</span><br style="box-sizing: border-box; color: rgb(102, 102, 102); font-family: &quot;Proxima Nova&quot;, -apple-system, &quot;Helvetica Neue&quot;, Helvetica, Roboto, Arial, sans-serif; font-size: 20px;" /> <span style="color: rgb(102, 102, 102);">Comprimento: 0,25cm.</span><br style="box-sizing: border-box; color: rgb(102, 102, 102); font-family: &quot;Proxima Nova&quot;, -apple-system, &quot;Helvetica Neue&quot;, Helvetica, Roboto, Arial, sans-serif; font-size: 20px;" /> <span style="color: rgb(102, 102, 102);">Cor: Preto.</span><br style="box-sizing: border-box; color: rgb(102, 102, 102); font-family: &quot;Proxima Nova&quot;, -apple-system, &quot;Helvetica Neue&quot;, Helvetica, Roboto, Arial, sans-serif; font-size: 20px;" /> <span style="color: rgb(102, 102, 102);">Comprimento do cabo: 0,25 Metro</span><br style="box-sizing: border-box; color: rgb(102, 102, 102); font-family: &quot;Proxima Nova&quot;, -apple-system, &quot;Helvetica Neue&quot;, Helvetica, Roboto, Arial, sans-serif; font-size: 20px;" /> <span style="color: rgb(102, 102, 102);">Conexão: Y 90 Graus</span><br style="box-sizing: border-box; color: rgb(102, 102, 102); font-family: &quot;Proxima Nova&quot;, -apple-system, &quot;Helvetica Neue&quot;, Helvetica, Roboto, Arial, sans-serif; font-size: 20px;" /> <span style="color: rgb(102, 102, 102);">Cor: Preto</span><br style="box-sizing: border-box; color: rgb(102, 102, 102); font-family: &quot;Proxima Nova&quot;, -apple-system, &quot;Helvetica Neue&quot;, Helvetica, Roboto, Arial, sans-serif; font-size: 20px;" /> <span style="color: rgb(102, 102, 102);">Embalagem: Polybag</span><br style="box-sizing: border-box; color: rgb(102, 102, 102); font-family: &quot;Proxima Nova&quot;, -apple-system, &quot;Helvetica Neue&quot;, Helvetica, Roboto, Arial, sans-serif; font-size: 20px;" /> <span style="color: rgb(102, 102, 102);">MM: 4mm</span><br style="box-sizing: border-box; color: rgb(102, 102, 102); font-family: &quot;Proxima Nova&quot;, -apple-system, &quot;Helvetica Neue&quot;, Helvetica, Roboto, Arial, sans-serif; font-size: 20px;" /> <span style="color: rgb(102, 102, 102);">Ponta: Gold</span><br style="box-sizing: border-box; color: rgb(102, 102, 102); font-family: &quot;Proxima Nova&quot;, -apple-system, &quot;Helvetica Neue&quot;, Helvetica, Roboto, Arial, sans-serif; font-size: 20px;" /> <span style="color: rgb(102, 102, 102);">Série: Automotivo</span></span></span></p> | T5: N | V5: 29.9 | X5: PIX | Y5: 0.2 | Z5: 20 | AA5: 20 | AB5: 10 | AH5: https://cdn.awsli.com.br/948/948321/produto/72457584/0cd1a849bb.jpg
A6: Pure Acoustics Proxima 60C - Caixa acústica Central 150w - Preto | B6: 10 | C6: S | D6: 4 dias | E6: indisponivel | F6: N | G6: N | H6: 61709088 | I6: sem-variacao | K6: Multimport-003 | L6: N | R6: <p><span style="font-size:16px;"><span style="font-family:verdana,geneva,sans-serif;"><strong>A perfeição está a apenas decibéis de distância</strong><br /> Os alto-falantes da série PROXIMA garantem uma qualidade de som incomparável, seja assistindo a filmes em sistema de som surround ou ouvindo gravações de música estéreo. O som é rico, dinâmico e livre de distorções. Os três drivers de 6,5 "oferecem uma reprodução de som excepcional com distorção mínima, enquanto o subwoofer de 10" oferece graves profundos e dinâmicos. O acabamento de alto brilho exclusivo adiciona um toque moderno que irá complementar qualquer cômodo da casa.</span></span></p> <p><strong><span style="font-size:16px;"><span style="font-family:verdana,geneva,sans-serif;">PROXIMA Center</span></span></strong></p> <p><span style="font-size:16px;"><span style="font-family:verdana,geneva,sans-serif;">- Dois woofers de 5,25 "oferecem uma dispersão de som realista com distorção mínima<br /> - Tweeter de cúpula de seda de 1 "com sistema de resfriamento de óleo para agudos cristalinos<br /> - Drivers com blindagem magnética eliminam a interferência de componentes eletrônicos próximos<br /> - Poderosa potência de saída de 150 W de 3 vias fornece distribuição de som equilibrada<br /> - Acabamento de piano moderno que irá melhorar qualquer configuração</span></span></p> <p><span style="font-size:16px;"><span style="font-family:verdana,geneva,sans-serif;"><strong>Potência da saída:</strong> 150 watts<br /> <strong>Resposta de frequência:</strong> 65 Hz - 20 KHz<br /> <strong>Sensibilidade:</strong> 89 dB<br /> <strong>Impedância:</strong> 8 ohm<br /> <strong>Woofer:</strong> 2 x 5 "<br /> <strong>Tweeter:</strong> 1 "<br /> <strong>Dimensões do produto:</strong> 17,5 x 55 x 18 cm<br /> <strong>Peso do Produto:</strong> 8 Kg</span></span></p> <p> </p> <p> </p> | T6: N | V6: 1350 | X6: Pure Acoustics | Y6: 8.5 | Z6: 20 | AA6: 60 | AB6: 20 | AC6: Sonorização | AD6: Caixas de Som | AH6: https://cdn.awsli.com.br/948/948321/produto/61709088/ac3fe464c8.jpg
A7: Microfone De Calibração Acm1hb. Receiver Denon/marantz/jbl, Harman, Sony, Onkyo | B7: 10 | C7: S | D7: imediata | E7: indisponivel | F7: S | G7: N | H7: 110443186 | I7: sem-variacao | K7: NVJ345DVC | L7: S | P7: Microfone De Calibração Acm1hb. Receiver Denon/marantz/jbl, Harman, | Q7: MICROFONE DE CALIBRAÇÃO RECEIVER DENON AUDYSSEY MICROFONE PARA CALIBRAÇÃO AUTOMÁTICA DE RECEIVERS PRODUTO NOVO NA CAIXA ORIGINAL 100% ORIGINAL MICROFONE AUDISSEY ORIGINAL PARA CALIBRAÇÃO DE RECEIVERS: DENON, MARANTZ, HARMAN, ONKYO, JBL, | R7: <p>MICROFONE DE CALIBRAÇÃO RECEIVER DENON AUDYSSEY<br /> MICROFONE PARA CALIBRAÇÃO AUTOMÁTICA DE RECEIVERS<br /> PRODUTO NOVO NA CAIXA ORIGINAL<br /> 100% ORIGINAL<br /> DENON -DMA409<br /> MICROFONE AUDISSEY ORIGINAL PARA CALIBRAÇÃO DE RECEIVERS:<br /> DENON, MARANTZ, HARMAN, ONKYO, JBL, OUTROS.</p> <p>!!!DUVIDAS NOS CONSULTE-NOS!!!</p> | T7: N | V7: 189 | W7: 159 | X7: DENON | Y7: 1 | Z7: 20 | AA7: 20 | AB7: 20 | AH7: https://cdn.awsli.com.br/948/948321/produto/110443186/9aa230bf7a.jpg | AI7: https://cdn.awsli.com.br/948/948321/produto/110443186/d367c6bde7.jpg
B8: 10 | C8: S | D8: 10 dias | E8: 10 dias | F8: S | G8: N | H8: 265737859 | I8: variacao | J8: PA6QDGV2B | K8: PA6QDGV2B-1m | L8: N | T8: N | V8: 146.5 | Y8: 0.2 | Z8: 5 | AA8: 5 | AB8: 5 | AY8: 1m
B9: 10 | C9: S | D9: 10 dias | E9: 10 dias | F9: S | G9: N | H9: 265738307 | I9: variacao | J9: PA6QDGV2B | K9: PA6QDGV2B-2m | L9: N | T9: N | V9: 170.5 | Y9: 0.4 | Z9: 10 | AA9: 10 | AB9: 10 | AY9: 2m
B10: 10 | C10: S | D10: 10 dias | E10: 10 dias | F10: S | G10: N | H10: 265738655 | I10: variacao | J10: PA6QDGV2B | K10: PA6QDGV2B-3m | L10: N | T10: N | V10: 227 | Y10: 0.5 | Z10: 10 | AA10: 10 | AB10: 10 | AY10: 3m
B11: 10 | C11: S | D11: 10 dias | E11: 10 dias | F11: S | G11: N | H11: 265738971 | I11: variacao | J11: PA6QDGV2B | K11: PA6QDGV2B-5m | L11: N | T11: N | V11: 299 | Y11: 0.5 | Z11: 10 | AA11: 10 | AB11: 10 | AY11: 5m
B12: 10 | C12: S | D12: 10 dias | E12: 10 dias | F12: S | G12: N | H12: 265739169 | I12: variacao | J12: PA6QDGV2B | K12: PA6QDGV2B-10m | L12: N | T12: N | V12: 495 | Y12: 0.7 | Z12: 11 | AA12: 11 | AB12: 11 | AY12: 10m
B13: 10 | C13: S | D13: 10 dias | E13: 10 dias | F13: S | G13: N | H13: 265741680 | I13: variacao | J13: PA6QDGV2B-83EZCXF76 | K13: PA6QDGV2B-10m-ED9W6C7RU | L13: N | T13: N | V13: 382 | Y13: 0.7 | Z13: 11 | AA13: 11 | AB13: 11 | AY13: 10m
B14: 10 | C14: S | D14: 10 dias | E14: 10 dias | F14: S | G14: N | H14: 265741681 | I14: variacao | J14: PA6QDGV2B-83EZCXF76 | K14: PA6QDGV2B-5m-PGSW6H6XU | L14: N | T14: N | V14: 207 | Y14: 0.5 | Z14: 10 | AA14: 10 | AB14: 10 | AY14: 5m
B15: 10 | C15: S | D15: 10 dias | E15: 10 dias | F15: S | G15: N | H15: 265741682 | I15: variacao | J15: PA6QDGV2B-83EZCXF76 | K15: PA6QDGV2B-3m-MLPAABLG5 | L15: N | T15: N | V15: 170.5 | Y15: 0.5 | Z15: 10 | AA15: 10 | AB15: 10 | AY15: 3m
B16: 10 | C16: S | D16: 10 dias | E16: 10 dias | F16: S | G16: N | H16: 265741684 | I16: variacao | J16: PA6QDGV2B-83EZCXF76 | K16: PA6QDGV2B-2m-XMJV7LBG0 | L16: N | T16: N | V16: 134.5 | Y16: 0.4 | Z16: 10 | AA16: 10 | AB16: 10 | AY16: 2m
B17: 10 | C17: S | D17: 10 dias | E17: 10 dias | F17: S | G17: N | H17: 265741685 | I17: variacao | J17: PA6QDGV2B-83EZCXF76 | K17: PA6QDGV2B-1m-4LWY4D2VP | L17: N | T17: N | V17: 114 | Y17: 0.2 | Z17: 5 | AA17: 5 | AB17: 5 | AY17: 1m
A18: Kit Passador De Fio Expansível | B18: 7 | C18: S | D18: imediata | E18: indisponivel | F18: S | G18: N | H18: 269286278 | I18: sem-variacao | K18: KQYSSUB6X | L18: N | R18: <p><strong><span style="font-size:14px;">Descrição</span></strong></p> <p><span style="font-size:14px;">Você que é profissional da área de elétrica, telecom ou afins e que já se deparou com a dificuldade em pescar fios em cima de forros, sabe que tempo é dinheiro.<br /> Esse Kit vem para facilitar sua vida na obra, ele acompanha vários acessórios que permitem você pescar ou passar fiação de forma fácil e tranquila por cima do forro, por ser expansível é possível ter até 11m de pescador, sua embalagem é slim e cabe em qualquer carro é leve e fácil de carregar.<br /> Adquira agora mesmo esse Kit passador de fio expansível, e veja seu tempo ser economizado com essa excelente ferramenta!</span></p> <p style="box-sizing: border-box; border: 0px; font-size: 14px; font-style: normal; font-weight: 500; margin: 0px 0px 1.75em; outline: 0px; padding: 0px; vertical-align: baseline; color: rgb(75, 79, 88); font-family: Montserrat, sans-serif; font-variant-ligatures: normal; font-variant-caps: normal; letter-spacing: normal; orphans: 2; text-align: start; text-indent: 0px; text-transform: none; widows: 2; word-spacing: 0px; -webkit-text-stroke-width: 0px; white-space: normal; background-color: rgb(255, 255, 255); text-decoration-thickness: initial; text-decoration-style: initial; text-decoration-color: initial;"><span style="font-size:14px;"><strong style="box-sizing: border-box; font-weight: 700;">Especificações Técnicas:</strong><br style="box-sizing: border-box;" /> A Vara de Pescar Cabos de Fibra Óptica é uma ferramenta indicada para acessar cabos ópticos e eltricos em lugares de difícil acesso, como no teto, em cavidade de calhas, em tubos no chão e em paredes.<br style="box-sizing: border-box;" /> A Vara de Pescar cabos de Fibra Óptica é composta por 10 hastes que são confeccionadas em fibra de vidro, na extremidade de cada haste há conectores rosqueáveis em cobre, que possuem o objetivo de ajustar o produto com a necessidade do profissional.</span></p> <p style="box-sizing: border-box; border: 0px; font-size: 14px; font-style: normal; font-weight: 500; margin: 0px 0px 1.75em; outline: 0px; padding: 0px; vertical-align: baseline; color: rgb(75, 79, 88); font-family: Montserrat, sans-serif; font-variant-ligatures: normal; font-variant-caps: normal; letter-spacing: normal; orphans: 2; text-align: start; text-indent: 0px; text-transform: none; widows: 2; word-spacing: 0px; -webkit-text-stroke-width: 0px; white-space: normal; background-color: rgb(255, 255, 255); text-decoration-thickness: initial; text-decoration-style: initial; text-decoration-color: initial;"><span style="font-size:14px;"><strong style="box-sizing: border-box; font-weight: 700;">Dimensões e Peso:</strong><br style="box-sizing: border-box;" /> Comprimento: 101cm cada haste<br style="box-sizing: border-box;" /> Diâmetro: 6mm<br style="box-sizing: border-box;" /> Peso: 1.030 Kg (Estojo com todas as peças)</span></p> <p style="box-sizing: border-box; border: 0px; font-size: 14px; font-style: normal; font-weight: 500; margin: 0px 0px 1.75em; outline: 0px; padding: 0px; vertical-align: baseline; color: rgb(75, 79, 88); font-family: Montserrat, sans-serif; font-variant-ligatures: normal; font-variant-caps: normal; letter-spacing: normal; orphans: 2; text-align: start; text-indent: 0px; text-transform: none; widows: 2; word-spacing: 0px; -webkit-text-stroke-width: 0px; white-space: normal; background-color: rgb(255, 255, 255); text-decoration-thickness: initial; text-decoration-style: initial; text-decoration-color: initial;"><span style="font-size:14px;"><strong style="box-sizing: border-box; font-weight: 700;">Conteúdo:</strong><br style="box-sizing: border-box;" /> 1 estojo para armazenar as peças Vara de Pescar Cabos de Fibra Óptica OT-8910-VA<br style="box-sizing: border-box;" /> 10 hastes com conectores de bronze rosqueáveis<br style="box-sizing: border-box;" /> 1 conexão flexível<br style="box-sizing: border-box;" /> 1 luz de led em uma das extremidades<br style="box-sizing: border-box;" /> 1 Gancho de bronze rosqueável<br style="box-sizing: border-box;" /> 1 Gancho para pescar cabos de fibra óptica<br style="box-sizing: border-box;" /> 1 Anel<br style="box-sizing: border-box;" /> 1 Fio de puxa<br style="box-sizing: border-box;" /> 1 Fio de puxar a fibra óptica<br style="box-sizing: border-box;" /> 1 Ímã<br style="box-sizing: border-box;" /> 1 Anel de 6 mm<br style="box-sizing: border-box;" /> 1 Anel de 4 mm</span></p> | T18: N | V18: 590 | Y18: 1 | Z18: 99 | AA18: 3 | AB18: 3 | AH18: https://cdn.awsli.com.br/948/948321/produto/269286278/whatsapp-image-2024-05-22-at-07-42-49--2--x7zrxdhy82.jpeg | AI18: https://cdn.awsli.com.br/948/948321/produto/269286278/whatsapp-image-2024-05-22-at-07-42-48--1--vz8rsbwq5c.jpeg | AJ18: https://cdn.awsli.com.br/948/948321/produto/269286278/whatsapp-image-2024-05-22-at-07-42-49-y86dgod1xn.jpeg | AK18: https://cdn.awsli.com.br/948/948321/produto/269286278/whatsapp-image-2024-05-22-at-07-42-49--1--zcerqgk8mg.jpeg | AL18: https://cdn.awsli.com.br/948/948321/produto/269286278/whatsapp-image-2024-05-22-at-07-42-48-nw8oncvqk0.jpeg
A19: CABO DE ÁUDIO ÓPTICO DIGITAL TOSLINK PIX 3m | B19: 6 | C19: S | D19: imediata | E19: indisponivel | F19: S | G19: N | H19: 59336787 | I19: sem-variacao | K19: XV856JDLM | L19: N | R19: <p><span style="font-size:16px;"><span style="font-family:verdana,geneva,sans-serif;">Você merece o melhor som digital e sem nenhum tipo de interferências ou distorção!</span></span></p> <p><span style="font-size:16px;"><span style="font-family:verdana,geneva,sans-serif;">Aproveite o máximo de fidelidade e desempenho sonoro dos seus equipamentos com o Cabo Ótico Digital da CHIP SCE. Com ele você poderá ter uma transmissão livre de interferências e qualidade incomparável de áudio.</span></span></p> <p><span style="font-size:16px;"><span style="font-family:verdana,geneva,sans-serif;">Indicado para equipamentos que utilizam conexão óptica como: Blu-ray, TV's, receptores de TV Digital, vídeo games, receivers, DVD, home theaters e demais equipamentos que se adéquam à este sistema.</span></span></p> <p> </p> <p><span style="font-size:16px;"><span style="font-family:verdana,geneva,sans-serif;"><strong>Especificações Técnicas:</strong></span></span></p> <p><span style="font-size:16px;"><span style="font-family:verdana,geneva,sans-serif;">Tamanho: 03 metros</span></span></p> <p><span style="font-size:16px;"><span style="font-family:verdana,geneva,sans-serif;">Conectores: Toslink - Gold</span></span></p> <p><span style="font-size:16px;"><span style="font-family:verdana,geneva,sans-serif;">Cabo: Fibra Ótica</span></span></p> <p><span style="font-size:16px;"><span style="font-family:verdana,geneva,sans-serif;">Aplicações: Blu-Ray, Receptores de Imagens digitais, Vídeo Games, Receivers, DVD, TVs e Home Theater.</span></span></p> <p><span style="font-size:16px;"><span style="font-family:verdana,geneva,sans-serif;"><strong>Conteúdo da embalagem:</strong><br /> 01 - Cabo Ótico de 3 metros</span></span></p> | T19: N | V19: 21.99 | X19: PIX | Y19: 0.8 | Z19: 12 | AA19: 12 | AB19: 12 | AH19: https://cdn.awsli.com.br/948/948321/produto/59336787/7cc66b3cf4.jpg
A20: CABO DE ÁUDIO ÓPTICO DIGITAL TOSLINK PIX 10m | B20: 6 | C20: S | D20: imediata | E20: indisponivel | F20: S | G20: N | H20: 59340752 | I20: sem-variacao | K20: TOSLINK10M | L20: N | R20: <p><span style="font-size:16px;"><span style="font-family:verdana,geneva,sans-serif;"><span style="color: rgb(102, 102, 102);">Você merece o melhor som digital e sem nenhum tipo de interferências ou distorção!</span><br style="box-sizing: border-box; color: rgb(102, 102, 102); font-family: &quot;Proxima Nova&quot;, -apple-system, &quot;Helvetica Neue&quot;, Helvetica, Roboto, Arial, sans-serif; font-size: 20px;" /> <span style="color: rgb(102, 102, 102);">Aproveite o máximo de fidelidade e desempenho sonoro dos seus equipamentos com o Cabo Ótico Digital da CHIP SCE. Com ele você poderá ter uma transmissão livre de interferências e qualidade incomparável de áudio.</span><br style="box-sizing: border-box; color: rgb(102, 102, 102); font-family: &quot;Proxima Nova&quot;, -apple-system, &quot;Helvetica Neue&quot;, Helvetica, Roboto, Arial, sans-serif; font-size: 20px;" /> <span style="color: rgb(102, 102, 102);">Indicado para equipamentos que utilizam conexão óptica como: Blu-ray, TV's, receptores de TV Digital, vídeo games, receivers, DVD, home theaters e demais equipamentos que se adéquam à este sistema.</span><br style="box-sizing: border-box; color: rgb(102, 102, 102); font-family: &quot;Proxima Nova&quot;, -apple-system, &quot;Helvetica Neue&quot;, Helvetica, Roboto, Arial, sans-serif; font-size: 20px;" /> <br style="box-sizing: border-box; color: rgb(102, 102, 102); font-family: &quot;Proxima Nova&quot;, -apple-system, &quot;Helvetica Neue&quot;, Helvetica, Roboto, Arial, sans-serif; font-size: 20px;" /> <strong><span style="color: rgb(102, 102, 102);">Especificações Técnicas:</span></strong><br style="box-sizing: border-box; color: rgb(102, 102, 102); font-family: &quot;Proxima Nova&quot;, -apple-system, &quot;Helvetica Neue&quot;, Helvetica, Roboto, Arial, sans-serif; font-size: 20px;" /> <span style="color: rgb(102, 102, 102);">Tamanho: </span><span style="color: rgb(102, 102, 102);">10 metros</span><br style="box-sizing: border-box; color: rgb(102, 102, 102); font-family: &quot;Proxima Nova&quot;, -apple-system, &quot;Helvetica Neue&quot;, Helvetica, Roboto, Arial, sans-serif; font-size: 20px;" /> <span style="color: rgb(102, 102, 102);">Conectores: </span><span style="color: rgb(102, 102, 102);">Toslink - Gold</span><br style="box-sizing: border-box; color: rgb(102, 102, 102); font-family: &quot;Proxima Nova&quot;, -apple-system, &quot;Helvetica Neue&quot;, Helvetica, Roboto, Arial, sans-serif; font-size: 20px;" /> <span style="color: rgb(102, 102, 102);">Cabo: </span><span style="color: rgb(102, 102, 102);">Fibra Ótica</span><br style="box-sizing: border-box; color: rgb(102, 102, 102); font-family: &quot;Proxima Nova&quot;, -apple-system, &quot;Helvetica Neue&quot;, Helvetica, Roboto, Arial, sans-serif; font-size: 20px;" /> <span style="color: rgb(102, 102, 102);">Aplicações: </span><span style="color: rgb(102, 102, 102);">Blu-Ray, Receptores de Imagens digitais, Vídeo Games, Receivers, DVD, TVs e Home Theater.</span><br style="box-sizing: border-box; color: rgb(102, 102, 102); font-family: &quot;Proxima Nova&quot;, -apple-system, &quot;Helvetica Neue&quot;, Helvetica, Roboto, Arial, sans-serif; font-size: 20px;" /> <br style="box-sizing: border-box; color: rgb(102, 102, 102); font-family: &quot;Proxima Nova&quot;, -apple-system, &quot;Helvetica Neue&quot;, Helvetica, Roboto, Arial, sans-serif; font-size: 20px;" /> <strong><span style="color: rgb(102, 102, 102);">Conteúdo da embalagem:</span></strong><br style="box-sizing: border-box; color: rgb(102, 102, 102); font-family: &quot;Proxima Nova&quot;, -apple-system, &quot;Helvetica Neue&quot;, Helvetica, Roboto, Arial, sans-serif; font-size: 20px;" /> <span style="color: rgb(102, 102, 102);">01 - Cabo Ótico de 10 metros</span></span></span></p> | T20: N | V20: 49.99 | X20: PIX | Y20: 0.8 | Z20: 12 | AA20: 12 | AB20: 10 | AH20: https://cdn.awsli.com.br/948/948321/produto/59340752/680c55ce4a.jpg | AI20: https://cdn.awsli.com.br/948/948321/produto/59340752/16bd3c23e0.jpg
A21: SUBWOOFER JBL CI8P ATIVO 100W 8 POLEGADAS PRETO | B21: 6 | C21: S | D21: imediata | E21: indisponivel | F21: S | G21: N | H21: 257657248 | I21: sem-variacao | K21: YN6HLEYU3 | L21: N | P21: SUBWOOFER JBL CI8P ATIVO 100W 8 POLEGADAS PRETO | Q21: Subwoofer JBL Ci8P Ativo 100w 8 Polegadas Preto O subwoofer JBL CI8P é desenhado para atender o mercado especializado de home e o mercado de instalação.Apresenta excelente performance sonora e é de fácil instalação, o seu design MODERNO e CLEAN, | R21: <p style="margin: 0px 0px 10px; padding: 0px; color: rgb(102, 102, 102); font-family: Montserrat; font-size: 12px; font-style: normal; font-variant-ligatures: normal; font-variant-caps: normal; font-weight: 400; letter-spacing: normal; orphans: 2; text-align: start; text-indent: 0px; text-transform: none; widows: 2; word-spacing: 0px; -webkit-text-stroke-width: 0px; white-space: normal; background-color: rgb(255, 255, 255); text-decoration-thickness: initial; text-decoration-style: initial; text-decoration-color: initial;"><span style="color:#000000;"><span style="font-size:14px;"><span style="font-family:Arial,Helvetica,sans-serif;">O subwoofer JBL CI8P é desenhado para atender o mercado especializado de home e o mercado de instalação.</span></span></span></p> <p style="margin: 0px 0px 10px; padding: 0px; color: rgb(102, 102, 102); font-family: Montserrat; font-size: 12px; font-style: normal; font-variant-ligatures: normal; font-variant-caps: normal; font-weight: 400; letter-spacing: normal; orphans: 2; text-align: start; text-indent: 0px; text-transform: none; widows: 2; word-spacing: 0px; -webkit-text-stroke-width: 0px; white-space: normal; background-color: rgb(255, 255, 255); text-decoration-thickness: initial; text-decoration-style: initial; text-decoration-color: initial;"><span style="color:#000000;"><span style="font-size:14px;"><span style="font-family:Arial,Helvetica,sans-serif;">Apresenta excelente performance sonora e é de fácil instalação, o seu design MODERNO e CLEAN, atende aos mais diversos tipos de ambientes e decorações.</span></span></span></p> <p style="margin: 0px 0px 10px; padding: 0px; color: rgb(102, 102, 102); font-family: Montserrat; font-size: 12px; font-style: normal; font-variant-ligatures: normal; font-variant-caps: normal; font-weight: 400; letter-spacing: normal; orphans: 2; text-align: start; text-indent: 0px; text-transform: none; widows: 2; word-spacing: 0px; -webkit-text-stroke-width: 0px; white-space: normal; background-color: rgb(255, 255, 255); text-decoration-thickness: initial; text-decoration-style: initial; text-decoration-color: initial;"><span style="color:#000000;"><span style="font-size:14px;"><span style="font-family:Arial,Helvetica,sans-serif;">Modeloativocompotênciade100WattsRMS</span></span></span></p> <p style="margin: 0px 0px 10px; padding: 0px; color: rgb(102, 102, 102); font-family: Montserrat; font-size: 12px; font-style: normal; font-variant-ligatures: normal; font-variant-caps: normal; font-weight: 400; letter-spacing: normal; orphans: 2; text-align: start; text-indent: 0px; text-transform: none; widows: 2; word-spacing: 0px; -webkit-text-stroke-width: 0px; white-space: normal; background-color: rgb(255, 255, 255); text-decoration-thickness: initial; text-decoration-style: initial; text-decoration-color: initial;"><span style="color:#000000;"><span style="font-size:14px;"><span style="font-family:Arial,Helvetica,sans-serif;">Altofalantedepolicelulosede8”</span></span></span></p> <p style="margin: 0px 0px 10px; padding: 0px; color: rgb(102, 102, 102); font-family: Montserrat; font-size: 12px; font-style: normal; font-variant-ligatures: normal; font-variant-caps: normal; font-weight: 400; letter-spacing: normal; orphans: 2; text-align: start; text-indent: 0px; text-transform: none; widows: 2; word-spacing: 0px; -webkit-text-stroke-width: 0px; white-space: normal; background-color: rgb(255, 255, 255); text-decoration-thickness: initial; text-decoration-style: initial; text-decoration-color: initial;"><span style="color:#000000;"><span style="font-size:14px;"><span style="font-family:Arial,Helvetica,sans-serif;">Gabinete do tipo bass-reflex</span></span></span></p> <p style="margin: 0px 0px 10px; padding: 0px; color: rgb(102, 102, 102); font-family: Montserrat; font-size: 12px; font-style: normal; font-variant-ligatures: normal; font-variant-caps: normal; font-weight: 400; letter-spacing: normal; orphans: 2; text-align: start; text-indent: 0px; text-transform: none; widows: 2; word-spacing: 0px; -webkit-text-stroke-width: 0px; white-space: normal; background-color: rgb(255, 255, 255); text-decoration-thickness: initial; text-decoration-style: initial; text-decoration-color: initial;"><span style="color:#000000;"><span style="font-size:14px;"><span style="font-family:Arial,Helvetica,sans-serif;">Controle de volume e entrada do tipo RCA(modo normal e LFE)</span></span></span></p> <p style="margin: 0px 0px 10px; padding: 0px; color: rgb(102, 102, 102); font-family: Montserrat; font-size: 12px; font-style: normal; font-variant-ligatures: normal; font-variant-caps: normal; font-weight: 400; letter-spacing: normal; orphans: 2; text-align: start; text-indent: 0px; text-transform: none; widows: 2; word-spacing: 0px; -webkit-text-stroke-width: 0px; white-space: normal; background-color: rgb(255, 255, 255); text-decoration-thickness: initial; text-decoration-style: initial; text-decoration-color: initial;"><span style="color:#000000;"><span style="font-size:14px;"><span style="font-family:Arial,Helvetica,sans-serif;">Função Power ON/OFF</span></span></span></p> <p style="margin: 0px 0px 10px; padding: 0px; color: rgb(102, 102, 102); font-family: Montserrat; font-size: 12px; font-style: normal; font-variant-ligatures: normal; font-variant-caps: normal; font-weight: 400; letter-spacing: normal; orphans: 2; text-align: start; text-indent: 0px; text-transform: none; widows: 2; word-spacing: 0px; -webkit-text-stroke-width: 0px; white-space: normal; background-color: rgb(255, 255, 255); text-decoration-thickness: initial; text-decoration-style: initial; text-decoration-color: initial;"><span style="color:#000000;"><span style="font-size:14px;"><span style="font-family:Arial,Helvetica,sans-serif;">Especificações Técnicas</span></span></span></p> <p style="margin: 0px 0px 10px; padding: 0px; color: rgb(102, 102, 102); font-family: Montserrat; font-size: 12px; font-style: normal; font-variant-ligatures: normal; font-variant-caps: normal; font-weight: 400; letter-spacing: normal; orphans: 2; text-align: start; text-indent: 0px; text-transform: none; widows: 2; word-spacing: 0px; -webkit-text-stroke-width: 0px; white-space: normal; background-color: rgb(255, 255, 255); text-decoration-thickness: initial; text-decoration-style: initial; text-decoration-color: initial;"><span style="color:#000000;"><span style="font-size:14px;"><span style="font-family:Arial,Helvetica,sans-serif;">Woofer de 8 polegadas com cone de policelulose (203.2mm)</span></span></span></p> <p style="margin: 0px 0px 10px; padding: 0px; color: rgb(102, 102, 102); font-family: Montserrat; font-size: 12px; font-style: normal; font-variant-ligatures: normal; font-variant-caps: normal; font-weight: 400; letter-spacing: normal; orphans: 2; text-align: start; text-indent: 0px; text-transform: none; widows: 2; word-spacing: 0px; -webkit-text-stroke-width: 0px; white-space: normal; background-color: rgb(255, 255, 255); text-decoration-thickness: initial; text-decoration-style: initial; text-decoration-color: initial;"><span style="color:#000000;"><span style="font-size:14px;"><span style="font-family:Arial,Helvetica,sans-serif;">Potência de 100W RMS</span></span></span></p> <p style="margin: 0px 0px 10px; padding: 0px; color: rgb(102, 102, 102); font-family: Montserrat; font-size: 12px; font-style: normal; font-variant-ligatures: normal; font-variant-caps: normal; font-weight: 400; letter-spacing: normal; orphans: 2; text-align: start; text-indent: 0px; text-transform: none; widows: 2; word-spacing: 0px; -webkit-text-stroke-width: 0px; white-space: normal; background-color: rgb(255, 255, 255); text-decoration-thickness: initial; text-decoration-style: initial; text-decoration-color: initial;"><span style="color:#000000;"><span style="font-size:14px;"><span style="font-family:Arial,Helvetica,sans-serif;">Resposta de frequencia de 35 Hz – 200 Hz</span></span></span></p> <p style="margin: 0px 0px 10px; padding: 0px; color: rgb(102, 102, 102); font-family: Montserrat; font-size: 12px; font-style: normal; font-variant-ligatures: normal; font-variant-caps: normal; font-weight: 400; letter-spacing: normal; orphans: 2; text-align: start; text-indent: 0px; text-transform: none; widows: 2; word-spacing: 0px; -webkit-text-stroke-width: 0px; white-space: normal; background-color: rgb(255, 255, 255); text-decoration-thickness: initial; text-decoration-style: initial; text-decoration-color: initial;"><span style="color:#000000;"><span style="font-size:14px;"><span style="font-family:Arial,Helvetica,sans-serif;">Controles de liga/desliga, entrada e volume</span></span></span></p> <p style="margin: 0px 0px 10px; padding: 0px; color: rgb(102, 102, 102); font-family: Montserrat; font-size: 12px; font-style: normal; font-variant-ligatures: normal; font-variant-caps: normal; font-weight: 400; letter-spacing: normal; orphans: 2; text-align: start; text-indent: 0px; text-transform: none; widows: 2; word-spacing: 0px; -webkit-text-stroke-width: 0px; white-space: normal; background-color: rgb(255, 255, 255); text-decoration-thickness: initial; text-decoration-style: initial; text-decoration-color: initial;"><span style="color:#000000;"><span style="font-size:14px;"><span style="font-family:Arial,Helvetica,sans-serif;">Entradas de linha tipo RCA estéreo e LFE</span></span></span></p> <p style="margin: 0px 0px 10px; padding: 0px; color: rgb(102, 102, 102); font-family: Montserrat; font-size: 12px; font-style: normal; font-variant-ligatures: normal; font-variant-caps: normal; font-weight: 400; letter-spacing: normal; orphans: 2; text-align: start; text-indent: 0px; text-transform: none; widows: 2; word-spacing: 0px; -webkit-text-stroke-width: 0px; white-space: normal; background-color: rgb(255, 255, 255); text-decoration-thickness: initial; text-decoration-style: initial; text-decoration-color: initial;"><span style="color:#000000;"><span style="font-size:14px;"><span style="font-family:Arial,Helvetica,sans-serif;">Gabinete do tipo Bass Reflex com porta sintonizada traseira</span></span></span></p> <p style="margin: 0px 0px 10px; padding: 0px; color: rgb(102, 102, 102); font-family: Montserrat; font-size: 12px; font-style: normal; font-variant-ligatures: normal; font-variant-caps: normal; font-weight: 400; letter-spacing: normal; orphans: 2; text-align: start; text-indent: 0px; text-transform: none; widows: 2; word-spacing: 0px; -webkit-text-stroke-width: 0px; white-space: normal; background-color: rgb(255, 255, 255); text-decoration-thickness: initial; text-decoration-style: initial; text-decoration-color: initial;"><span style="color:#000000;"><span style="font-size:14px;"><span style="font-family:Arial,Helvetica,sans-serif;">Bivolt Automático (AC ~100-240V, 50/ 60 Hz)</span></span></span></p> <p style="margin: 0px 0px 10px; padding: 0px; color: rgb(102, 102, 102); font-family: Montserrat; font-size: 12px; font-style: normal; font-variant-ligatures: normal; font-variant-caps: normal; font-weight: 400; letter-spacing: normal; orphans: 2; text-align: start; text-indent: 0px; text-transform: none; widows: 2; word-spacing: 0px; -webkit-text-stroke-width: 0px; white-space: normal; background-color: rgb(255, 255, 255); text-decoration-thickness: initial; text-decoration-style: initial; text-decoration-color: initial;"><span style="color:#000000;"><span style="font-size:14px;"><span style="font-family:Arial,Helvetica,sans-serif;">Consumo de energia (max): 120W</span></span></span></p> <p style="margin: 0px 0px 10px; padding: 0px; color: rgb(102, 102, 102); font-family: Montserrat; font-size: 12px; font-style: normal; font-variant-ligatures: normal; font-variant-caps: normal; font-weight: 400; letter-spacing: normal; orphans: 2; text-align: start; text-indent: 0px; text-transform: none; widows: 2; word-spacing: 0px; -webkit-text-stroke-width: 0px; white-space: normal; background-color: rgb(255, 255, 255); text-decoration-thickness: initial; text-decoration-style: initial; text-decoration-color: initial;"><span style="color:#000000;"><span style="font-size:14px;"><span style="font-family:Arial,Helvetica,sans-serif;">Dimensões (LxPxA): 300 x 300 x 342 mm</span></span></span></p> <p style="margin: 0px 0px 10px; padding: 0px; color: rgb(102, 102, 102); font-family: Montserrat; font-size: 12px; font-style: normal; font-variant-ligatures: normal; font-variant-caps: normal; font-weight: 400; letter-spacing: normal; orphans: 2; text-align: start; text-indent: 0px; text-transform: none; widows: 2; word-spacing: 0px; -webkit-text-stroke-width: 0px; white-space: normal; background-color: rgb(255, 255, 255); text-decoration-thickness: initial; text-decoration-style: initial; text-decoration-color: initial;"><span style="color:#000000;"><span style="font-size:14px;"><span style="font-family:Arial,Helvetica,sans-serif;">Peso 7.9 Kg</span></span></span></p> | T21: N | V21: 1699 | W21: 1079.9 | X21: JBL | Y21: 9 | Z21: 40 | AA21: 40 | AB21: 40 | AH21: https://cdn.awsli.com.br/948/948321/produto/257657248/sub8-7d5zosdp17.jpeg | AI21: https://cdn.awsli.com.br/948/948321/produto/257657248/sub81-mxz4ivcq3a.png | AJ21: https://cdn.awsli.com.br/948/948321/produto/257657248/sem-t-tulo-zz9265u8x3.jpg
B22: 5 | C22: S | D22: imediata | E22: indisponivel | F22: S | G22: N | H22: 328705586 | I22: variacao | J22: DMM55YWDT | K22: DMM55YWDT-branco | L22: N | T22: N | V22: 849 | W22: 769 | Y22: 2 | Z22: 35 | AA22: 35 | AB22: 35 | AN22: Branco
B23: 5 | C23: S | D23: imediata | E23: indisponivel | F23: S | G23: N | H23: 328705846 | I23: variacao | J23: DMM55YWDT | K23: DMM55YWDT-preto | L23: N | T23: N | V23: 849 | W23: 769 | Y23: 2 | Z23: 45 | AA23: 35 | AB23: 55 | AN23: Preto
B24: 5 | C24: S | D24: imediata | E24: indisponivel | F24: S | G24: N | H24: 329677208 | I24: variacao | J24: 882B3YGFW | K24: 882B3YGFW-bivolt | L24: N | T24: N | V24: 3099 | W24: 2739 | Y24: 16 | Z24: 60 | AA24: 60 | AB24: 60 | AU24: Bivolt
A25: Receiver JBL MA510 5.2ch 8k Wifi Dolby Digital e DTS | B25: 3 | C25: S | D25: imediata | E25: indisponivel | F25: S | G25: N | H25: 326613652 | I25: sem-variacao | K25: SL6AA8PBT | L25: N | R25: <p><span style="font-size:12pt; font-variant:normal; white-space:pre-wrap"><span style="font-family:Roboto,sans-serif"><span style="color:#252525"><span style="background-color:#ffffff"><span style="font-weight:400"><span style="font-style:normal"><span style="text-decoration:none">O JBL MA510 é um receiver A/V que oferece um realismo espetacular com especificações HDMI 8K para uma super experiência de cinema em casa. Integre perfeitamente sua smart TV ou projetor com 4 entradas HDMI e 1 saída, além de suporte para eARC. Com decodificação nativa de 5 canais dos formatos Dolby e DTS, o MA510 pode proporcionar experiências de cinema incríveis. Ele é projetado com paixão para música e filmes, dando vida a ambos com verdadeira alta fidelidade. Conteúdo de música adicional pode ser acessado via Bluetooth e streaming de rede. O MA510 possui cinco canais de amplificação Classe D de baixo ruído para fornecer potência real a todos os canais.</span></span></span></span></span></span></span><br /> </p> <ul> <li aria-level="1" style="list-style-type:disc"> </li> <li aria-level="1" style="list-style-type:disc"><span style="font-size:12pt; font-variant:normal; white-space:pre-wrap"><span style="font-family:Roboto,sans-serif"><span style="color:#252525"><span style="background-color:#ffffff"><span style="font-weight:400"><span style="font-style:normal"><span style="text-decoration:none">HDMI eARC: Sim</span></span></span></span></span></span></span></li> <li aria-level="1" style="list-style-type:disc"><span style="font-size:12pt; font-variant:normal; white-space:pre-wrap"><span style="font-family:Roboto,sans-serif"><span style="color:#252525"><span style="background-color:#ffffff"><span style="font-weight:400"><span style="font-style:normal"><span style="text-decoration:none">Canal de retorno de áudio HDMI: Sim</span></span></span></span></span></span></span></li> <li aria-level="1" style="list-style-type:disc"><span style="font-size:12pt; font-variant:normal; white-space:pre-wrap"><span style="font-family:Roboto,sans-serif"><span style="color:#252525"><span style="background-color:#ffffff"><span style="font-weight:400"><span style="font-style:normal"><span style="text-decoration:none">Conectores de entrada HDMI 8K (HDMI 2.1, HDCP 2.3 até 8K /60 Hz, 4K /120 Hz): 4</span></span></span></span></span></span></span></li> <li aria-level="1" style="list-style-type:disc"><span style="font-size:12pt; font-variant:normal; white-space:pre-wrap"><span style="font-family:Roboto,sans-serif"><span style="color:#252525"><span style="background-color:#ffffff"><span style="font-weight:400"><span style="font-style:normal"><span style="text-decoration:none">Recursos aprimorados de jogos HDMI 2.1: Games-VRR, ALLM, QFT, HFR (4K a 120 Hz)</span></span></span></span></span></span></span></li> <li aria-level="1" style="list-style-type:disc"><span style="font-size:12pt; font-variant:normal; white-space:pre-wrap"><span style="font-family:Roboto,sans-serif"><span style="color:#252525"><span style="background-color:#ffffff"><span style="font-weight:400"><span style="font-style:normal"><span style="text-decoration:none">HDR 10+, Dolby Vision: Sim , Sim</span></span></span></span></span></span></span></li> <li aria-level="1" style="list-style-type:disc"><span style="font-size:12pt; font-variant:normal; white-space:pre-wrap"><span style="font-family:Roboto,sans-serif"><span style="color:#252525"><span style="background-color:#ffffff"><span style="font-weight:400"><span style="font-style:normal"><span style="text-decoration:none">Formato do arquivo: MP3 / MPEG-4 AAC</span></span></span></span></span></span></span></li> <li aria-level="1" style="list-style-type:disc"><span style="font-size:12pt; font-variant:normal; white-space:pre-wrap"><span style="font-family:Roboto,sans-serif"><span style="color:#252525"><span style="background-color:#ffffff"><span style="font-weight:400"><span style="font-style:normal"><span style="text-decoration:none">Pure Direct: Sim</span></span></span></span></span></span></span></li> <li aria-level="1" style="list-style-type:disc"><span style="font-size:12pt; font-variant:normal; white-space:pre-wrap"><span style="font-family:Roboto,sans-serif"><span style="color:#252525"><span style="background-color:#ffffff"><span style="font-weight:400"><span style="font-style:normal"><span style="text-decoration:none">EZ Set EQ: Sim</span></span></span></span></span></span></span></li> <li aria-level="1" style="list-style-type:disc"><span style="font-size:12pt; font-variant:normal; white-space:pre-wrap"><span style="font-family:Roboto,sans-serif"><span style="color:#252525"><span style="background-color:#ffffff"><span style="font-weight:400"><span style="font-style:normal"><span style="text-decoration:none">Processamento de sinal digital: até 24 bits/192 kHz</span></span></span></span></span></span></span></li> <li aria-level="1" style="list-style-type:disc"><span style="font-size:12pt; font-variant:normal; white-space:pre-wrap"><span style="font-family:Roboto,sans-serif"><span style="color:#252525"><span style="background-color:#ffffff"><span style="font-weight:400"><span style="font-style:normal"><span style="text-decoration:none">Canais: 5.2</span></span></span></span></span></span></span></li> <li aria-level="1" style="list-style-type:disc"><span style="font-size:12pt; font-variant:normal; white-space:pre-wrap"><span style="font-family:Roboto,sans-serif"><span style="color:#252525"><span style="background-color:#ffffff"><span style="font-weight:400"><span style="font-style:normal"><span style="text-decoration:none">Potência nominal a 8Ω (20 Hz a 20 kHz, 2 canais acionados, máx. 0,5% de THD): 75 W RMS</span></span></span></span></span></span></span></li> <li aria-level="1" style="list-style-type:disc"><span style="font-size:12pt; font-variant:normal; white-space:pre-wrap"><span style="font-family:Roboto,sans-serif"><span style="color:#252525"><span style="background-color:#ffffff"><span style="font-weight:400"><span style="font-style:normal"><span style="text-decoration:none">Potência nominal a 4Ω (20 Hz a 20 kHz, 2 canais acionados, máx. 0,5% de THD): 100 W RMS</span></span></span></span></span></span></span></li> <li aria-level="1" style="list-style-type:disc"><span style="font-size:12pt; font-variant:normal; white-space:pre-wrap"><span style="font-family:Roboto,sans-serif"><span style="color:#252525"><span style="background-color:#ffffff"><span style="font-weight:400"><span style="font-style:normal"><span style="text-decoration:none">Dimensões, incluindo pés e terminais das caixas acústicas (A x L x P): 109,2 mm x 432,0 mm x 347,6 mm (4,3 pol. x 17,0 pol. x 13,7 pol.)</span></span></span></span></span></span></span></li> <li aria-level="1" style="list-style-type:disc"><span style="font-size:12pt; font-variant:normal; white-space:pre-wrap"><span style="font-family:Roboto,sans-serif"><span style="color:#252525"><span style="background-color:#ffffff"><span style="font-weight:400"><span style="font-style:normal"><span style="text-decoration:none">Peso: 5,4 kg (12 lb)</span></span></span></span></span></span></span></li> <li aria-level="1" style="list-style-type:disc"><span style="font-size:12pt; font-variant:normal; white-space:pre-wrap"><span style="font-family:Roboto,sans-serif"><span style="color:#252525"><span style="background-color:#ffffff"><span style="font-weight:400"><span style="font-style:normal"><span style="text-decoration:none">Entrada/saída HDMI: 4 / 1</span></span></span></span></span></span></span></li> <li aria-level="1" style="list-style-type:disc"><span style="font-size:12pt; font-variant:normal; white-space:pre-wrap"><span style="font-family:Roboto,sans-serif"><span style="color:#252525"><span style="background-color:#ffffff"><span style="font-weight:400"><span style="font-style:normal"><span style="text-decoration:none">Wi-Fi: Sim (2,4/5 GHz)</span></span></span></span></span></span></span></li> <li aria-level="1" style="list-style-type:disc"><span style="font-size:12pt; font-variant:normal; white-space:pre-wrap"><span style="font-family:Roboto,sans-serif"><span style="color:#252525"><span style="background-color:#ffffff"><span style="font-weight:400"><span style="font-style:normal"><span style="text-decoration:none">Recebimento Bluetooth: Sim (v4.1, Baixa energia)</span></span></span></span></span></span></span></li> <li aria-level="1" style="list-style-type:disc"><span style="font-size:12pt; font-variant:normal; white-space:pre-wrap"><span style="font-family:Roboto,sans-serif"><span style="color:#252525"><span style="background-color:#ffffff"><span style="font-weight:400"><span style="font-style:normal"><span style="text-decoration:none">Entradas de áudio digital: 1 coaxial, 1 óptico, 1 USB</span></span></span></span></span></span></span></li> <li aria-level="1" style="list-style-type:disc"><span style="font-size:12pt; font-variant:normal; white-space:pre-wrap"><span style="font-family:Roboto,sans-serif"><span style="color:#252525"><span style="background-color:#ffffff"><span style="font-weight:400"><span style="font-style:normal"><span style="text-decoration:none">Entrada analógica estéreo: 2 RCA de terminação simples</span></span></span></span></span></span></span></li> <li aria-level="1" style="list-style-type:disc"><span style="font-size:12pt; font-variant:normal; white-space:pre-wrap"><span style="font-family:Roboto,sans-serif"><span style="color:#252525"><span style="background-color:#ffffff"><span style="font-weight:400"><span style="font-style:normal"><span style="text-decoration:none">Saída Pré (RCA de extremidade única): Subwoofer 1, Subwoofer 2</span></span></span></span></span></span></span></li> <li aria-level="1" style="list-style-type:disc"><span style="font-size:12pt; font-variant:normal; white-space:pre-wrap"><span style="font-family:Roboto,sans-serif"><span style="color:#252525"><span style="background-color:#ffffff"><span style="font-weight:400"><span style="font-style:normal"><span style="text-decoration:none">Ethernet: RJ45 Gigabit, WiFi integrado</span></span></span></span></span></span></span></li> <li aria-level="1" style="list-style-type:disc"><span style="font-size:12pt; font-variant:normal; white-space:pre-wrap"><span style="font-family:Roboto,sans-serif"><span style="color:#252525"><span style="background-color:#ffffff"><span style="font-weight:400"><span style="font-style:normal"><span style="text-decoration:none">Tensão da rede: 110 a 240 V, 50 a 60 Hz</span></span></span></span></span></span></span></li> <li aria-level="1" style="list-style-type:disc"><span style="font-size:12pt; font-variant:normal; white-space:pre-wrap"><span style="font-family:Roboto,sans-serif"><span style="color:#252525"><span style="background-color:#ffffff"><span style="font-weight:400"><span style="font-style:normal"><span style="text-decoration:none">Consumo máximo de energia: 300W</span></span></span></span></span></span></span></li> <li aria-level="1" style="list-style-type:disc"><span style="font-size:12pt; font-variant:normal; white-space:pre-wrap"><span style="font-family:Roboto,sans-serif"><span style="color:#252525"><span style="background-color:#ffffff"><span style="font-weight:400"><span style="font-style:normal"><span style="text-decoration:none">Consumo de energia em standby: <0,5 W</span></span></span></span></span></span></span></li> </ul> <p> </p> | T25: N | V25: 4759.9 | X25: JBL | Y25: 6 | Z25: 11 | AA25: 45 | AB25: 35 | AH25: https://cdn.awsli.com.br/948/948321/produto/326613652/ls_jbl_ma510_receivers_right_facing_2_blk_d3-vnpg5qhze2.PNG | AI25: https://cdn.awsli.com.br/948/948321/produto/326613652/ls_jbl_ma510_receivers_left_facing_1_blk_hero-c5pom084ic.PNG | AJ25: https://cdn.awsli.com.br/948/948321/produto/326613652/ls_jbl_ma510_receivers_front_1_blk_d1-zcbiw0orkz.PNG | AK25: https://cdn.awsli.com.br/948/948321/produto/326613652/ls_jbl_ma510_receivers_back_2_blk_d4-biin35fhh7.PNG | AL25: https://cdn.awsli.com.br/948/948321/produto/326613652/ls_jbl_ma510_receivers_back_detail_1_blk_d7-xe32n3d2eq.PNG
B26: 2 | C26: S | D26: imediata | E26: indisponivel | F26: S | G26: N | H26: 328705050 | I26: variacao | J26: GPUMXWQBA | K26: GPUMXWQBA-branco-preto | L26: N | T26: N | V26: 820 | W26: 769 | Y26: 2 | Z26: 35 | AA26: 35 | AB26: 35 | AO26: Branco/Branco
B27: 2 | C27: S | D27: imediata | E27: indisponivel | F27: S | G27: N | H27: 328710437 | I27: variacao | J27: DMM55YWDT-ZCHYS5P41 | K27: DMM55YWDT-preto-L03TFCDXS | L27: N | T27: N | V27: 1339 | W27: 1199 | Y27: 2 | Z27: 45 | AA27: 55 | AB27: 55 | AN27: Preto
B28: 2 | C28: S | D28: imediata | E28: indisponivel | F28: S | G28: N | H28: 328710438 | I28: variacao | J28: DMM55YWDT-ZCHYS5P41 | K28: DMM55YWDT-branco-T7UNRELRQ | L28: N | T28: N | V28: 1339 | W28: 1199 | Y28: 2 | Z28: 55 | AA28: 55 | AB28: 55 | AN28: Branco
B29: 2 | C29: S | D29: imediata | E29: indisponivel | F29: S | G29: N | H29: 331336115 | I29: variacao | J29: GPUMXWQBA | K29: GPUMXWQBA-PRETO | L29: N | T29: N | V29: 820 | W29: 769 | Y29: 2 | Z29: 35 | AA29: 35 | AB29: 35 | AO29: Preto/Preto
